Workbook

Sheet GOV'T AGENCIES
E8: YOUR GROWTH OPPORTUNITY IS WITH DBP! | L8: CUSTOMIZED EVALUATION (GH & BH APPROVAL)
E9: INPUT DATA ON WHITE CELLS | I9: =NOW() -> 46084.283 | L9: 2018 GAA NTHP | M9: 5000 | P9: =DAY(EOMONTH(I9,0)) -> 31 | Q9: Month-end date | R9: LOAN EVALUATION GUIDE
G10: LOANS FOR TAKE-OUT | H10: BALANCE | I10: AMORT | L10: BPI days | M10: =$P$9-DAY(I9) -> 28 | N10: Prevailing Parameter
E11: TYPE: [1] FOR RENEWAL/RE-AVAILMENT OR [0] FOR NEW | F11: 0 | G11: LOAN 1 | H11: 0 | I11: 0 | L11: MAX AMORT: | M11: =F50 -> 2000 | N11: =IF(F49<F47,"BASED ON IGIR","BASED ON NTHP") -> BASED ON NTHP | R11: Min Loan Amount to Pay-off Everything | S11: =(F14+H15)/0.97947 -> 0 | U11: NET PROCEEDS | V11: =S11-H15-F14-W47 -> -6304
E12: GROSS SALARY | G12: LOAN 2 | N12: Net Proceeds
E13: NET SALARY (OR NET TAKE HOME PAY) | G13: LOAN 3 | H13: 0 | I13: 0 | L13: LOAN AMOUNT | M13: 150000 | N13: =M13-F14-H15-W47 -> 143696 | R13: ORIGINAL EFFECTIVE NTHP | S13: ='NEW BORROWER'!C5 -> 8000
E14: OUTSTANDING BALANCE OF EXISTING DBP LOAN | F14: 0 | G14: LOAN 4 | H14: 0 | I14: 0 | L14: TERM | M14: AMORT/MO | N14: Remarks | R14: TERM | S14: AMORT/MO | T14: IGIR RATIO | U14: NTHP | V14: INC / DEC IN NTHP
E15: MONTHLY AMORTIZATION OF EXISTING DBP LOAN | F15: 0 | G15: TOTAL | H15: =SUM(H11:H14) -> 0 | I15: =SUM(I11:I14) -> 0 | L15: 4 YRS | M15: =IF('NEW BORROWER'!B11=0,0,-PMT('NEW BORROWER'!B10/12,48,M13)) -> 0 | N15: =IF('NEW BORROWER'!B11=0,"N.A.",IF(M15>$M$11,"CANNOT BE","OK")) -> N.A. | R15: 4 YRS | S15: =-PMT('NEW BORROWER'!B10/12,48,M13) -> 4174.6122 | T15: =S15/'NEW BORROWER'!$C$3 -> 0.27830748 | U15: ='NEW BORROWER'!$C$5+$I$15+$F$15-S15 -> 3825.3878 | V15: =U15-S13 -> -4174.6122
L16: 3 YRS | M16: =-PMT('NEW BORROWER'!C10/12,36,M13) -> 4982.1465 | N16: =IF(M16>$M$11,"CANNOT BE","OK") -> CANNOT BE | R16: 3 YRS | S16: =-PMT('NEW BORROWER'!C10/12,36,M13) -> 4982.1465 | T16: =S16/'NEW BORROWER'!$C$3 -> 0.3321431 | U16: ='NEW BORROWER'!$C$5+$I$15+$F$15-S16 -> 3017.8535 | V16: =U16-('NEW BORROWER'!$C$5-$I$15) -> -4982.1465
F17: NEW | L17: 2 YRS | M17: =-PMT('NEW BORROWER'!D10/12,24,M13) -> 7061.0208 | N17: =IF(M17>$M$11,"CANNOT BE","OK") -> CANNOT BE
L18: 1 YR | M18: =-PMT('NEW BORROWER'!E10/12,12,M13) -> 13327.318 | N18: =IF(M18>$M$11,"CANNOT BE","OK") -> CANNOT BE | R18: 2 YRS | S18: =-PMT('NEW BORROWER'!D10/12,24,M13) -> 7061.0208 | T18: =S18/'NEW BORROWER'!$C$3 -> 0.47073472 | U18: ='NEW BORROWER'!$C$5+$I$15+$F$15-S18 -> 938.97917 | V18: =U18-('NEW BORROWER'!$C$5-$I$15) -> -7061.0208
R19: 1 YR | S19: =-PMT('NEW BORROWER'!E10/12,12,M13) -> 13327.318 | T19: =S19/'NEW BORROWER'!$C$3 -> 0.88848789 | U19: ='NEW BORROWER'!$C$5+$I$15+$F$15-S19 -> -5327.3183 | V19: =U19-('NEW BORROWER'!$C$5-$I$15) -> -13327.318
L21: AMORT/MO | M21: 6500 | N21: =IF(M21>M11,"CANNOT BE","OK") -> CANNOT BE
L22: TERM | M22: AMOUNT | N22: Net Proceeds
L23: 4 YRS | M23: =IF('NEW BORROWER'!B11=0,0,-PV('NEW BORROWER'!B10/12,48,M21)) -> 0 | N23: =M23-$F$14-$H$15-W37 -> 0
L24: 3 YRS | M24: =-PV('NEW BORROWER'!C10/12,36,M21) -> 195698.78 | N24: =M24-$F$14-$H$15-W38 -> 189344.8
F25: RENEWAL/REAVAILMENT | L25: 2 YRS | M25: =-PV('NEW BORROWER'!D10/12,24,M21) -> 138082.02 | N25: =M25-$F$14-$H$15-W39 -> 133859.01
E26: TERM | F26: 4 YRS | G26: 3 YRS | H26: 2 YRS | I26: 1 YR | L26: 1 YR | M26: =-PV('NEW BORROWER'!E10/12,12,M21) -> 73158.004 | N26: =M26-$F$14-$H$15-W40 -> 71097.63
E27: INTEREST RATE (PER ANNUM) | F27: 0.1 | G27: 0.08 | H27: 0.08 | I27: 0.08
E28: MAXIMUM LOANABLE AMOUNT | F28: =IF(F61<48,0,ROUNDDOWN(-PV(F27/12,48,F60),-3)) -> 0 | G28: =ROUNDDOWN(-PV(G27/12,36,F60),-3) -> 95000 | H28: =ROUNDDOWN(-PV(H27/12,24,F60),-3) -> 66000 | I28: =ROUNDDOWN(-PV(I27/12,12,F60),-3) -> 34000
E29: MONTHLY AMORTIZATION | F29: =-PMT(F27/12,48,F28) -> 0 | G29: =-PMT(G27/12,36,G28) -> 2976.9547 | H29: =-PMT(H27/12,24,H28) -> 2985.0012 | I29: =-PMT(I27/12,12,I28) -> 2957.6066
E30: ESTIMATED NET PROCEEDS | F30: =F28-F14-F41-H15 -> 0 | G30: =G28-F14-G41-H15 -> 92911.8 | H30: =H28-F14-H41-H15 -> 64715.5 | I30: =I28-F14-I41-H15 -> 33380.407
E31: NET TAKE HOME PAY | F31: ='NEW BORROWER'!$C$5-F29+$F$15+$I$15 -> 8000 | G31: ='NEW BORROWER'!$C$5-G29+$F$15+$I$15 -> 5023.0453 | H31: ='NEW BORROWER'!$C$5-H29+$F$15+$I$15 -> 5014.9988 | I31: ='NEW BORROWER'!$C$5-I29+$F$15+$I$15 -> 5042.3934
E33: THANK YOU FOR BANKING WITH DBP!
I34: COPY RIGHTS: DBP Cebu & Catbalogan Branches
E35: COMPUTATIONS | S35: SCHEDULE OF FEES - BASED ON DESIRED LOAN AMORT
N36: =N13/M13 -> 0.95797333 | S36: SF | T36: DST | U36: MRI | V36: BPI | W36: TOTAL
E37: SERVICE FEE | F37: =IF('NEW BORROWER'!B11*1%<1500,'NEW BORROWER'!B11*1%,1500) -> 0 | G37: =IF('NEW BORROWER'!C11*1%<1500,'NEW BORROWER'!C11*1%,1500) -> 600 | H37: =IF('NEW BORROWER'!D11*1%<1500,'NEW BORROWER'!D11*1%,1500) -> 420 | I37: =IF('NEW BORROWER'!E11*1%<1500,'NEW BORROWER'!E11*1%,1500) -> 220 | R37: 4 | S37: =IF(M23*1%<1500,M23*1%,1500) -> 0 | T37: =IF(M23<250000,0,M23/200) -> 0 | U37: =(M23/1000)*G100 -> 0 | V37: =M23*$M$10*'NEW BORROWER'!B10/360 -> 0 | W37: =SUM(S37:V37) -> 0
E38: DOC STAMPS | F38: =IF('NEW BORROWER'!B11<250000,0,'NEW BORROWER'!B11*1.5/200) -> 0 | G38: =IF('NEW BORROWER'!C11<250000,0,'NEW BORROWER'!C11*1.5/200) -> 0 | H38: =IF('NEW BORROWER'!D11<250000,0,'NEW BORROWER'!D11*1.5/200) -> 0 | I38: =IF('NEW BORROWER'!E11<250000,0,'NEW BORROWER'!E11*1.5/200) -> 0 | R38: 3 | S38: =IF(M24*1%<1500,M24*1%,1500) -> 1500 | T38: =IF(M24<250000,0,M24/200) -> 0 | U38: =(M24/1000)*G99 -> 3027.4602 | V38: =M24*$M$10*'NEW BORROWER'!C10/360 -> 1826.522 | W38: =SUM(S38:V38) -> 6353.9821
E39: Max Broken Period Interest | F39: ='NEW BORROWER'!B11*'NEW BORROWER'!B10*$M$10/360 -> 0 | G39: ='NEW BORROWER'!C11*'NEW BORROWER'!C10*$M$10/360 -> 560 | H39: ='NEW BORROWER'!D11*'NEW BORROWER'!D10*$M$10/360 -> 392 | I39: ='NEW BORROWER'!E11*'NEW BORROWER'!E10*$M$10/360 -> 205.33333 | R39: 2 | S39: =IF(M25*1%<1500,M25*1%,1500) -> 1380.8202 | T39: =IF(M25<250000,0,M25/200) -> 0 | U39: =(M25/1000)*G98 -> 1553.4227 | V39: =M25*$M$10*'NEW BORROWER'!D10/360 -> 1288.7655 | W39: =SUM(S39:V39) -> 4223.0084
E40: MRI | F40: =('NEW BORROWER'!B11/1000)*G100 -> 0 | G40: ='NEW BORROWER'!C11*G99/1000 -> 928.2 | H40: ='NEW BORROWER'!D11*G98/1000 -> 472.5 | I40: ='NEW BORROWER'!E11*G97/1000 -> 194.26 | R40: 1 | S40: =IF(M26*1%<1500,M26*1%,1500) -> 731.58004 | T40: =IF(M26<250000,0,M26/200) -> 0 | U40: =(M26/1000)*G97 -> 645.98517 | V40: =M26*$M$10*'NEW BORROWER'!E10/360 -> 682.80803 | W40: =SUM(S40:V40) -> 2060.3732
E41: TOTAL FEES/CHARGES | F41: =SUM(F37:F40) -> 0 | G41: =SUM(G37:G40) -> 2088.2 | H41: =SUM(H37:H40) -> 1284.5 | I41: =SUM(I37:I40) -> 619.59333
S42: SCHEDULE OF FEES BASED ON DESIRED LOAN AMOUNT
E43: COMPUTATIONS FOR LOANABLE AMOUNT PARAMETERS - GROUP HEAD AND BH AUTHORITY
E45: NTHP ADD DBP LOAN AND OTHER LOANS | F45: ='NEW BORROWER'!C5+F15+I15 -> 8000 | S45: SF | T45: DST | U45: MRI | V45: BPI | W45: TOTAL
E46: NTHP COMPUTATION TO PER NTHP TABLE | F46: =IF(F11>0,M9,IF('NEW BORROWER'!C3<18000,H68,IF('NEW BORROWER'!C3<38000,H69,H70))) -> 6000
E47: NTHP LESS GAA REQ | F47: =F45-F46 -> 2000 | S47: =IF(M13*1%<1500,M37*1%,1500) -> 1500 | T47: =IF(M13<250000,0,M13/200) -> 0 | U47: =(M13/1000)*G100 -> 3054 | V47: =M13*$M$10*'NEW BORROWER'!B10/360 -> 1750 | W47: =SUM(S47:V47) -> 6304
E48: IGIR TO USE | F48: =IF(F11>0,IF('NEW BORROWER'!C3<10000,20%,IF('NEW BORROWER'!C3<13000,30%,IF('NEW BORROWER'!C3<38000,35%,40%))),IF('NEW BORROWER'!C3<10000,10%,IF('NEW BORROWER'!C3<13000,25%,30%))) -> 0.3
E49: LOAN INSTALLMENT (LI) | F49: =F48*'NEW BORROWER'!C3 -> 4500
E50: INSTALLMENT TO USE | F50: =IF(F47<F49,F47,F49) -> 2000
E51: MAX ALLOWABLE TERM OF LOAN | F51: =IF(F11>0,I73,IF('NEW BORROWER'!C3<18000,36,48)) -> 36 | G51: Months
E53: COMPUTATIONS FOR LOANABLE AMOUNT PARAMETERS - SECTOR HEAD AUTHORITY
E55: NTHP ADD DBP LOAN AND OTHER LOANS | F55: ='NEW BORROWER'!C5+F15+I15 -> 8000
E56: NTHP COMPUTATION TO PER NTHP TABLE | F56: =M9 -> 5000
E57: NTHP LESS GAA REQ | F57: =F55-F56 -> 3000
E58: IGIR TO USE | F58: =IF(F11>0,IF('NEW BORROWER'!C3<10000,40%,IF('NEW BORROWER'!C3<13000,50%,IF('NEW BORROWER'!C3<38000,60%,70%))),IF('NEW BORROWER'!C3<10000,30%,IF('NEW BORROWER'!C3<13000,40%,IF('NEW BORROWER'!C3<38000,50%,60%)))) -> 0.5
E59: LOAN INSTALLMENT (LI) | F59: =F58*'NEW BORROWER'!C3 -> 7500
E60: INSTALLMENT TO USE | F60: =IF(F57<F59,F57,F59) -> 3000
E61: MAX ALLOWABLE TERM OF LOAN | F61: =IF(F11>0,I73,IF('NEW BORROWER'!C3<18000,36,48)) -> 36 | G61: Months
F63: Group Head and BH Approval | I63: TERM
F65: IGIR TABLE - NEW | H65: NTHP - NEW | I65: NEW
F66: Less than 10K | G66: 0.1 | H66: 6000 | I66: 36
F67: From 10K to <13K | G67: 0.25 | H67: 6000 | I67: 36
F68: From 13K to <18K | G68: 0.3 | H68: 6000 | I68: 36
F69: From 18K to <38K | G69: 0.3 | H69: 7000 | I69: 48
F70: From 38K and above | G70: 0.3 | H70: 8000 | I70: 48
F72: IGIR TABLE - RENEWAL | H72: NTHP-RENEWAL | I72: TERM-RENEWAL
F73: Less than 10K | G73: 0.2 | H73: 6000 | I73: 48
F74: From 10K to <13K | G74: 0.3 | H74: 6000 | I74: 48
F75: From 13K to <18K | G75: 0.35 | H75: 6000 | I75: 48
F76: From 18K to <38K | G76: 0.35 | H76: 7000 | I76: 48
F77: From 38K and above | G77: 0.4 | H77: 8000 | I77: 48
F79: SECTOR HEAD APPROVAL
F81: IGIR TABLE - NEW | H81: NTHP- NEW
F82: Less than 10K | G82: 0.3 | H82: 5000
F83: From 10K to <13K | G83: 0.4 | H83: 5000
F84: From 13K to <18K | G84: 0.5 | H84: 5000
F85: From 18K to <38K | G85: 0.5 | H85: 5000
F86: From 38K and above | G86: 0.6 | H86: 5000
F88: IGIR TABLE - RENEWAL
F89: Less than 10K | G89: 0.4
F90: From 10K to <13K | G90: 0.5
F91: From 13K to <18K | G91: 0.6
F92: From 18K to <38K | G92: 0.6
F93: From 38K and above | G93: 0.7
F96: MRI TARIFF (per 1000.00)
F97: 12 MOS | G97: 8.83
F98: 24 MOS | G98: 11.25
F99: 36 MOS | G99: 15.47
F100: 48 MOS | G100: 20.36

Sheet NEW BORROWER
A1: LOAN CALCULATOR FOR NEW BORROWER
A3: Gross Salary for Latest Month (Basic and PERA only): P | C3: 15000
A5: Net Pay for the Latest Month: P | C5: 8000
A9: TERM IN YEARS: | B9: 4 YRS | C9: 3 YRS | D9: 2 YRS | E9: 1 YR
A10: INTEREST RATE PER ANNUM: | B10: 0.15 | C10: 0.12 | D10: 0.12 | E10: 0.12
A11: MAXIMUM LOAN AMOUNT: | B11: =IF('GOV''T AGENCIES'!F51<48,0,ROUNDDOWN(-PV(B10/12,48,'GOV''T AGENCIES'!F50),-3)) -> 0 | C11: =ROUNDDOWN(-PV(C10/12,36,'GOV''T AGENCIES'!F50),-3) -> 60000 | D11: =ROUNDDOWN(-PV(D10/12,24,'GOV''T AGENCIES'!F50),-3) -> 42000 | E11: =ROUNDDOWN(-PV(E10/12,12,'GOV''T AGENCIES'!F50),-3) -> 22000
A12: MONTHLY AMORTIZATION: | B12: =-PMT(B10/12,48,B11) -> 0 | C12: =-PMT(C10/12,36,C11) -> 1992.8586 | D12: =-PMT(D10/12,24,D11) -> 1977.0858 | E12: =-PMT(E10/12,12,E11) -> 1954.6734
A13: ESTIMATED NET PROCEEDS: | B13: =B11-'GOV''T AGENCIES'!F14-'GOV''T AGENCIES'!F41-'GOV''T AGENCIES'!H15 -> 0 | C13: =C11-'GOV''T AGENCIES'!F14-'GOV''T AGENCIES'!G41-'GOV''T AGENCIES'!H15 -> 57911.8 | D13: =D11-'GOV''T AGENCIES'!F14-'GOV''T AGENCIES'!H41-'GOV''T AGENCIES'!H15 -> 40715.5 | E13: =E11-'GOV''T AGENCIES'!F14-'GOV''T AGENCIES'!I41-'GOV''T AGENCIES'!H15 -> 21380.407

Sheet DAR
E8: YOUR FINANCING OPPORTUNITY WITH DBP
E9: INPUT DATA ON WHITE CELLS | N9: Prevailing Factor
G10: LOANS FOR TAKE-OUT | H10: BALANCE | I10: AMORT | L10: MAX AMORT: | M10: =F37 -> 20000 | N10: =IF(F36<F34,"BASED ON IGIR","BASED ON NTHP") -> BASED ON IGIR
E11: TYPE: [1] FOR RENEWAL/RE-AVAILMENT OR [0] FOR NEW | F11: 1 | G11: LOAN 1 | H11: 40000 | I11: 3000 | N11: Net Proceeds
E12: GROSS SALARY | F12: 50000 | G12: LOAN 2 | H12: 50000 | I12: 2000 | L12: LOAN AMOUNT | M12: 759400 | N12: =(0.97912334*M12-F14)-H15 -> 593546.26
E13: NET SALARY (OR NET TAKE HOME PAY) | F13: 30000 | G13: LOAN 3 | H13: 30000 | I13: 3000 | L13: TERM | M13: AMORT/MO | N13: Remarks
E14: OUTSTANDING BALANCE OF EXISTING DBP LOAN | F14: 0 | G14: LOAN 4 | H14: 30000 | I14: 2000 | L14: 4 YRS | M14: =-PMT(F18/12,48,M12) -> 19997.915 | N14: =IF(M14>$M$10,"CANNOT BE","OK") -> OK
E15: MONTHLY AMORTIZATION OF EXISTING DBP LOAN | F15: 0 | G15: TOTAL | H15: =SUM(H11:H14) -> 150000 | I15: =SUM(I11:I14) -> 10000 | L15: 3 YRS | M15: =-PMT(G18/12,36,M12) -> 24503.702 | N15: =IF(M15>$M$10,"CANNOT BE","OK") -> CANNOT BE
L16: 2 YRS | M16: =-PMT(H18/12,24,M12) -> 35042.457 | N16: =IF(M16>$M$10,"CANNOT BE","OK") -> CANNOT BE
E17: TERM | F17: 4 YRS | G17: 3 YRS | H17: 2 YRS | I17: 1 YR | L17: 1 YR | M17: =-PMT(I18/12,12,M12) -> 66763.325 | N17: =IF(M17>$M$10,"CANNOT BE","OK") -> CANNOT BE
E18: INTEREST RATE (PER ANNUM) | F18: 0.12 | G18: 0.1 | H18: 0.1 | I18: 0.1
E19: MAXIMUM LOANABLE AMOUNT | F19: =ROUNDDOWN(-PV(F18/12,48,F37),-2) -> 759400 | G19: =ROUNDDOWN(-PV(G18/12,36,F37),-2) -> 619800 | H19: =ROUNDDOWN(-PV(H18/12,24,F37),-2) -> 433400 | I19: =ROUNDDOWN(-PV(I18/12,12,F37),-2) -> 227400 | L19: AMORT/MO | M19: 19997.91 | N19: =IF(M19>M10,"CANNOT BE","OK") -> OK
E20: MONTHLY AMORTIZATION | F20: =-PMT(F18/12,48,F19) -> 19997.915 | G20: =-PMT(G18/12,36,G19) -> 19999.203 | H20: =-PMT(H18/12,24,H19) -> 19999.211 | I20: =-PMT(I18/12,12,I19) -> 19992.073 | L20: TERM | M20: AMOUNT | N20: Net Proceeds
E21: ESTIMATED NET PROCEEDS | F21: =F19-F14-F31-H15 -> 595066.14 | G21: =G19-F14-G31-H15 -> 459598.01 | H21: =H19-F14-H31-H15 -> 276881.23 | I21: =I19-F14-I31-H15 -> 74683.41 | L21: 4 YRS | M21: =-PV(F18/12,48,M19) -> 759399.82 | N21: =(M21*0.97912334)-$F$14-H15 -> 593546.09
E22: NET TAKE HOME PAY | F22: =$F$13-F20+$F$15+$I$15 -> 20002.085 | G22: =$F$13-G20+$F$15+I15 -> 20000.797 | H22: =$F$13-H20+$F$15+I15 -> 20000.789 | I22: =$F$13-I20+$F$15+I15 -> 20007.927 | L22: 3 YRS | M22: =-PV(G18/12,36,M19) -> 619759.94 | N22: =(M22*0.97912334)-$F$14-H15 -> 456821.42
L23: 2 YRS | M23: =-PV(H18/12,24,M19) -> 433371.8 | N23: =(M23*0.97912334)-$F$14-H15 -> 274324.45
E24: THANK YOU FOR BANKING WITH DBP! | L24: 1 YR | M24: =-PV(I18/12,12,M19) -> 227466.4 | N24: =(M24*0.97912334)-$F$14-H15 -> 72717.657
I25: COPY RIGHTS: DBP CATBALOGAN
E26: COMPUTATIONS
E28: SERVICE FEE | F28: =IF(F19*1%<1500,F19*1%,1500) -> 1500 | G28: =IF(G19*1%<1500,G19*1%,1500) -> 1500 | H28: =IF(H19*1%<1500,H19*1%,1500) -> 1500 | I28: =IF(I19*1%<1500,I19*1%,1500) -> 1500
E29: DOC STAMPS | F29: =IF(F19<250000,0,F19/200) -> 3797 | G29: =IF(G19<250000,0,G19/200) -> 3099 | H29: =IF(H19<250000,0,H19/200) -> 2167 | I29: =IF(I19<250000,0,I19/200) -> 0
E30: MRI | F30: =(F19/1000)*G60 -> 9036.86 | G30: =G19*G59/1000 -> 5602.992 | H30: =H19*6.58/1000 -> 2851.772 | I30: =I19*G57/1000 -> 1216.59
E31: TOTAL FEES/CHARGES | F31: =SUM(F28:F30) -> 14333.86 | G31: =SUM(G28:G30) -> 10201.992 | H31: =SUM(H28:H30) -> 6518.772 | I31: =SUM(I28:I30) -> 2716.59
E33: NTHP ADD DBP LOAN AND OTHER LOANS | F33: =F13+F15+I15 -> 40000
E34: NTHP LESS 3.5K GAA | F34: =F33-3500 -> 36500
E35: IGIR | F35: =IF(F11>0,IF(F12<10000,20%,IF(F12<13000,30%,IF(F12<38000,35%,40%))),IF(F12<10000,10%,IF(F12<13000,25%,30%))) -> 0.4
E36: LOAN INSTALLMENT (LI) | F36: =F35*F12 -> 20000
E37: INSTALLMENT TO USE | F37: =IF(F34<F36,F34,F36) -> 20000
F41: IGIR TABLE - NEW
F42: Less than 10K | G42: 0.1
F43: From 10K to <13K | G43: 0.25
F44: From 13K to <18K | G44: 0.3
F45: From 18K to <38K | G45: 0.3
F46: From 38K and above | G46: 0.3
F48: IGIR TABLE - RENEWAL
F49: Less than 10K | G49: 0.2
F50: From 10K to <13K | G50: 0.3
F51: From 13K to <18K | G51: 0.35
F52: From 18K to <38K | G52: 0.35
F53: From 38K and above | G53: 0.4
F56: MRI TARIFF (per 1000.00)
F57: 12 MOS | G57: 5.35
F58: 24 MOS | G58: 6.58
F59: 36 MOS | G59: 9.04
F60: 48 MOS | G60: 11.9

Sheet GOV'T AGENCIES (2)
E8: YOUR FINANCING OPPORTUNITY WITH DBP
E9: INPUT DATA ON WHITE CELLS | I9: =NOW() -> 46084.283 | L9: GAA NTHP | M9: 4000 | P9: =DAY(EOMONTH(I9,0)) -> 31 | Q9: Month-end date | R9: LOAN EVALUATION GUIDE
G10: LOANS FOR TAKE-OUT | H10: BALANCE | I10: AMORT | L10: BPI days | M10: =$P$9-DAY(I9) -> 28 | N10: Prevailing Factor
E11: TYPE: [1] FOR RENEWAL/RE-AVAILMENT OR [0] FOR NEW | F11: 1 | G11: LOAN 1 | H11: 0 | I11: 3000 | L11: MAX AMORT: | M11: =F38 -> 20000 | N11: =IF(F37<F35,"BASED ON IGIR","BASED ON NTHP") -> BASED ON IGIR | R11: Min Loan Amount to Pay-off Everything | S11: =H15+F14+F32 -> 421421.59
E12: GROSS SALARY | F12: 50000 | G12: LOAN 2 | H12: 0 | I12: 0 | N12: Net Proceeds
E13: NET SALARY (OR NET TAKE HOME PAY) | F13: 20000 | G13: LOAN 3 | H13: 0 | I13: 0 | L13: LOAN AMOUNT | M13: 414334 | N13: =M13-F14-H15-F32 -> -7087.5933 | R13: ORIGINAL EFFECTIVE NTHP | S13: =F13-I15 -> 17000
E14: OUTSTANDING BALANCE OF EXISTING DBP LOAN | F14: 400000 | G14: LOAN 4 | H14: 0 | I14: 0 | L14: TERM | M14: AMORT/MO | N14: Remarks | R14: TERM | S14: AMORT/MO | T14: IGIR RATIO | U14: NTHP | V14: INC / DEC IN NTHP
E15: MONTHLY AMORTIZATION OF EXISTING DBP LOAN | F15: 17000 | G15: TOTAL | H15: =SUM(H11:H14) -> 0 | I15: =SUM(I11:I14) -> 3000 | L15: 4 YRS | M15: =-PMT(F18/12,48,M13) -> 10911.003 | N15: =IF(M15>$M$11,"CANNOT BE","OK") -> OK | R15: 4 YRS | S15: =-PMT(F18/12,48,M13) -> 10911.003 | T15: =S15/$F$12 -> 0.21822007 | U15: =$F$13+$I$15+$F$15-S15 -> 29088.997 | V15: =U15-($F$13-$I$15) -> 12088.997
L16: 3 YRS | M16: =-PMT(G18/12,36,M13) -> 13369.393 | N16: =IF(M16>$M$11,"CANNOT BE","OK") -> OK | R16: 3 YRS | S16: =-PMT(G18/12,36,M13) -> 13369.393 | T16: =S16/$F$12 -> 0.26738785 | U16: =$F$13+$I$15+$F$15-S16 -> 26630.607 | V16: =U16-($F$13-$I$15) -> 9630.6073
E17: TERM | F17: 4 YRS | G17: 3 YRS | H17: 2 YRS | I17: 1 YR | L17: 2 YRS | M17: =-PMT(H18/12,24,M13) -> 19119.412 | N17: =IF(M17>$M$11,"CANNOT BE","OK") -> OK | R17: 2 YRS | S17: =-PMT(H18/12,24,M13) -> 19119.412 | T17: =S17/$F$12 -> 0.38238824 | U17: =$F$13+$I$15+$F$15-S17 -> 20880.588 | V17: =U17-($F$13-$I$15) -> 3880.5881
E18: INTEREST RATE (PER ANNUM) | F18: 0.12 | G18: 0.1 | H18: 0.1 | I18: 0.1 | L18: 1 YR | M18: =-PMT(I18/12,12,M13) -> 36426.541 | N18: =IF(M18>$M$11,"CANNOT BE","OK") -> CANNOT BE | R18: 1 YR | S18: =-PMT(I18/12,12,M13) -> 36426.541 | T18: =S18/$F$12 -> 0.72853082 | U18: =$F$13+$I$15+$F$15-S18 -> 3573.4588 | V18: =U18-($F$13-$I$15) -> -13426.541
E19: MAXIMUM LOANABLE AMOUNT | F19: =ROUNDDOWN(-PV(F18/12,48,F38),-2) -> 759400 | G19: =ROUNDDOWN(-PV(G18/12,36,F38),-2) -> 619800 | H19: =ROUNDDOWN(-PV(H18/12,24,F38),-2) -> 433400 | I19: =ROUNDDOWN(-PV(I18/12,12,F38),-2) -> 227400
E20: MONTHLY AMORTIZATION | F20: =-PMT(F18/12,48,F19) -> 19997.915 | G20: =-PMT(G18/12,36,G19) -> 19999.203 | H20: =-PMT(H18/12,24,H19) -> 19999.211 | I20: =-PMT(I18/12,12,I19) -> 19992.073 | L20: AMORT/MO | M20: 19999.18 | N20: =IF(M20>M11,"CANNOT BE","OK") -> OK
E21: ESTIMATED NET PROCEEDS | F21: =F19-F14-F32-H15 -> 337978.41 | G21: =G19-F14-G32-H15 -> 204777.34 | H21: =H19-F14-H32-H15 -> 23510.339 | I21: =I19-F14-I32-H15 -> -177085.26 | L21: TERM | M21: AMOUNT | N21: Net Proceeds
E22: NET TAKE HOME PAY | F22: =$F$13-F20+$F$15+$I$15 -> 20002.085 | G22: =$F$13-G20+$F$15+I15 -> 20000.797 | H22: =$F$13-H20+$F$15+I15 -> 20000.789 | I22: =$F$13-I20+$F$15+I15 -> 20007.927 | L22: 4 YRS | M22: =-PV(F18/12,48,M20) -> 759448.05 | N22: =M22-$F$14-$H$15-F32 -> 338026.46
L23: 3 YRS | M23: =-PV(G18/12,36,M20) -> 619799.3 | N23: =M23-F14-H15-G32 -> 204776.64
E24: THANK YOU FOR BANKING WITH DBP! | L24: 2 YRS | M24: =-PV(H18/12,24,M20) -> 433399.33 | N24: =M24-F14-H15-H32 -> 23509.666
I25: COPY RIGHTS: DBP CATBALOGAN | L25: 1 YR | M25: =-PV(I18/12,12,M20) -> 227480.84 | N25: =M25-F14-H15-I32 -> -177004.42
E26: COMPUTATIONS
E28: SERVICE FEE | F28: =IF(F19*1%<1500,F19*1%,1500) -> 1500 | G28: =IF(G19*1%<1500,G19*1%,1500) -> 1500 | H28: =IF(H19*1%<1500,H19*1%,1500) -> 1500 | I28: =IF(I19*1%<1500,I19*1%,1500) -> 1500
E29: DOC STAMPS | F29: =IF(F19<250000,0,F19/200) -> 3797 | G29: =IF(G19<250000,0,G19/200) -> 3099 | H29: =IF(H19<250000,0,H19/200) -> 2167 | I29: =IF(I19<250000,0,I19/200) -> 0
E30: Max Broken Period Interest | F30: =F19*F18*$M$10/360 -> 7087.7333 | G30: =G19*G18*$M$10/360 -> 4820.6667 | H30: =H19*H18*$M$10/360 -> 3370.8889 | I30: =I19*I18*$M$10/360 -> 1768.6667
E31: MRI | F31: =(F19/1000)*G61 -> 9036.86 | G31: =G19*G60/1000 -> 5602.992 | H31: =H19*6.58/1000 -> 2851.772 | I31: =I19*G58/1000 -> 1216.59
E32: TOTAL FEES/CHARGES | F32: =SUM(F28:F31) -> 21421.593 | G32: =SUM(G28:G31) -> 15022.659 | H32: =SUM(H28:H31) -> 9889.6609 | I32: =SUM(I28:I31) -> 4485.2567
E34: NTHP ADD DBP LOAN AND OTHER LOANS | F34: =F13+F15+I15 -> 40000
E35: NTHP LESS GAA REQ | F35: =F34-$M$9 -> 36000
E36: IGIR | F36: =IF(F11>0,IF(F12<10000,20%,IF(F12<13000,30%,IF(F12<38000,35%,40%))),IF(F12<10000,10%,IF(F12<13000,25%,30%))) -> 0.4
E37: LOAN INSTALLMENT (LI) | F37: =F36*F12 -> 20000
E38: INSTALLMENT TO USE | F38: =IF(F35<F37,F35,F37) -> 20000
F42: IGIR TABLE - NEW
F43: Less than 10K | G43: 0.1
F44: From 10K to <13K | G44: 0.25
F45: From 13K to <18K | G45: 0.3
F46: From 18K to <38K | G46: 0.3
F47: From 38K and above | G47: 0.3
F49: IGIR TABLE - RENEWAL
F50: Less than 10K | G50: 0.2
F51: From 10K to <13K | G51: 0.3
F52: From 13K to <18K | G52: 0.35
F53: From 18K to <38K | G53: 0.35
F54: From 38K and above | G54: 0.4
F57: MRI TARIFF (per 1000.00)
F58: 12 MOS | G58: 5.35
F59: 24 MOS | G59: 6.58
F60: 36 MOS | G60: 9.04
F61: 48 MOS | G61: 11.9

Sheet WITH LOAN-TAKE-OUT
E8: HOW MUCH IS YOUR LOANABLE AMOUNT?
E9: INPUT DATA ON WHITE CELLS | N9: Prevailing Factor
G10: LOANS FOR TAKE-OUT | H10: BALANCE | I10: AMORT | L10: MAX AMORT: | M10: =F37 -> 20000 | N10: =IF(F36<F34,"BASED ON IGIR","BASED ON NTHP") -> BASED ON IGIR
E11: TYPE: [1] FOR RENEWAL/RE-AVAILMENT OR [0] FOR NEW | F11: 1 | G11: LOAN 1 | H11: 40000 | I11: 3000 | N11: Net Proceeds
E12: GROSS SALARY | F12: 50000 | G12: LOAN 2 | H12: 50000 | I12: 2000 | L12: LOAN AMOUNT | M12: 300000 | N12: =(0.97912334*M12-F14)-H15 -> 143737
E13: NET SALARY (OR NET TAKE HOME PAY) | F13: 30000 | G13: LOAN 3 | H13: 30000 | I13: 3000 | L13: TERM | M13: AMORT/MO | N13: Remarks
E14: OUTSTANDING BALANCE OF EXISTING DBP LOAN | F14: 0 | G14: LOAN 4 | H14: 30000 | I14: 2000 | L14: 4 YRS | M14: =-PMT(F18/12,48,M12) -> 8349.2245 | N14: =IF(M14>$M$10,"CANNOT BE","OK") -> OK
E15: MONTHLY AMORTIZATION OF EXISTING DBP LOAN | F15: 0 | G15: TOTAL | H15: =SUM(H11:H14) -> 150000 | I15: =SUM(I11:I14) -> 10000 | L15: 3 YRS | M15: =-PMT(G18/12,36,M12) -> 9964.2929 | N15: =IF(M15>$M$10,"CANNOT BE","OK") -> OK
L16: 2 YRS | M16: =-PMT(H18/12,24,M12) -> 14122.042 | N16: =IF(M16>$M$10,"CANNOT BE","OK") -> OK
E17: TERM | F17: 4 YRS | G17: 3 YRS | H17: 2 YRS | I17: 1 YR | L17: 1 YR | M17: =-PMT(I18/12,12,M12) -> 26654.637 | N17: =IF(M17>$M$10,"CANNOT BE","OK") -> CANNOT BE
E18: INTEREST RATE (PER ANNUM) | F18: 0.15 | G18: 0.12 | H18: 0.12 | I18: 0.12
E19: MAXIMUM LOANABLE AMOUNT | F19: =ROUNDDOWN(-PV(F18/12,48,F37),-2) -> 718600 | G19: =ROUNDDOWN(-PV(G18/12,36,F37),-2) -> 602100 | H19: =ROUNDDOWN(-PV(H18/12,24,F37),-2) -> 424800 | I19: =ROUNDDOWN(-PV(I18/12,12,F37),-2) -> 225100 | L19: AMORT/MO | M19: 8200 | N19: =IF(M19>M10,"CANNOT BE","OK") -> OK
E20: MONTHLY AMORTIZATION | F20: =-PMT(F18/12,48,F19) -> 19999.176 | G20: =-PMT(G18/12,36,G19) -> 19998.336 | H20: =-PMT(H18/12,24,H19) -> 19996.811 | I20: =-PMT(I18/12,12,I19) -> 19999.862 | L20: TERM | M20: AMOUNT | N20: Net Proceeds
E21: ESTIMATED NET PROCEEDS | F21: =F19-F14-F31-H15 -> 554955.66 | G21: =G19-F14-G31-H15 -> 442146.52 | H21: =H19-F14-H31-H15 -> 268380.82 | I21: =I19-F14-I31-H15 -> 72395.715 | L21: 4 YRS | M21: =-PV(F18/12,48,M19) -> 294638.14 | N21: =(M21*0.97912334)-$F$14-H15 -> 138487.08
E22: NET TAKE HOME PAY | F22: =$F$13-F20+$F$15+$I$15 -> 20000.824 | G22: =$F$13-G20+$F$15+I15 -> 20001.664 | H22: =$F$13-H20+$F$15+I15 -> 20003.189 | I22: =$F$13-I20+$F$15+I15 -> 20000.138 | L22: 3 YRS | M22: =-PV(G18/12,36,M19) -> 246881.54 | N22: =(M22*0.97912334)-$F$14-H15 -> 91727.479
L23: 2 YRS | M23: =-PV(H18/12,24,M19) -> 174195.78 | N23: =(M23*0.97912334)-$F$14-H15 -> 20559.15
E24: THANK YOU FOR BANKING WITH DBP! | L24: 1 YR | M24: =-PV(I18/12,12,M19) -> 92291.635 | N24: =(M24*0.97912334)-$F$14-H15 -> -59635.106
I25: COPY RIGHTS: DBP CATBALOGAN
E26: COMPUTATIONS
E28: SERVICE FEE | F28: =IF(F19*1%<1500,F19*1%,1500) -> 1500 | G28: =IF(G19*1%<1500,G19*1%,1500) -> 1500 | H28: =IF(H19*1%<1500,H19*1%,1500) -> 1500 | I28: =IF(I19*1%<1500,I19*1%,1500) -> 1500
E29: DOC STAMPS | F29: =IF(F19<250000,0,F19/200) -> 3593 | G29: =IF(G19<250000,0,G19/200) -> 3010.5 | H29: =IF(H19<250000,0,H19/200) -> 2124 | I29: =IF(I19<250000,0,I19/200) -> 0
E30: MRI | F30: =(F19/1000)*G60 -> 8551.34 | G30: =G19*G59/1000 -> 5442.984 | H30: =H19*6.58/1000 -> 2795.184 | I30: =I19*G57/1000 -> 1204.285
E31: TOTAL FEES/CHARGES | F31: =SUM(F28:F30) -> 13644.34 | G31: =SUM(G28:G30) -> 9953.484 | H31: =SUM(H28:H30) -> 6419.184 | I31: =SUM(I28:I30) -> 2704.285
E33: NTHP ADD DBP LOAN AND OTHER LOANS | F33: =F13+F15+I15 -> 40000
E34: NTHP LESS 3.5K GAA | F34: =F33-3500 -> 36500
E35: IGIR | F35: =IF(F11>0,IF(F12<10000,20%,IF(F12<13000,30%,IF(F12<38000,35%,40%))),IF(F12<10000,10%,IF(F12<13000,25%,30%))) -> 0.4
E36: LOAN INSTALLMENT (LI) | F36: =F35*F12 -> 20000
E37: INSTALLMENT TO USE | F37: =IF(F34<F36,F34,F36) -> 20000
F41: IGIR TABLE - NEW
F42: Less than 10K | G42: 0.1
F43: From 10K to <13K | G43: 0.25
F44: From 13K to <18K | G44: 0.3
F45: From 18K to <38K | G45: 0.3
F46: From 38K and above | G46: 0.3
F48: IGIR TABLE - RENEWAL
F49: Less than 10K | G49: 0.2
F50: From 10K to <13K | G50: 0.3
F51: From 13K to <18K | G51: 0.35
F52: From 18K to <38K | G52: 0.35
F53: From 38K and above | G53: 0.4
F56: MRI TARIFF (per 1000.00)
F57: 12 MOS | G57: 5.35
F58: 24 MOS | G58: 6.58
F59: 36 MOS | G59: 9.04
F60: 48 MOS | G60: 11.9

Sheet LOANABLE AMOUNT-REGULAR
E8: HOW MUCH IS YOUR LOANABLE AMOUNT?
N9: Prevailing Factor
L10: MAX AMORT: | M10: =F37 -> 9000 | N10: =IF(F36<F34,"BASED ON IGIR","BASED ON NTHP") -> BASED ON IGIR
E11: TYPE: [1] FOR RENEWAL/RE-AVAILMENT OR [0] FOR NEW | F11: 0 | N11: Net Proceeds
E12: GROSS SALARY | F12: 30000 | L12: LOAN AMOUNT | M12: 800000 | N12: =(0.97912334*M12-F14) -> 783298.67
E13: NET SALARY (OR NET TAKE HOME PAY) | F13: 25000 | L13: TERM | M13: AMORT/MO | N13: Remarks
E14: OUTSTANDING BALANCE OF EXISTING DBP LOAN | F14: 0 | L14: 4 YRS | M14: =-PMT(F18/12,48,M12) -> 22264.599 | N14: =IF(M14>$M$10,"CANNOT BE","OK") -> CANNOT BE
E15: MONTHLY AMORTIZATION OF EXISTING DBP LOAN | F15: 0 | L15: 3 YRS | M15: =-PMT(G18/12,36,M12) -> 26571.448 | N15: =IF(M15>$M$10,"CANNOT BE","OK") -> CANNOT BE
L16: 2 YRS | M16: =-PMT(H18/12,24,M12) -> 37658.778 | N16: =IF(M16>$M$10,"CANNOT BE","OK") -> CANNOT BE
E17: TERM | F17: 4 YRS | G17: 3 YRS | H17: 2 YRS | I17: 1 YR | L17: 1 YR | M17: =-PMT(I18/12,12,M12) -> 71079.031 | N17: =IF(M17>$M$10,"CANNOT BE","OK") -> CANNOT BE
E18: INTEREST RATE (PER ANNUM) | F18: 0.15 | G18: 0.12 | H18: 0.12 | I18: 0.12
E19: MAXIMUM LOANABLE AMOUNT | F19: =ROUNDDOWN(-PV(F18/12,48,F37),-2) -> 323300 | G19: =ROUNDDOWN(-PV(G18/12,36,F37),-2) -> 270900 | H19: =ROUNDDOWN(-PV(H18/12,24,F37),-2) -> 191100 | I19: =ROUNDDOWN(-PV(I18/12,12,F37),-2) -> 101200 | L19: AMORT/MO | M19: 15000
E20: MONTHLY AMORTIZATION | F20: =-PMT(F18/12,48,F19) -> 8997.6809 | G20: =-PMT(G18/12,36,G19) -> 8997.7565 | H20: =-PMT(H18/12,24,H19) -> 8995.7405 | I20: =-PMT(I18/12,12,I19) -> 8991.4974 | L20: TERM | M20: AMOUNT | N20: Net Proceeds
E21: ESTIMATED NET PROCEEDS | F21: =F19-F14-F31 -> 316336.23 | G21: =G19-F14-G31 -> 265596.56 | H21: =H19-F14-H31 -> 188342.56 | I21: =I19-F14-I31 -> 99646.58 | L21: 4 YRS | M21: =-PV(F18/12,48,M19) -> 538972.21 | N21: =(M21*0.97912334)-$F$14 -> 527720.27
E22: NET TAKE HOME PAY | F22: =$F$13-F20+$F$15 -> 16002.319 | G22: =$F$13-G20+$F$15 -> 16002.243 | H22: =$F$13-H20+$F$15 -> 16004.259 | I22: =$F$13-I20+$F$15 -> 16008.503 | L22: 3 YRS | M22: =-PV(G18/12,36,M19) -> 451612.58 | N22: =(M22*0.97912334)-$F$14 -> 442184.41
L23: 2 YRS | M23: =-PV(H18/12,24,M19) -> 318650.81 | N23: =(M23*0.97912334)-$F$14 -> 311998.44
E24: THANK YOU FOR BANKING WITH DBP! | L24: 1 YR | M24: =-PV(I18/12,12,M19) -> 168826.16 | N24: =(M24*0.97912334)-$F$14 -> 165301.64
I25: COPY RIGHTS: DBP CATBALOGAN
E26: COMPUTATIONS
E28: SERVICE FEE | F28: =IF(F19*1%<1500,F19*1%,1500) -> 1500 | G28: =IF(G19*1%<1500,G19*1%,1500) -> 1500 | H28: =IF(H19*1%<1500,H19*1%,1500) -> 1500 | I28: =IF(I19*1%<1500,I19*1%,1500) -> 1012
E29: DOC STAMPS | F29: =IF(F19<250000,0,F19/200) -> 1616.5 | G29: =IF(G19<250000,0,G19/200) -> 1354.5 | H29: =IF(H19<250000,0,H19/200) -> 0 | I29: =IF(I19<250000,0,I19/200) -> 0
E30: MRI | F30: =(F19/1000)*G60 -> 3847.27 | G30: =G19*G59/1000 -> 2448.936 | H30: =H19*6.58/1000 -> 1257.438 | I30: =I19*G57/1000 -> 541.42
E31: TOTAL FEES/CHARGES | F31: =SUM(F28:F30) -> 6963.77 | G31: =SUM(G28:G30) -> 5303.436 | H31: =SUM(H28:H30) -> 2757.438 | I31: =SUM(I28:I30) -> 1553.42
E33: NTHP ADD DBP LOAN | F33: =F13+F15 -> 25000
E34: NTHP LESS 3.5K GAA | F34: =F33-3500 -> 21500
E35: IGIR | F35: =IF(F11>0,IF(F12<10000,20%,IF(F12<13000,30%,IF(F12<38000,35%,40%))),IF(F12<10000,10%,IF(F12<13000,25%,30%))) -> 0.3
E36: LOAN INSTALLMENT (LI) | F36: =F35*F12 -> 9000
E37: INSTALLMENT TO USE | F37: =IF(F34<F36,F34,F36) -> 9000
F41: IGIR TABLE - NEW
F42: Less than 10K | G42: 0.1
F43: From 10K to <13K | G43: 0.25
F44: From 13K to <18K | G44: 0.3
F45: From 18K to <38K | G45: 0.3
F46: From 38K and above | G46: 0.3
F48: IGIR TABLE - RENEWAL
F49: Less than 10K | G49: 0.2
F50: From 10K to <13K | G50: 0.3
F51: From 13K to <18K | G51: 0.35
F52: From 18K to <38K | G52: 0.35
F53: From 38K and above | G53: 0.4
F56: MRI TARIFF (per 1000.00)
F57: 12 MOS | G57: 5.35
F58: 24 MOS | G58: 6.58
F59: 36 MOS | G59: 9.04
F60: 48 MOS | G60: 11.9

Sheet LOANABLE AMOUNT- DAR
E8: HOW MUCH IS YOUR LOANABLE AMOUNT?
E11: ---FOR DAR ONLY---
E12: GROSS SALARY | F12: 50000
E13: NET SALARY (OR NET TAKE HOME PAY) | F13: 40000
E14: OUTSTANDING BALANCE OF EXISTING DBP LOAN | F14: 0
E15: MONTHLY AMORTIZATION OF EXISTING DBP LOAN | F15: 0
E17: TERM | F17: 4 YRS | G17: 3 YRS | H17: 2 YRS | I17: 1 YR
E18: INTEREST RATE (PER ANNUM) | F18: 0.12 | G18: 0.1 | H18: 0.1 | I18: 0.1
E19: MAXIMUM LOANABLE AMOUNT | F19: =ROUNDDOWN(-PV(F18/12,48,F37),-2) -> 569600 | G19: =ROUNDDOWN(-PV(G18/12,36,F37),-2) -> 464800 | H19: =ROUNDDOWN(-PV(H18/12,24,F37),-2) -> 325000 | I19: =ROUNDDOWN(-PV(I18/12,12,F37),-2) -> 170600
E20: MONTHLY AMORTIZATION | F20: =-PMT(F18/12,48,F19) -> 14999.753 | G20: =-PMT(G18/12,36,G19) -> 14997.789 | H20: =-PMT(H18/12,24,H19) -> 14997.101 | I20: =-PMT(I18/12,12,I19) -> 14998.45
E21: ESTIMATED NET PROCEEDS | F21: =F19-F14-F31 -> 558473.76 | G21: =G19-F14-G31 -> 456774.21 | H21: =H19-F14-H31 -> 319736.5 | I21: =I19-F14-I31 -> 168187.29
E22: NET TAKE HOME PAY | F22: =$F$13-F20+$F$15 -> 25000.247 | G22: =$F$13-G20+$F$15 -> 25002.211 | H22: =$F$13-H20+$F$15 -> 25002.899 | I22: =$F$13-I20+$F$15 -> 25001.55
E24: THANK YOU FOR BANKING WITH DBP!
I25: COPY RIGHTS: DBP CATBALOGAN
E26: COMPUTATIONS
E28: SERVICE FEE | F28: =IF(F19*1%<1500,F19*1%,1500) -> 1500 | G28: =IF(G19*1%<1500,G19*1%,1500) -> 1500 | H28: =IF(H19*1%<1500,H19*1%,1500) -> 1500 | I28: =IF(I19*1%<1500,I19*1%,1500) -> 1500
E29: DOC STAMPS | F29: =IF(F19<250000,0,F19/200) -> 2848 | G29: =IF(G19<250000,0,G19/200) -> 2324 | H29: =IF(H19<250000,0,H19/200) -> 1625 | I29: =IF(I19<250000,0,I19/200) -> 0
E30: MRI | F30: =(F19/1000)*G60 -> 6778.24 | G30: =G19*G59/1000 -> 4201.792 | H30: =H19*6.58/1000 -> 2138.5 | I30: =I19*G57/1000 -> 912.71
E31: TOTAL FEES/CHARGES | F31: =SUM(F28:F30) -> 11126.24 | G31: =SUM(G28:G30) -> 8025.792 | H31: =SUM(H28:H30) -> 5263.5 | I31: =SUM(I28:I30) -> 2412.71
E33: NTHP ADD DBP LOAN | F33: =F13+F15 -> 40000
E34: NTHP LESS 3.5K GAA | F34: =F33-3500 -> 36500
E35: IGIR | F35: =IF(F15>0,IF(F12<10000,20%,IF(F12<13000,30%,IF(F12<38000,35%,40%))),IF(F12<10000,10%,IF(F12<13000,25%,30%))) -> 0.3
E36: LOAN INSTALLMENT (LI) | F36: =F35*F12 -> 15000
E37: INSTALLMENT TO USE | F37: =IF(F34<F36,F34,F36) -> 15000
F41: IGIR TABLE - NEW
F42: Less than 10K | G42: 0.1
F43: From 10K to <13K | G43: 0.25
F44: From 13K to <18K | G44: 0.3
F45: From 18K to <38K | G45: 0.3
F46: From 38K and above | G46: 0.3
F48: IGIR TABLE - RENEWAL
F49: Less than 10K | G49: 0.2
F50: From 10K to <13K | G50: 0.3
F51: From 13K to <18K | G51: 0.35
F52: From 18K to <38K | G52: 0.35
F53: From 38K and above | G53: 0.4
F56: MRI TARIFF (per 1000.00)
F57: 12 MOS | G57: 5.35
F58: 24 MOS | G58: 6.58
F59: 36 MOS | G59: 9.04
F60: 48 MOS | G60: 11.9

Sheet Signatories
B4: PLEASE PROVIDE INFO ON THE FF:
B8: NAME OF SIGNATORIES
B9: Name of RO | C9: JANICE B. SOLAYAO
B10: Name of BOO | C10: AM IRISH MAE N. CREER
B11: Name of Manager | C11: SM HELBERT ANTOINE A. ACHAY
B13: Branch | C13: CATBALOGAN
B14: Address | C14: CATBALOGAN CITY, SAMAR
B15: RMC | C15: EASTERN VISAYAS

Sheet INPUT FIELDS
C2: PROVINCE OF SAMAR RSLP TEMPLATE
C4: BORROWER'S DATA SHEET
D5: 1 | AV5: 2 | AX5: 3 | AZ5: 4 | BB5: 5 | BD5: 6 | BF5: 7 | BH5: 8 | BJ5: 9 | BL5: 10 | BN5: 11 | BP5: 12 | BR5: 13 | BT5: 14 | BV5: 15 | BX5: 16 | BZ5: 17 | CB5: 18 | CD5: 19 | CF5: 20
C6: OT NO AND DATE | D6: OT N0. 15-005 DATED APRIL 7, 2015
C7: SURNAME | D7: RABADAM | AV7: LEJAS | AX7: NUNEZ | AZ7: LIMA | BB7: ALEGRIA | BD7: GACELOS | BF7: GONZALES | BH7: MAYOR | BJ7: YBOA | BL7: GONZALES | BN7: ARCALES | BP7: GACELOS | BR7: TONELETE | BT7: GABON
C8: FIRST NAME | D8: MARIA EMY | AV8: ALLAN | AX8: JOSE JR | AZ8: NESTOR | BB8: MARCIANO JR | BD8: MANOLITO | BF8: LEONILA | BH8: CHONA | BJ8: JONAS | BL8: RUBIA | BN8: DOMINGO JR | BP8: REBECCA | BR8: NARCISA | BT8: MA WINONA
C9: MIDDLE NAME | D9: TAN | AV9: GULFERIC | AX9: ADESAS | AZ9: PELENO | BB9: HERNANDEZ | BD9: ABARRACOSO | BF9: HILONGO | BH9: BRANZUELA | BJ9: ABELIDO | BL9: ABARCAR | BN9: JADLOC | BP9: TILLES | BR9: CAMUIN | BT9: CON UI
C10: NAME OF SPOUSE | D10: ARNEL B RABADAM | AV10: MARIAN DAGANZO LEJAS | AX10: ERLINDA BACUETES NUNEZ | AZ10: MARY GEN ISANAN LIMA | BB10: MARILYN SOLAYAO ALEGRIA | BD10: CHERIE N GACELOS | BH10: VENG JAYCO B MAYOR | BJ10: NANCY ALBOS YBOA | BL10: NELSON VILLANUEVA GONZALES | BR10: ANTONIO DETALO TONELETE | BT10: ALEJANDRO CUNA GABON
C11: ADDRESS | D11: 202 CURRY AVENUE CATBALOGAN CITY SAMAR | AV11: PUROK 1 BRGY CANLAPWAS CATBALOGAN CITY SAMAR | AX11: 352 RIZAL AVENUE BRGY 12 CATBALOGAN CITY SAMAR | AZ11: PATONG STREET BRGY GUINSORONGAN CATBALOGAN CITY | BB11: P2 BRGY JIA AN JIABONG SAMAR | BD11: BRGY RAWIS HINABANGAN SAMAR | BF11: BRGY SAN JOSE ALMAGRO WESTERN SAMAR | BH11: BRGY PANJOBJOBAN ALMAGRO SAMAR | BJ11: 5TH ST COR BANOYO ST BRGY 10 CATBALOGAN CITY SAMAR | BL11: NO 20 B 2 LOT 8 BLISS CANLAPWAS CATBALOGAN CITY | BN11: 491 PUROK 3 BRGY MERCEDES CATBALOGAN CITY | BP11: 117 P 2 BRGY MAULONG CATBALOGAN CITY SAMAR | BR11: 270 BRGY MAULONG CATBALOGAN CITY SAMAR | BT11: 451 GABON BLVD BRGY 3 PARANAS WRIGHT SAMAR
C12: TIN | D12: 943994147 | AV12: 273165815 | AX12: 184693732 | AZ12: 130157835 | BB12: 905838005 | BD12: 400532413 | BF12: 129842327 | BH12: 947543937 | BJ12: 174344327 | BL12: 166545733 | BN12: 914894035 | BP12: 131439004 | BR12: 133458617 | BT12: 178650362
C13: BIRTHDATE | D13: 29144 | AV13: 30469 | AX13: 112566 | AZ13: 20219 | BB13: 26900 | BD13: 28260 | BF13: 20852 | BH13: 24599 | BJ13: 25868 | BL13: 22656 | BN13: 24098 | BP13: 19920 | BR13: 21917 | BT13: 25812
C14: DATE PERMANENT | D14: 39218 | AV14: 40525 | AX14: 34541 | AZ14: 31048 | BB14: 36297 | BD14: 40252 | BF14: 30376 | BH14: 39114 | BJ14: 35492 | BL14: 34319 | BN14: 35506 | BP14: 29859 | BR14: 29692 | BT14: 37097
C15: AGENCY/EMPLOYER | D15: PROVINCE OF SAMAR1 | AV15: PROVINCE OF SAMAR2 | AX15: PROVINCE OF SAMAR3 | AZ15: PROVINCE OF SAMAR4 | BB15: PROVINCE OF SAMAR5 | BD15: PROVINCE OF SAMAR6 | BF15: PROVINCE OF SAMAR7 | BH15: PROVINCE OF SAMAR4 | BJ15: PROVINCE OF SAMAR9 | BL15: PROVINCE OF SAMAR10 | BN15: PROVINCE OF SAMAR11 | BP15: PROVINCE OF SAMAR12 | BR15: PROVINCE OF SAMAR13 | BT15: PROVINCE OF SAMAR14
C16: OFFICE | D16: PROVINCIAL TREASURER OFFICE | AV16: PROVINCIAL ENGINEERING OFFICE | AX16: PROVINCIAL AGRICULTURE OFFICE | AZ16: PROVINCIAL WARDENS OFFICE | BB16: PROVINCIAL WARDENS OFFICE | BD16: PROVINCIAL HEALTH OFFICE | BN16: PROVINCIAL AGRICULTURE OFFICE | BR16: PROVINCIAL SANGGUNIANG PANLALAWIGAN
C17: POSITION | D17: ADMIN AIDE I | AV17: CM CAPATAZ | AX17: DRAFTSMAN I | AZ17: PRISON GUARD I | BB17: ADMIN AIDE III | BD17: DRIVER I | BF17: DENTIST II | BH17: DENTAL AIDE | BJ17: ADMIN AIDE VI | BL17: LABORATORY AIDE I | BN17: AGRICULTURAL TECHNICIAN II | BP17: AGRICULTURAL TECHNOLOGIST I | BR17: BOARD SECRETARY I | BT17: COMPUTER MAINTENANCE TECHNICIAN
C18: BASIC PAY | D18: 38000 | AV18: 12139 | AX18: 13853 | AZ18: 12886 | BB18: 10931 | BD18: 10505 | BF18: 31339 | BH18: 11405 | BJ18: 13580 | BL18: 10373 | BN18: 15768.87 | BP18: 18135 | BR18: 23979 | BT18: 19495
C19: ACA/PERA/RATA/OTHERS | D19: 2000 | AV19: 2000 | AX19: 2000 | AZ19: 2000 | BB19: 2000 | BD19: 3650 | BF19: 3650 | BH19: 3650 | BJ19: 2000 | BL19: 3650 | BN19: 2000 | BP19: 2000 | BR19: 2000 | BT19: 2000
C20: TOTAL DEDUCTIONS PER NTHP | D20: 26000 | AV20: 6939.36 | AX20: 9753.9 | AZ20: 10386 | BB20: 7761 | BD20: 2357.99 | BF20: 21547.08 | BH20: 8448.62 | BJ20: 10473.62 | BL20: 7735.27 | BN20: 12313.58 | BP20: 14037.39 | BR20: 16345.01 | BT20: 8580.2
C21: EXISTING DBP LOAN AMORT | D21: 5000 | AV21: 0 | AX21: 3714.69 | AZ21: 3453.19 | BB21: 2999.23 | BD21: 0 | BF21: 8404.99 | BH21: 3057.58 | BJ21: 3640.94 | BL21: 2752.49 | BN21: 4207.52 | BP21: 4652.09 | BR21: 6583.07 | BT21: 5176.43
C23: APPLICATION NO | D23: 15-0070 | AV23: 15-0070 | AX23: 15-0070 | AZ23: 15-0080 | CF23: 15-0070
C24: DATE FILED | D24: 42094 | AV24: 42094 | AX24: 42094 | AZ24: 42094 | BB24: 42100 | BD24: 42101 | BF24: 42100 | BH24: 42100 | BJ24: 42100 | BL24: 42100 | BN24: 42100 | BP24: 42101 | BR24: 42100 | BT24: 42100
C25: DATE EXECUTED: SPA NOTARIZATION DATE | D25: 42081 | AV25: 34409 | AX25: 42095 | AZ25: 42087 | BB25: 42095 | BD25: 42101 | BF25: 42100 | BH25: 42100 | BJ25: 42093 | BL25: 42093 | BN25: 42100 | BP25: 42100 | BR25: 42093 | BT25: 42093
C26: CERTIFICATION DATE: AS PERMANENT EMPLOYEE | D26: 42081 | AV26: 42097 | AX26: 42095 | AZ26: 42093 | BB26: 42100 | BD26: 42101 | BF26: 42095 | BH26: 42100 | BJ26: 42090 | BL26: 42100 | BN26: 42095 | BP26: 42100 | BR26: 42087 | BT26: 42086
C27: CERTIFICATION DATE: NO PENDING ADMIN CASE | D27: 42081 | AV27: 42135 | AX27: 42093 | AZ27: 42087 | BB27: 42090 | BD27: =BD26 -> 42101 | BF27: =BF26 -> 42095 | BH27: 42095 | BJ27: 42093 | BL27: 42095 | BM27: 0 | BN27: 42093 | BP27: 42093 | BR27: 42087 | BT27: =BT26 -> 42086 | BV27: =BV26 -> 0 | BX27: =BX26 -> 0 | BZ27: =BZ26 -> 0 | CB27: =CB26 -> 0 | CD27: =CD26 -> 0 | CF27: =CF26 -> 0
C28: CERTIFICATION DATE: LEAVE CREDITS | D28: 42081 | AV28: 42463 | AX28: 42095 | AZ28: 42087 | BB28: =BB26 -> 42100 | BD28: =BD26 -> 42101 | BF28: =BF26 -> 42095 | BH28: 42095 | BJ28: =BJ26 -> 42090 | BL28: 42095 | BN28: 42093 | BP28: 42093 | BR28: =BR26 -> 42087 | BT28: =BT26 -> 42086 | BV28: =BV26 -> 0 | BX28: =BX26 -> 0 | BZ28: =BZ26 -> 0 | CB28: =CB26 -> 0 | CD28: =CD26 -> 0 | CF28: =CF26 -> 0
C29: DATE ISSUED: SERVICE RECORD | D29: 42081 | AV29: 42463 | AX29: 42095 | AZ29: 42087 | BB29: 42089 | BD29: 42101 | BF29: 42095 | BH29: 42095 | BJ29: 42093 | BL29: 42095 | BN29: 42093 | BP29: 42100 | BR29: 42086 | BT29: 42088
C30: DATE ISSUED: CERT OF NET TAKE HOME PAY | D30: 42081 | AV30: 42463 | AX30: 42095 | AZ30: 42087 | BB30: 42089 | BD30: 42101 | BF30: 42095 | BH30: 42094 | BJ30: 42090 | BL30: 42094 | BN30: 42095 | BP30: 42093 | BR30: 42087 | BT30: 42086
C31: DATE SWORN: OATH OF OFFICE (ELECTIVE OFF'L) | D31: NA | AV31: NA | AX31: NA | AZ31: NA | BB31: NA | BD31: NA | BF31: NA | BH31: NA | BJ31: NA | BL31: NA | BN31: NA | BP31: NA | BR31: NA | BT31: NA
C32: BIR FORM 2316/ITR | D32: 2014 | AV32: 2014 | AX32: 2014 | AZ32: 2014 | BB32: 2014 | BD32: 2014 | BF32: 2014 | BH32: 2014 | BJ32: 2014 | BL32: 2014 | BN32: 2014 | BP32: 2014 | BR32: 2014 | BT32: 2014
C33: DATE ISSUED: NFIS CHECKING | D33: - | AV33: - | AX33: - | AZ33: - | CF33: -
D35: 1 | AL35: 5 | AM35: 5 | AN35: 6 | AO35: 7 | AP35: 8 | AQ35: 9 | AR35: 10 | AS35: 11 | AT35: 12 | AV35: 2 | AX35: 3 | AZ35: 4 | BB35: 5 | BD35: 6 | BF35: 7 | BH35: 8 | BJ35: 9 | BL35: 10 | BN35: 11 | BP35: 12 | BR35: 13 | BT35: 14 | BV35: 15 | BX35: 16 | BZ35: 17 | CB35: 18 | CD35: 19 | CF35: 20
D36: NAME | E36: BIRTHDATE | F36: DATE PERMANENT | G36: AGE | H36: YEARS IN SERVICE | I36: POSITION | J36: BASIC SALARY | K36: ACA/PERA/OTHERS | L36: GROSS INCOME | M36: TOTAL DEDUCTIONS PER NTHP | N36: LESS: EXISTING DBP LOANS | O36: IGIR % | P36: MAX LI | Q36: ADD: NEW AMORT | R36: NEW TOTAL DEDUCTIONS | S36: MONTHLY NTHP | T36: TYPE OF LOAN (NEW/RENEWAL) | U36: MAX LOAN AMOUNT | V36: AMOUNT OF LOAN | W36: INTEREST RATE | X36: TERM OF LOAN | Z36: Application No. | AA36: Date Filed | AB36: Date Executed | AC36: Date Issued | AD36: Date Issued | AE36: Date Issued | AF36: Date Issued | AG36: Date Issued | AH36: Date Sworn | AI36: For Year | AJ36: Date Issued | AL36: IB_FNAM | AM36: IB_MNAM | AN36: IB_LNAM | AO36: IB_SPOUSE | AP36: IB_ADDR1 | AQ36: IB_TAN | AR36: IB_BIRTH | AS36: RECKEY | AT36: IB_BANKCD
C37: 1 | D37: =CONCATENATE(D7,", ",D8," ",D9) -> RABADAM, MARIA EMY TAN | E37: =D13 -> 29144 | F37: =D14 -> 39218 | G37: =IF(E37>0,ROUNDDOWN((NOW()-E37)/365,0),0) -> 46 | H37: =IF(F37>0,ROUNDDOWN((NOW()-F37)/365,0),0) -> 18 | I37: =D17 -> ADMIN AIDE I | J37: =D18 -> 38000 | K37: =D19 -> 2000 | L37: =J37+K37 -> 40000 | M37: =D20 -> 26000 | N37: =D21 -> 5000 | O37: =IF(L37<10000,10%,IF(L37<13000,25%,30%)) -> 0.3 | P37: =L37*O37 -> 12000 | Q37: =-PMT(W37/12,X37,V37) -> 6392.3145 | R37: =M37-N37+Q37 -> 27392.315 | S37: =J37+K37-R37 -> 12607.685 | T37: =IF(N37>0,"RENEWAL","NEW") -> RENEWAL | U37: =-PV(W37/12,X37,P37) -> 134599.13 | V37: ='COMPUTATION SHEET'!AA24 -> 71700 | W37: =IF(X37>36,15.81%,12.651%) -> 0.12651 | X37: ='COMPUTATION SHEET'!AC24 -> 12 | Y37: =C37 -> 1 | Z37: =D23 -> 15-0070 | AA37: =$D24 -> 42094 | AB37: =$D25 -> 42081 | AC37: =$D26 -> 42081 | AD37: =$D27 -> 42081 | AE37: =$D28 -> 42081 | AF37: =$D29 -> 42081 | AG37: =$D30 -> 42081 | AH37: =$D31 -> NA | AI37: =$D32 -> 2014 | AJ37: =$D33 -> - | AL37: =$D7 -> RABADAM | AM37: =$D8 -> MARIA EMY | AN37: =$D9 -> TAN | AO37: =$D10 -> ARNEL B RABADAM | AP37: =$D11 -> 202 CURRY AVENUE CATBALOGAN CITY SAMAR | AQ37: =$D12 -> 943994147 | AR37: =$D13 -> 29144 | AS37: =$D15 -> PROVINCE OF SAMAR1 | AT37: DBP | AV37: =CONCATENATE(AV7,", ",AV8," ",AV9) -> LEJAS, ALLAN GULFERIC | AX37: =CONCATENATE(AX7,", ",AX8," ",AX9) -> NUNEZ, JOSE JR ADESAS | AZ37: =CONCATENATE(AZ7,", ",AZ8," ",AZ9) -> LIMA, NESTOR PELENO | BB37: =CONCATENATE(BB7,", ",BB8," ",BB9) -> ALEGRIA, MARCIANO JR HERNANDEZ | BD37: =CONCATENATE(BD7,", ",BD8," ",BD9) -> GACELOS, MANOLITO ABARRACOSO | BF37: =CONCATENATE(BF7,", ",BF8," ",BF9) -> GONZALES, LEONILA HILONGO | BH37: =CONCATENATE(BH7,", ",BH8," ",BH9) -> MAYOR, CHONA BRANZUELA | BJ37: =CONCATENATE(BJ7,", ",BJ8," ",BJ9) -> YBOA, JONAS ABELIDO | BL37: =CONCATENATE(BL7,", ",BL8," ",BL9) -> GONZALES, RUBIA ABARCAR | BM37: 1 | BN37: =CONCATENATE(BN7,", ",BN8," ",BN9) -> ARCALES, DOMINGO JR JADLOC | BP37: =CONCATENATE(BP7,", ",BP8," ",BP9) -> GACELOS, REBECCA TILLES | BR37: =CONCATENATE(BR7,", ",BR8," ",BR9) -> TONELETE, NARCISA CAMUIN | BT37: =CONCATENATE(BT7,", ",BT8," ",BT9) -> GABON, MA WINONA CON UI | BV37: =CONCATENATE(BV7,", ",BV8," ",BV9) -> , | BX37: =CONCATENATE(BX7,", ",BX8," ",BX9) -> , | BZ37: =CONCATENATE(BZ7,", ",BZ8," ",BZ9) -> , | CB37: =CONCATENATE(CB7,", ",CB8," ",CB9) -> , | CD37: =CONCATENATE(CD7,", ",CD8," ",CD9) -> , | CF37: =CONCATENATE(CF7,", ",CF8," ",CF9) -> ,
Q38: =-PMT(W38/12,X38,V38) -> 0 | R38: =M38-N38+Q38 -> 0 | S38: =J38+K38-R38 -> 0 | T38: RENEWAL | U38: =-PV(W38/12,X38,P38) -> 0 | V38: ='COMPUTATION SHEET'!AA25 -> 0 | W38: =IF(X38>36,15.81%,12.651%) -> 0.1581 | X38: 49 | Y38: =C38 -> 0
C39: 2 | D39: =AV37 -> LEJAS, ALLAN GULFERIC | E39: =AV13 -> 30469 | F39: =AV14 -> 40525 | G39: =IF(E39>0,ROUNDDOWN((NOW()-E39)/365,0),0) -> 42 | H39: =IF(F39>0,ROUNDDOWN((NOW()-F39)/365,0),0) -> 15 | I39: =AV17 -> CM CAPATAZ | J39: =AV18 -> 12139 | K39: =AV19 -> 2000 | L39: =J39+K39 -> 14139 | M39: =AV20 -> 6939.36 | N39: =AV21 -> 0 | O39: =IF(L39<10000,10%,IF(L39<13000,25%,30%)) -> 0.3 | P39: =L39*O39 -> 4241.7 | Q39: =-PMT(W39/12,X39,V39) -> 3191.4665 | R39: =M39-N39+Q39 -> 10130.826 | S39: =J39+K39-R39 -> 4008.1735 | T39: =IF(N39>0,"RENEWAL","NEW") -> NEW | U39: =-PV(W39/12,X39,P39) -> 150185.53 | V39: ='COMPUTATION SHEET'!AA26 -> 113000 | W39: =IF(X39>36,15.81%,12.651%) -> 0.1581 | X39: ='COMPUTATION SHEET'!AC26 -> 48 | Y39: =C39 -> 2 | Z39: =AV23 -> 15-0070 | AA39: =$AV24 -> 42094 | AB39: =$AV25 -> 34409 | AC39: =$AV26 -> 42097 | AD39: =$AV27 -> 42135 | AE39: =$AV28 -> 42463 | AF39: =$AV29 -> 42463 | AG39: =$AV30 -> 42463 | AH39: =$AV31 -> NA | AI39: =$AV32 -> 2014 | AJ39: =$AV33 -> - | AL39: =$AV7 -> LEJAS | AM39: =$AV8 -> ALLAN | AN39: =$AV9 -> GULFERIC | AO39: =$AV10 -> MARIAN DAGANZO LEJAS | AP39: =$AV11 -> PUROK 1 BRGY CANLAPWAS CATBALOGAN CITY SAMAR | AQ39: =$AV12 -> 273165815 | AR39: =$AV13 -> 30469 | AS39: =$AV15 -> PROVINCE OF SAMAR2 | AT39: DBP
G40: =ROUNDDOWN((NOW()-E40)/365,0) -> 126 | H40: =ROUNDDOWN((NOW()-F40)/365,0) -> 126 | L40: =J40+K40 -> 0 | O40: =IF(L40<10000,10%,IF(L40<13000,25%,30%)) -> 0.1 | P40: =L40*O40 -> 0 | Q40: =-PMT(W40/12,X40,V40) -> #NUM! | R40: =M40-N40+Q40 -> #NUM! | S40: =J40+K40-R40 -> #NUM! | T40: =IF(N40>0,"RENEWAL","NEW") -> NEW | U40: =-PV(W40/12,X40,P40) -> 0 | V40: ='COMPUTATION SHEET'!AA27 -> 0 | W40: =IF(X40>36,15.81%,12.651%) -> 0.12651 | X40: ='COMPUTATION SHEET'!AC27 -> 0 | Y40: =C40 -> 0 | AT40: DBP
C41: 3 | D41: =AX37 -> NUNEZ, JOSE JR ADESAS | E41: =AX13 -> 112566 | F41: =AX14 -> 34541 | G41: =IF(E41>0,ROUNDDOWN((NOW()-E41)/365,0),0) -> -182 | H41: =IF(F41>0,ROUNDDOWN((NOW()-F41)/365,0),0) -> 31 | I41: =AX17 -> DRAFTSMAN I | J41: =AX18 -> 13853 | K41: =AX19 -> 2000 | L41: =J41+K41 -> 15853 | M41: =AX20 -> 9753.9 | N41: =AX21 -> 3714.69 | O41: =IF(L41<10000,10%,IF(L41<13000,25%,30%)) -> 0.3 | P41: =L41*O41 -> 4755.9 | Q41: =-PMT(W41/12,X41,V41) -> 5546.9382 | R41: =M41-N41+Q41 -> 11586.148 | S41: =J41+K41-R41 -> 4266.8518 | T41: =IF(N41>0,"RENEWAL","NEW") -> RENEWAL | U41: =-PV(W41/12,X41,P41) -> 168391.77 | V41: ='COMPUTATION SHEET'!AA28 -> 196400 | W41: =IF(X41>36,15.81%,12.651%) -> 0.1581 | X41: ='COMPUTATION SHEET'!AC28 -> 48 | Y41: =C41 -> 3 | Z41: =AX23 -> 15-0070 | AA41: =$AX24 -> 42094 | AB41: =$AX25 -> 42095 | AC41: =$AX26 -> 42095 | AD41: =$AX27 -> 42093 | AE41: =$AX28 -> 42095 | AF41: =$AX29 -> 42095 | AG41: =$AX30 -> 42095 | AH41: =$AX31 -> NA | AI41: =$AX32 -> 2014 | AJ41: =$AX33 -> - | AL41: =$AX7 -> NUNEZ | AM41: =$AX8 -> JOSE JR | AN41: =$AX9 -> ADESAS | AO41: =$AX10 -> ERLINDA BACUETES NUNEZ | AP41: =$AX11 -> 352 RIZAL AVENUE BRGY 12 CATBALOGAN CITY SAMAR | AQ41: =$AX12 -> 184693732 | AR41: =$AX13 -> 112566 | AS41: =$AX15 -> PROVINCE OF SAMAR3 | AT41: DBP
G42: =ROUNDDOWN((NOW()-E42)/365,0) -> 126 | H42: =ROUNDDOWN((NOW()-F42)/365,0) -> 126 | L42: =J42+K42 -> 0 | O42: =IF(L42<10000,10%,IF(L42<13000,25%,30%)) -> 0.1 | P42: =L42*O42 -> 0 | Q42: =-PMT(W42/12,X42,V42) -> #NUM! | R42: =M42-N42+Q42 -> #NUM! | S42: =J42+K42-R42 -> #NUM! | T42: =IF(N42>0,"RENEWAL","NEW") -> NEW | U42: =-PV(W42/12,X42,P42) -> 0 | V42: ='COMPUTATION SHEET'!AA29 -> 0 | W42: =IF(X42>36,15.81%,12.651%) -> 0.12651 | X42: ='COMPUTATION SHEET'!AC29 -> 0 | Y42: =C42 -> 0 | AT42: DBP
C43: 4 | D43: =AZ37 -> LIMA, NESTOR PELENO | E43: =AZ13 -> 20219 | F43: =AZ14 -> 31048 | G43: =IF(E43>0,ROUNDDOWN((NOW()-E43)/365,0),0) -> 70 | H43: =IF(F43>0,ROUNDDOWN((NOW()-F43)/365,0),0) -> 41 | I43: =AZ17 -> PRISON GUARD I | J43: =AZ18 -> 12886 | K43: =AZ19 -> 2000 | L43: =J43+K43 -> 14886 | M43: =AZ20 -> 10386 | N43: =AZ21 -> 3453.19 | O43: =IF(L43<10000,10%,IF(L43<13000,25%,30%)) -> 0.3 | P43: =L43*O43 -> 4465.8 | Q43: =-PMT(W43/12,X43,V43) -> 3939.9077 | R43: =M43-N43+Q43 -> 10872.718 | S43: =J43+K43-R43 -> 4013.2823 | T43: =IF(N43>0,"RENEWAL","NEW") -> RENEWAL | U43: =-PV(W43/12,X43,P43) -> 158120.23 | V43: ='COMPUTATION SHEET'!AA30 -> 139500 | W43: =IF(X43>36,15.81%,12.651%) -> 0.1581 | X43: ='COMPUTATION SHEET'!AC30 -> 48 | Y43: =C43 -> 4 | Z43: =AZ23 -> 15-0080 | AA43: =$AZ24 -> 42094 | AB43: =$AZ25 -> 42087 | AC43: =$AZ26 -> 42093 | AD43: =$AZ27 -> 42087 | AE43: =$AZ28 -> 42087 | AF43: =$AZ29 -> 42087 | AG43: =$AZ30 -> 42087 | AH43: =$AZ31 -> NA | AI43: =$AZ32 -> 2014 | AJ43: =$AZ33 -> - | AL43: =$AZ7 -> LIMA | AM43: =$AZ8 -> NESTOR | AN43: =$AZ9 -> PELENO | AO43: =$AZ10 -> MARY GEN ISANAN LIMA | AP43: =$AZ11 -> PATONG STREET BRGY GUINSORONGAN CATBALOGAN CITY | AQ43: =$AZ12 -> 130157835 | AR43: =$AZ13 -> 20219 | AS43: =$AZ15 -> PROVINCE OF SAMAR4 | AT43: DBP
G44: =ROUNDDOWN((NOW()-E44)/365,0) -> 126 | H44: =ROUNDDOWN((NOW()-F44)/365,0) -> 126 | L44: =J44+K44 -> 0 | O44: =IF(L44<10000,10%,IF(L44<13000,25%,30%)) -> 0.1 | P44: =L44*O44 -> 0 | Q44: =-PMT(W44/12,X44,V44) -> #NUM! | R44: =M44-N44+Q44 -> #NUM! | S44: =J44+K44-R44 -> #NUM! | T44: =IF(N44>0,"RENEWAL","NEW") -> NEW | U44: =-PV(W44/12,X44,P44) -> 0 | V44: ='COMPUTATION SHEET'!AA31 -> 0 | W44: =IF(X44>36,15.81%,12.651%) -> 0.12651 | X44: ='COMPUTATION SHEET'!AC31 -> 0 | Y44: =C44 -> 0 | AT44: DBP
C45: 5 | D45: =BB37 -> ALEGRIA, MARCIANO JR HERNANDEZ | E45: =BB13 -> 26900 | F45: =BB14 -> 36297 | G45: =IF(E45>0,ROUNDDOWN((NOW()-E45)/365,0),0) -> 52 | H45: =IF(F45>0,ROUNDDOWN((NOW()-F45)/365,0),0) -> 26 | I45: =BB17 -> ADMIN AIDE III | J45: =BB18 -> 10931 | K45: =BB19 -> 2000 | L45: =J45+K45 -> 12931 | M45: =BB20 -> 7761 | N45: =BB21 -> 2999.23 | O45: =IF(L45<10000,10%,IF(L45<13000,25%,30%)) -> 0.25 | P45: =L45*O45 -> 3232.75 | Q45: =-PMT(W45/12,X45,V45) -> 3879.1852 | R45: =M45-N45+Q45 -> 8640.9552 | S45: =J45+K45-R45 -> 4290.0448 | T45: =IF(N45>0,"RENEWAL","NEW") -> RENEWAL | U45: =-PV(W45/12,X45,P45) -> 114461.72 | V45: ='COMPUTATION SHEET'!AA32 -> 137350 | W45: =IF(X45>36,15.81%,12.651%) -> 0.1581 | X45: ='COMPUTATION SHEET'!AC32 -> 48 | Y45: =C45 -> 5 | Z45: =BB23 -> 0 | AA45: =$BB24 -> 42100 | AB45: =$BB25 -> 42095 | AC45: =$BB26 -> 42100 | AD45: =$BB27 -> 42090 | AE45: =$BB28 -> 42100 | AF45: =$BB29 -> 42089 | AG45: =$BB30 -> 42089 | AH45: =$BB31 -> NA | AI45: =$BB32 -> 2014 | AJ45: =$BB33 -> 0 | AL45: =$BB7 -> ALEGRIA | AM45: =$BB8 -> MARCIANO JR | AN45: =$BB9 -> HERNANDEZ | AO45: =$BB10 -> MARILYN SOLAYAO ALEGRIA | AP45: =$BB11 -> P2 BRGY JIA AN JIABONG SAMAR | AQ45: =$BB12 -> 905838005 | AR45: =$BB13 -> 26900 | AS45: =$BB15 -> PROVINCE OF SAMAR5 | AT45: DBP
G46: =IF(E46>0,ROUNDDOWN((NOW()-E46)/365,0),0) -> 0 | H46: =IF(F46>0,ROUNDDOWN((NOW()-F46)/365,0),0) -> 0 | L46: =J46+K46 -> 0 | O46: =IF(L46<10000,10%,IF(L46<13000,25%,30%)) -> 0.1 | P46: =L46*O46 -> 0 | Q46: =-PMT(W46/12,X46,V46) -> #NUM! | R46: =M46-N46+Q46 -> #NUM! | S46: =J46+K46-R46 -> #NUM! | T46: =IF(N46>0,"RENEWAL","NEW") -> NEW | U46: =-PV(W46/12,X46,P46) -> 0 | V46: ='COMPUTATION SHEET'!AA33 -> 0 | W46: =IF(X46>36,15.81%,12.651%) -> 0.12651 | X46: ='COMPUTATION SHEET'!AC33 -> 0 | Y46: =C46 -> 0 | AT46: DBP
C47: 6 | D47: =BD37 -> GACELOS, MANOLITO ABARRACOSO | E47: =BD13 -> 28260 | F47: =BD14 -> 40252 | G47: =IF(E47>0,ROUNDDOWN((NOW()-E47)/365,0),0) -> 48 | H47: =IF(F47>0,ROUNDDOWN((NOW()-F47)/365,0),0) -> 15 | I47: =BD17 -> DRIVER I | J47: =BD18 -> 10505 | K47: =BD19 -> 3650 | L47: =J47+K47 -> 14155 | M47: =BD20 -> 2357.99 | N47: =BD21 -> 0 | O47: =IF(L47<10000,10%,IF(L47<13000,25%,30%)) -> 0.3 | P47: =L47*O47 -> 4246.5 | Q47: =-PMT(W47/12,X47,V47) -> 4244.9329 | R47: =M47-N47+Q47 -> 6602.9229 | S47: =J47+K47-R47 -> 7552.0771 | T47: =IF(N47>0,"RENEWAL","NEW") -> NEW | U47: =-PV(W47/12,X47,P47) -> 150355.49 | V47: ='COMPUTATION SHEET'!AA34 -> 150300 | W47: =IF(X47>36,15.81%,12.651%) -> 0.1581 | X47: ='COMPUTATION SHEET'!AC34 -> 48 | Y47: =C47 -> 6 | Z47: =BD23 -> 0 | AA47: =$BD24 -> 42101 | AB47: =$BD25 -> 42101 | AC47: =$BD26 -> 42101 | AD47: =$BD27 -> 42101 | AE47: =$BD28 -> 42101 | AF47: =$BD29 -> 42101 | AG47: =$BD30 -> 42101 | AH47: =$BD31 -> NA | AI47: =$BD32 -> 2014 | AJ47: =$BD33 -> 0 | AL47: =$BD7 -> GACELOS | AM47: =$BD8 -> MANOLITO | AN47: =$BD9 -> ABARRACOSO | AO47: =$BD10 -> CHERIE N GACELOS | AP47: =$BD11 -> BRGY RAWIS HINABANGAN SAMAR | AQ47: =$BD12 -> 400532413 | AR47: =$BD13 -> 28260 | AS47: =$BD15 -> PROVINCE OF SAMAR6 | AT47: DBP
G48: =IF(E48>0,ROUNDDOWN((NOW()-E48)/365,0),0) -> 0 | H48: =IF(F48>0,ROUNDDOWN((NOW()-F48)/365,0),0) -> 0 | L48: =J48+K48 -> 0 | O48: =IF(L48<10000,10%,IF(L48<13000,25%,30%)) -> 0.1 | P48: =L48*O48 -> 0 | Q48: =-PMT(W48/12,X48,V48) -> #NUM! | R48: =M48-N48+Q48 -> #NUM! | S48: =J48+K48-R48 -> #NUM! | T48: =IF(N48>0,"RENEWAL","NEW") -> NEW | U48: =-PV(W48/12,X48,P48) -> 0 | V48: ='COMPUTATION SHEET'!AA35 -> 0 | W48: =IF(X48>36,15.81%,12.651%) -> 0.12651 | X48: ='COMPUTATION SHEET'!AC35 -> 0 | Y48: =C48 -> 0 | AT48: DBP
C49: 7 | D49: =BF37 -> GONZALES, LEONILA HILONGO | E49: =BF13 -> 20852 | F49: =BF14 -> 30376 | G49: =IF(E49>0,ROUNDDOWN((NOW()-E49)/365,0),0) -> 69 | H49: =IF(F49>0,ROUNDDOWN((NOW()-F49)/365,0),0) -> 43 | I49: =BF17 -> DENTIST II | J49: =BF18 -> 31339 | K49: =BF19 -> 3650 | L49: =J49+K49 -> 34989 | M49: =BF20 -> 21547.08 | N49: =BF21 -> 8404.99 | O49: =IF(L49<10000,10%,IF(L49<13000,25%,30%)) -> 0.3 | P49: =L49*O49 -> 10496.7 | Q49: =-PMT(W49/12,X49,V49) -> 12243.369 | R49: =M49-N49+Q49 -> 25385.459 | S49: =J49+K49-R49 -> 9603.5408 | T49: =IF(N49>0,"RENEWAL","NEW") -> RENEWAL | U49: =-PV(W49/12,X49,P49) -> 371655.82 | V49: ='COMPUTATION SHEET'!AA36 -> 433500 | W49: =IF(X49>36,15.81%,12.651%) -> 0.1581 | X49: ='COMPUTATION SHEET'!AC36 -> 48 | Y49: =C49 -> 7 | Z49: =BF23 -> 0 | AA49: =$BF24 -> 42100 | AB49: =$BF25 -> 42100 | AC49: =$BF26 -> 42095 | AD49: =$BF27 -> 42095 | AE49: =$BF28 -> 42095 | AF49: =$BF29 -> 42095 | AG49: =$BF30 -> 42095 | AH49: =$BF31 -> NA | AI49: =$BF32 -> 2014 | AJ49: =$BF33 -> 0 | AL49: =$BF7 -> GONZALES | AM49: =$BF8 -> LEONILA | AN49: =$BF9 -> HILONGO | AO49: =$BF10 -> 0 | AP49: =$BF11 -> BRGY SAN JOSE ALMAGRO WESTERN SAMAR | AQ49: =$BF12 -> 129842327 | AR49: =$BF13 -> 20852 | AS49: =$BF15 -> PROVINCE OF SAMAR7 | AT49: DBP
G50: =IF(E50>0,ROUNDDOWN((NOW()-E50)/365,0),0) -> 0 | H50: =IF(F50>0,ROUNDDOWN((NOW()-F50)/365,0),0) -> 0 | L50: =J50+K50 -> 0 | O50: =IF(L50<10000,10%,IF(L50<13000,25%,30%)) -> 0.1 | P50: =L50*O50 -> 0 | Q50: =-PMT(W50/12,X50,V50) -> #NUM! | R50: =M50-N50+Q50 -> #NUM! | S50: =J50+K50-R50 -> #NUM! | T50: =IF(N50>0,"RENEWAL","NEW") -> NEW | U50: =-PV(W50/12,X50,P50) -> 0 | V50: ='COMPUTATION SHEET'!AA37 -> 0 | W50: =IF(X50>36,15.81%,12.651%) -> 0.12651 | X50: ='COMPUTATION SHEET'!AC37 -> 0 | Y50: =C50 -> 0 | AT50: DBP
C51: 8 | D51: =BH37 -> MAYOR, CHONA BRANZUELA | E51: =BH13 -> 24599 | F51: =BH14 -> 39114 | G51: =IF(E51>0,ROUNDDOWN((NOW()-E51)/365,0),0) -> 58 | H51: =IF(F51>0,ROUNDDOWN((NOW()-F51)/365,0),0) -> 19 | I51: =BH17 -> DENTAL AIDE | J51: =BH18 -> 11405 | K51: =BH19 -> 3650 | L51: =J51+K51 -> 15055 | M51: =BH20 -> 8448.62 | N51: =BH21 -> 3057.58 | O51: =IF(L51<10000,10%,IF(L51<13000,25%,30%)) -> 0.3 | P51: =L51*O51 -> 4516.5 | Q51: =-PMT(W51/12,X51,V51) -> 5267.3319 | R51: =M51-N51+Q51 -> 10658.372 | S51: =J51+K51-R51 -> 4396.6281 | T51: =IF(N51>0,"RENEWAL","NEW") -> RENEWAL | U51: =-PV(W51/12,X51,P51) -> 159915.36 | V51: ='COMPUTATION SHEET'!AA38 -> 186500 | W51: =IF(X51>36,15.81%,12.651%) -> 0.1581 | X51: ='COMPUTATION SHEET'!AC38 -> 48 | Y51: =C51 -> 8 | Z51: =BH23 -> 0 | AA51: =$BH24 -> 42100 | AB51: =$BH25 -> 42100 | AC51: =$BH26 -> 42100 | AD51: =$BH27 -> 42095 | AE51: =$BH28 -> 42095 | AF51: =$BH29 -> 42095 | AG51: =$BH30 -> 42094 | AH51: =$BH31 -> NA | AI51: =$BH32 -> 2014 | AJ51: =$BH33 -> 0 | AL51: =$BH7 -> MAYOR | AM51: =$BH8 -> CHONA | AN51: =$BH9 -> BRANZUELA | AO51: =$BH10 -> VENG JAYCO B MAYOR | AP51: =$BH11 -> BRGY PANJOBJOBAN ALMAGRO SAMAR | AQ51: =$BH12 -> 947543937 | AR51: =$BH13 -> 24599 | AS51: =$BH15 -> PROVINCE OF SAMAR4 | AT51: DBP
G52: =IF(E52>0,ROUNDDOWN((NOW()-E52)/365,0),0) -> 0 | H52: =IF(F52>0,ROUNDDOWN((NOW()-F52)/365,0),0) -> 0 | L52: =J52+K52 -> 0 | O52: =IF(L52<10000,10%,IF(L52<13000,25%,30%)) -> 0.1 | P52: =L52*O52 -> 0 | Q52: =-PMT(W52/12,X52,V52) -> #NUM! | R52: =M52-N52+Q52 -> #NUM! | S52: =J52+K52-R52 -> #NUM! | T52: =IF(N52>0,"RENEWAL","NEW") -> NEW | U52: =-PV(W52/12,X52,P52) -> 0 | V52: ='COMPUTATION SHEET'!AA39 -> 0 | W52: =IF(X52>36,15.81%,12.651%) -> 0.12651 | X52: ='COMPUTATION SHEET'!AC39 -> 0 | Y52: =C52 -> 0 | AT52: DBP
C53: 9 | D53: =BJ37 -> YBOA, JONAS ABELIDO | E53: =BJ13 -> 25868 | F53: =BJ14 -> 35492 | G53: =IF(E53>0,ROUNDDOWN((NOW()-E53)/365,0),0) -> 55 | H53: =IF(F53>0,ROUNDDOWN((NOW()-F53)/365,0),0) -> 29 | I53: =BJ17 -> ADMIN AIDE VI | J53: =BJ18 -> 13580 | K53: =BJ19 -> 2000 | L53: =J53+K53 -> 15580 | M53: =BJ20 -> 10473.62 | N53: =BJ21 -> 3640.94 | O53: =IF(L53<10000,10%,IF(L53<13000,25%,30%)) -> 0.3 | P53: =L53*O53 -> 4674 | Q53: =-PMT(W53/12,X53,V53) -> 4671.4032 | R53: =M53-N53+Q53 -> 11504.083 | S53: =J53+K53-R53 -> 4075.9168 | T53: =IF(N53>0,"RENEWAL","NEW") -> RENEWAL | U53: =-PV(W53/12,X53,P53) -> 165491.95 | V53: ='COMPUTATION SHEET'!AA40 -> 165400 | W53: =IF(X53>36,15.81%,12.651%) -> 0.1581 | X53: ='COMPUTATION SHEET'!AC40 -> 48 | Y53: =C53 -> 9 | Z53: =BJ23 -> 0 | AA53: =$BJ24 -> 42100 | AB53: =$BJ25 -> 42093 | AC53: =$BJ26 -> 42090 | AD53: =$BJ27 -> 42093 | AE53: =$BJ28 -> 42090 | AF53: =$BJ29 -> 42093 | AG53: =$BJ30 -> 42090 | AH53: =$BJ31 -> NA | AI53: =$BJ32 -> 2014 | AJ53: =$BJ33 -> 0 | AL53: =$BJ7 -> YBOA | AM53: =$BJ8 -> JONAS | AN53: =$BJ9 -> ABELIDO | AO53: =$BJ10 -> NANCY ALBOS YBOA | AP53: =$BJ11 -> 5TH ST COR BANOYO ST BRGY 10 CATBALOGAN CITY SAMAR | AQ53: =$BJ12 -> 174344327 | AR53: =$BJ13 -> 25868 | AS53: =$BJ15 -> PROVINCE OF SAMAR9 | AT53: DBP
G54: =IF(E54>0,ROUNDDOWN((NOW()-E54)/365,0),0) -> 0 | H54: =IF(F54>0,ROUNDDOWN((NOW()-F54)/365,0),0) -> 0 | L54: =J54+K54 -> 0 | O54: =IF(L54<10000,10%,IF(L54<13000,25%,30%)) -> 0.1 | P54: =L54*O54 -> 0 | Q54: =-PMT(W54/12,X54,V54) -> #NUM! | R54: =M54-N54+Q54 -> #NUM! | S54: =J54+K54-R54 -> #NUM! | T54: =IF(N54>0,"RENEWAL","NEW") -> NEW | U54: =-PV(W54/12,X54,P54) -> 0 | V54: ='COMPUTATION SHEET'!AA41 -> 0 | W54: =IF(X54>36,15.81%,12.651%) -> 0.12651 | X54: ='COMPUTATION SHEET'!AC41 -> 0 | Y54: =C54 -> 0 | AT54: DBP
C55: 10 | D55: =BL37 -> GONZALES, RUBIA ABARCAR | E55: =BL13 -> 22656 | F55: =BL14 -> 34319 | G55: =IF(E55>0,ROUNDDOWN((NOW()-E55)/365,0),0) -> 64 | H55: =IF(F55>0,ROUNDDOWN((NOW()-F55)/365,0),0) -> 32 | I55: =BL17 -> LABORATORY AIDE I | J55: =BL18 -> 10373 | K55: =BL19 -> 3650 | L55: =J55+K55 -> 14023 | M55: =BL20 -> 7735.27 | N55: =BL21 -> 2752.49 | O55: =IF(L55<10000,10%,IF(L55<13000,25%,30%)) -> 0.3 | P55: =L55*O55 -> 4206.9 | Q55: =-PMT(W55/12,X55,V55) -> 4205.3926 | R55: =M55-N55+Q55 -> 9188.1726 | S55: =J55+K55-R55 -> 4834.8274 | T55: =IF(N55>0,"RENEWAL","NEW") -> RENEWAL | U55: =-PV(W55/12,X55,P55) -> 148953.37 | V55: ='COMPUTATION SHEET'!AA42 -> 148900 | W55: =IF(X55>36,15.81%,12.651%) -> 0.1581 | X55: ='COMPUTATION SHEET'!AC42 -> 48 | Y55: =C55 -> 10 | Z55: =BL23 -> 0 | AA55: =$BL24 -> 42100 | AB55: =$BL25 -> 42093 | AC55: =$BL26 -> 42100 | AD55: =$BL27 -> 42095 | AE55: =$BL28 -> 42095 | AF55: =$BL29 -> 42095 | AG55: =$BL30 -> 42094 | AH55: =$BL31 -> NA | AI55: =$BL32 -> 2014 | AJ55: =$BL33 -> 0 | AL55: =$BL7 -> GONZALES | AM55: =$BL8 -> RUBIA | AN55: =$BL9 -> ABARCAR | AO55: =$BL10 -> NELSON VILLANUEVA GONZALES | AP55: =$BL11 -> NO 20 B 2 LOT 8 BLISS CANLAPWAS CATBALOGAN CITY | AQ55: =$BL12 -> 166545733 | AR55: =$BL13 -> 22656 | AS55: =$BL15 -> PROVINCE OF SAMAR10 | AT55: DBP
G56: =IF(E56>0,ROUNDDOWN((NOW()-E56)/365,0),0) -> 0 | H56: =IF(F56>0,ROUNDDOWN((NOW()-F56)/365,0),0) -> 0 | L56: =J56+K56 -> 0 | O56: =IF(L56<10000,10%,IF(L56<13000,25%,30%)) -> 0.1 | P56: =L56*O56 -> 0 | Q56: =-PMT(W56/12,X56,V56) -> #NUM! | R56: =M56-N56+Q56 -> #NUM! | S56: =J56+K56-R56 -> #NUM! | T56: =IF(N56>0,"RENEWAL","NEW") -> NEW | U56: =-PV(W56/12,X56,P56) -> 0 | V56: ='COMPUTATION SHEET'!AA43 -> 0 | W56: =IF(X56>36,15.81%,12.651%) -> 0.12651 | X56: ='COMPUTATION SHEET'!AC43 -> 0 | Y56: =C56 -> 0 | AT56: DBP
C57: 11 | D57: =BN37 -> ARCALES, DOMINGO JR JADLOC | E57: =BN13 -> 24098 | F57: =BN14 -> 35506 | G57: =IF(E57>0,ROUNDDOWN((NOW()-E57)/365,0),0) -> 60 | H57: =IF(F57>0,ROUNDDOWN((NOW()-F57)/365,0),0) -> 28 | I57: =BN17 -> AGRICULTURAL TECHNICIAN II | J57: =BN18 -> 15768.87 | K57: =BN19 -> 2000 | L57: =J57+K57 -> 17768.87 | M57: =BN20 -> 12313.58 | N57: =BN21 -> 4207.52 | O57: =IF(L57<10000,10%,IF(L57<13000,25%,30%)) -> 0.3 | P57: =L57*O57 -> 5330.661 | Q57: =-PMT(W57/12,X57,V57) -> 5329.4666 | R57: =M57-N57+Q57 -> 13435.527 | S57: =J57+K57-R57 -> 4333.3434 | T57: =IF(N57>0,"RENEWAL","NEW") -> RENEWAL | U57: =-PV(W57/12,X57,P57) -> 188742.29 | V57: ='COMPUTATION SHEET'!AA44 -> 188700 | W57: =IF(X57>36,15.81%,12.651%) -> 0.1581 | X57: ='COMPUTATION SHEET'!AC44 -> 48 | Y57: =C57 -> 11 | Z57: =BN23 -> 0 | AA57: =$BN24 -> 42100 | AB57: =$BN25 -> 42100 | AC57: =$BN26 -> 42095 | AD57: =$BN27 -> 42093 | AE57: =$BN28 -> 42093 | AF57: =$BN29 -> 42093 | AG57: =$BN30 -> 42095 | AH57: =$BN31 -> NA | AI57: =$BN32 -> 2014 | AJ57: =$BN33 -> 0 | AL57: =$BN7 -> ARCALES | AM57: =$BN8 -> DOMINGO JR | AN57: =$BN9 -> JADLOC | AO57: =$BN10 -> 0 | AP57: =$BN11 -> 491 PUROK 3 BRGY MERCEDES CATBALOGAN CITY | AQ57: =$BN12 -> 914894035 | AR57: =$BN13 -> 24098 | AS57: =$BN15 -> PROVINCE OF SAMAR11 | AT57: DBP
G58: =IF(E58>0,ROUNDDOWN((NOW()-E58)/365,0),0) -> 0 | H58: =IF(F58>0,ROUNDDOWN((NOW()-F58)/365,0),0) -> 0 | L58: =J58+K58 -> 0 | O58: =IF(L58<10000,10%,IF(L58<13000,25%,30%)) -> 0.1 | P58: =L58*O58 -> 0 | Q58: =-PMT(W58/12,X58,V58) -> #NUM! | R58: =M58-N58+Q58 -> #NUM! | S58: =J58+K58-R58 -> #NUM! | T58: =IF(N58>0,"RENEWAL","NEW") -> NEW | U58: =-PV(W58/12,X58,P58) -> 0 | V58: ='COMPUTATION SHEET'!AA45 -> 0 | W58: =IF(X58>36,15.81%,12.651%) -> 0.12651 | X58: ='COMPUTATION SHEET'!AC45 -> 0 | Y58: =C58 -> 0 | AT58: DBP
C59: 12 | D59: =BP37 -> GACELOS, REBECCA TILLES | E59: =BP13 -> 19920 | F59: =BP14 -> 29859 | G59: =IF(E59>0,ROUNDDOWN((NOW()-E59)/365,0),0) -> 71 | H59: =IF(F59>0,ROUNDDOWN((NOW()-F59)/365,0),0) -> 44 | I59: =BP17 -> AGRICULTURAL TECHNOLOGIST I | J59: =BP18 -> 18135 | K59: =BP19 -> 2000 | L59: =J59+K59 -> 20135 | M59: =BP20 -> 14037.39 | N59: =BP21 -> 4652.09 | O59: =IF(L59<10000,10%,IF(L59<13000,25%,30%)) -> 0.3 | P59: =L59*O59 -> 6040.5 | Q59: =-PMT(W59/12,X59,V59) -> 6747.2685 | R59: =M59-N59+Q59 -> 16132.569 | S59: =J59+K59-R59 -> 4002.4315 | T59: =IF(N59>0,"RENEWAL","NEW") -> RENEWAL | U59: =-PV(W59/12,X59,P59) -> 213875.5 | V59: ='COMPUTATION SHEET'!AA46 -> 238900 | W59: =IF(X59>36,15.81%,12.651%) -> 0.1581 | X59: ='COMPUTATION SHEET'!AC46 -> 48 | Y59: =C59 -> 12 | Z59: =BP23 -> 0 | AA59: =$BP24 -> 42101 | AB59: =$BP25 -> 42100 | AC59: =$BP26 -> 42100 | AD59: =$BP27 -> 42093 | AE59: =$BP28 -> 42093 | AF59: =$BP29 -> 42100 | AG59: =$BP30 -> 42093 | AH59: =$BP31 -> NA | AI59: =$BP32 -> 2014 | AJ59: =$BP33 -> 0 | AL59: =$BP7 -> GACELOS | AM59: =$BP8 -> REBECCA | AN59: =$BP9 -> TILLES | AO59: =$BP10 -> 0 | AP59: =$BP11 -> 117 P 2 BRGY MAULONG CATBALOGAN CITY SAMAR | AQ59: =$BP12 -> 131439004 | AR59: =$BP13 -> 19920 | AS59: =$BP15 -> PROVINCE OF SAMAR12 | AT59: DBP
G60: =IF(E60>0,ROUNDDOWN((NOW()-E60)/365,0),0) -> 0 | H60: =IF(F60>0,ROUNDDOWN((NOW()-F60)/365,0),0) -> 0 | L60: =J60+K60 -> 0 | O60: =IF(L60<10000,10%,IF(L60<13000,25%,30%)) -> 0.1 | P60: =L60*O60 -> 0 | Q60: =-PMT(W60/12,X60,V60) -> #NUM! | R60: =M60-N60+Q60 -> #NUM! | S60: =J60+K60-R60 -> #NUM! | T60: =IF(N60>0,"RENEWAL","NEW") -> NEW | U60: =-PV(W60/12,X60,P60) -> 0 | V60: ='COMPUTATION SHEET'!AA47 -> 0 | W60: =IF(X60>36,15.81%,12.651%) -> 0.12651 | X60: ='COMPUTATION SHEET'!AC47 -> 0 | Y60: =C60 -> 0 | AT60: DBP
C61: 13 | D61: =BR37 -> TONELETE, NARCISA CAMUIN | E61: =BR13 -> 21917 | F61: =BR14 -> 29692 | G61: =IF(E61>0,ROUNDDOWN((NOW()-E61)/365,0),0) -> 66 | H61: =IF(F61>0,ROUNDDOWN((NOW()-F61)/365,0),0) -> 44 | I61: =BR17 -> BOARD SECRETARY I | J61: =BR18 -> 23979 | K61: =BR19 -> 2000 | L61: =J61+K61 -> 25979 | M61: =BR20 -> 16345.01 | N61: =BR21 -> 6583.07 | O61: =IF(L61<10000,10%,IF(L61<13000,25%,30%)) -> 0.3 | P61: =L61*O61 -> 7793.7 | Q61: =-PMT(W61/12,X61,V61) -> 9066.0243 | R61: =M61-N61+Q61 -> 18827.964 | S61: =J61+K61-R61 -> 7151.0357 | T61: =IF(N61>0,"RENEWAL","NEW") -> RENEWAL | U61: =-PV(W61/12,X61,P61) -> 275950.92 | V61: ='COMPUTATION SHEET'!AA48 -> 321000 | W61: =IF(X61>36,15.81%,12.651%) -> 0.1581 | X61: ='COMPUTATION SHEET'!AC48 -> 48 | Y61: =C61 -> 13 | Z61: =BR23 -> 0 | AA61: =$BR24 -> 42100 | AB61: =$BR25 -> 42093 | AC61: =$BR26 -> 42087 | AD61: =$BR27 -> 42087 | AE61: =$BR28 -> 42087 | AF61: =$BR29 -> 42086 | AG61: =$BR30 -> 42087 | AH61: =$BR31 -> NA | AI61: =$BR32 -> 2014 | AJ61: =$BR33 -> 0 | AL61: =$BR7 -> TONELETE | AM61: =$BR8 -> NARCISA | AN61: =$BR9 -> CAMUIN | AO61: =$BR10 -> ANTONIO DETALO TONELETE | AP61: =$BR11 -> 270 BRGY MAULONG CATBALOGAN CITY SAMAR | AQ61: =$BR12 -> 133458617 | AR61: =$BR13 -> 21917 | AS61: =$BR15 -> PROVINCE OF SAMAR13 | AT61: DBP
G62: =IF(E62>0,ROUNDDOWN((NOW()-E62)/365,0),0) -> 0 | H62: =IF(F62>0,ROUNDDOWN((NOW()-F62)/365,0),0) -> 0 | L62: =J62+K62 -> 0 | O62: =IF(L62<10000,10%,IF(L62<13000,25%,30%)) -> 0.1 | P62: =L62*O62 -> 0 | Q62: =-PMT(W62/12,X62,V62) -> #NUM! | R62: =M62-N62+Q62 -> #NUM! | S62: =J62+K62-R62 -> #NUM! | T62: =IF(N62>0,"RENEWAL","NEW") -> NEW | U62: =-PV(W62/12,X62,P62) -> 0 | V62: ='COMPUTATION SHEET'!AA49 -> 0 | W62: =IF(X62>36,15.81%,12.651%) -> 0.12651 | X62: ='COMPUTATION SHEET'!AC49 -> 0 | Y62: =C62 -> 0 | AT62: DBP
C63: 14 | D63: =BT37 -> GABON, MA WINONA CON UI | E63: =BT13 -> 25812 | F63: =BT14 -> 37097 | G63: =IF(E63>0,ROUNDDOWN((NOW()-E63)/365,0),0) -> 55 | H63: =IF(F63>0,ROUNDDOWN((NOW()-F63)/365,0),0) -> 24 | I63: =BT17 -> COMPUTER MAINTENANCE TECHNICIAN | J63: =BT18 -> 19495 | K63: =BT19 -> 2000 | L63: =J63+K63 -> 21495 | M63: =BT20 -> 8580.2 | N63: =BT21 -> 5176.43 | O63: =IF(L63<10000,10%,IF(L63<13000,25%,30%)) -> 0.3 | P63: =L63*O63 -> 6448.5 | Q63: =-PMT(W63/12,X63,V63) -> 7521.1285 | R63: =M63-N63+Q63 -> 10924.899 | S63: =J63+K63-R63 -> 10570.101 | T63: =IF(N63>0,"RENEWAL","NEW") -> RENEWAL | U63: =-PV(W63/12,X63,P63) -> 228321.53 | V63: ='COMPUTATION SHEET'!AA50 -> 266300 | W63: =IF(X63>36,15.81%,12.651%) -> 0.1581 | X63: ='COMPUTATION SHEET'!AC50 -> 48 | Y63: =C63 -> 14 | Z63: =BT23 -> 0 | AA63: =$BT24 -> 42100 | AB63: =$BT25 -> 42093 | AC63: =$BT26 -> 42086 | AD63: =$BT27 -> 42086 | AE63: =$BT28 -> 42086 | AF63: =$BT29 -> 42088 | AG63: =$BT30 -> 42086 | AH63: =$BT31 -> NA | AI63: =$BT32 -> 2014 | AJ63: =$BT33 -> 0 | AL63: =$BT7 -> GABON | AM63: =$BT8 -> MA WINONA | AN63: =$BT9 -> CON UI | AO63: =$BT10 -> ALEJANDRO CUNA GABON | AP63: =$BT11 -> 451 GABON BLVD BRGY 3 PARANAS WRIGHT SAMAR | AQ63: =$BT12 -> 178650362 | AR63: =$BT13 -> 25812 | AS63: =$BT15 -> PROVINCE OF SAMAR14 | AT63: DBP
G64: =IF(E64>0,ROUNDDOWN((NOW()-E64)/365,0),0) -> 0 | H64: =IF(F64>0,ROUNDDOWN((NOW()-F64)/365,0),0) -> 0 | L64: =J64+K64 -> 0 | O64: =IF(L64<10000,10%,IF(L64<13000,25%,30%)) -> 0.1 | P64: =L64*O64 -> 0 | Q64: =-PMT(W64/12,X64,V64) -> #NUM! | R64: =M64-N64+Q64 -> #NUM! | S64: =J64+K64-R64 -> #NUM! | T64: =IF(N64>0,"RENEWAL","NEW") -> NEW | U64: =-PV(W64/12,X64,P64) -> 0 | V64: ='COMPUTATION SHEET'!AA51 -> 0 | W64: =IF(X64>36,15.81%,12.651%) -> 0.12651 | X64: ='COMPUTATION SHEET'!AC51 -> 0 | Y64: =C64 -> 0 | AT64: DBP
C65: 15 | D65: =BV37 -> , | E65: =BV13 -> 0 | F65: =BV14 -> 0 | G65: =IF(E65>0,ROUNDDOWN((NOW()-E65)/365,0),0) -> 0 | H65: =IF(F65>0,ROUNDDOWN((NOW()-F65)/365,0),0) -> 0 | I65: =BV17 -> 0 | J65: =BV18 -> 0 | K65: =BV19 -> 0 | L65: =J65+K65 -> 0 | M65: =BV20 -> 0 | N65: =BV21 -> 0 | O65: =IF(L65<10000,10%,IF(L65<13000,25%,30%)) -> 0.1 | P65: =L65*O65 -> 0 | Q65: =-PMT(W65/12,X65,V65) -> #NUM! | R65: =M65-N65+Q65 -> #NUM! | S65: =J65+K65-R65 -> #NUM! | T65: =IF(N65>0,"RENEWAL","NEW") -> NEW | U65: =-PV(W65/12,X65,P65) -> 0 | V65: ='COMPUTATION SHEET'!AA52 -> 0 | W65: =IF(X65>36,15.81%,12.651%) -> 0.12651 | X65: ='COMPUTATION SHEET'!AC52 -> 0 | Y65: =C65 -> 15 | Z65: =BV23 -> 0 | AA65: =$BV24 -> 0 | AB65: =$BV25 -> 0 | AC65: =$BV26 -> 0 | AD65: =$BV27 -> 0 | AE65: =$BV28 -> 0 | AF65: =$BV29 -> 0 | AG65: =$BV30 -> 0 | AH65: =$BV31 -> 0 | AI65: =$BV32 -> 0 | AJ65: =$BV33 -> 0 | AL65: =$BV7 -> 0 | AM65: =$BV8 -> 0 | AN65: =$BV9 -> 0 | AO65: =$BV10 -> 0 | AP65: =$BV11 -> 0 | AQ65: =$BV12 -> 0 | AR65: =$BV13 -> 0 | AS65: =$BV15 -> 0 | AT65: DBP
G66: =IF(E66>0,ROUNDDOWN((NOW()-E66)/365,0),0) -> 0 | H66: =IF(F66>0,ROUNDDOWN((NOW()-F66)/365,0),0) -> 0 | L66: =J66+K66 -> 0 | O66: =IF(L66<10000,10%,IF(L66<13000,25%,30%)) -> 0.1 | P66: =L66*O66 -> 0 | Q66: =-PMT(W66/12,X66,V66) -> #NUM! | R66: =M66-N66+Q66 -> #NUM! | S66: =J66+K66-R66 -> #NUM! | T66: =IF(N66>0,"RENEWAL","NEW") -> NEW | U66: =-PV(W66/12,X66,P66) -> 0 | V66: ='COMPUTATION SHEET'!AA53 -> 0 | W66: =IF(X66>36,15.81%,12.651%) -> 0.12651 | X66: ='COMPUTATION SHEET'!AC53 -> 0 | Y66: =C66 -> 0 | AT66: DBP
C67: 16 | D67: =BX37 -> , | E67: =BX13 -> 0 | F67: =BX14 -> 0 | G67: =IF(E67>0,ROUNDDOWN((NOW()-E67)/365,0),0) -> 0 | H67: =IF(F67>0,ROUNDDOWN((NOW()-F67)/365,0),0) -> 0 | I67: =BX17 -> 0 | J67: =BX18 -> 0 | K67: =BX19 -> 0 | L67: =J67+K67 -> 0 | M67: =BX20 -> 0 | N67: =BX21 -> 0 | O67: =IF(L67<10000,10%,IF(L67<13000,25%,30%)) -> 0.1 | P67: =L67*O67 -> 0 | Q67: =-PMT(W67/12,X67,V67) -> #NUM! | R67: =M67-N67+Q67 -> #NUM! | S67: =J67+K67-R67 -> #NUM! | T67: =IF(N67>0,"RENEWAL","NEW") -> NEW | U67: =-PV(W67/12,X67,P67) -> 0 | V67: ='COMPUTATION SHEET'!AA54 -> 0 | W67: =IF(X67>36,15.81%,12.651%) -> 0.12651 | X67: ='COMPUTATION SHEET'!AC54 -> 0 | Y67: =C67 -> 16 | Z67: =BX23 -> 0 | AA67: =$BX24 -> 0 | AB67: =$BX25 -> 0 | AC67: =$BX26 -> 0 | AD67: =$BX27 -> 0 | AE67: =$BX28 -> 0 | AF67: =$BX29 -> 0 | AG67: =$BX30 -> 0 | AH67: =$BX31 -> 0 | AI67: =$BX32 -> 0 | AJ67: =$BX33 -> 0 | AL67: =$BX7 -> 0 | AM67: =$BX8 -> 0 | AN67: =$BX9 -> 0 | AO67: =$BX10 -> 0 | AP67: =$BX11 -> 0 | AQ67: =$BX12 -> 0 | AR67: =$BX13 -> 0 | AS67: =$BX15 -> 0 | AT67: DBP
G68: =IF(E68>0,ROUNDDOWN((NOW()-E68)/365,0),0) -> 0 | H68: =IF(F68>0,ROUNDDOWN((NOW()-F68)/365,0),0) -> 0 | L68: =J68+K68 -> 0 | O68: =IF(L68<10000,10%,IF(L68<13000,25%,30%)) -> 0.1 | P68: =L68*O68 -> 0 | Q68: =-PMT(W68/12,X68,V68) -> #NUM! | R68: =M68-N68+Q68 -> #NUM! | S68: =J68+K68-R68 -> #NUM! | T68: =IF(N68>0,"RENEWAL","NEW") -> NEW | U68: =-PV(W68/12,X68,P68) -> 0 | V68: ='COMPUTATION SHEET'!AA55 -> 0 | W68: =IF(X68>36,15.81%,12.651%) -> 0.12651 | X68: ='COMPUTATION SHEET'!AC55 -> 0 | Y68: =C68 -> 0 | AT68: DBP
C69: 17 | D69: =BZ37 -> , | E69: =BZ13 -> 0 | F69: =BZ14 -> 0 | G69: =IF(E69>0,ROUNDDOWN((NOW()-E69)/365,0),0) -> 0 | H69: =IF(F69>0,ROUNDDOWN((NOW()-F69)/365,0),0) -> 0 | I69: =BZ17 -> 0 | J69: =BZ18 -> 0 | K69: =BZ19 -> 0 | L69: =J69+K69 -> 0 | M69: =BZ20 -> 0 | N69: =BZ21 -> 0 | O69: =IF(L69<10000,10%,IF(L69<13000,25%,30%)) -> 0.1 | P69: =L69*O69 -> 0 | Q69: =-PMT(W69/12,X69,V69) -> #NUM! | R69: =M69-N69+Q69 -> #NUM! | S69: =J69+K69-R69 -> #NUM! | T69: =IF(N69>0,"RENEWAL","NEW") -> NEW | U69: =-PV(W69/12,X69,P69) -> 0 | V69: ='COMPUTATION SHEET'!AA56 -> 0 | W69: =IF(X69>36,15.81%,12.651%) -> 0.12651 | X69: ='COMPUTATION SHEET'!AC56 -> 0 | Y69: =C69 -> 17 | Z69: =BZ23 -> 0 | AA69: =$BZ24 -> 0 | AB69: =$BZ25 -> 0 | AC69: =$BZ26 -> 0 | AD69: =$BZ27 -> 0 | AE69: =$BZ28 -> 0 | AF69: =$BZ29 -> 0 | AG69: =$BZ30 -> 0 | AH69: =$BZ31 -> 0 | AI69: =$BZ32 -> 0 | AJ69: =$BZ33 -> 0 | AL69: =$BZ7 -> 0 | AM69: =$BZ8 -> 0 | AN69: =$BZ9 -> 0 | AO69: =$BZ10 -> 0 | AP69: =$BZ11 -> 0 | AQ69: =$BZ12 -> 0 | AR69: =$BZ13 -> 0 | AS69: =$BZ15 -> 0 | AT69: DBP
G70: =IF(E70>0,ROUNDDOWN((NOW()-E70)/365,0),0) -> 0 | H70: =IF(F70>0,ROUNDDOWN((NOW()-F70)/365,0),0) -> 0 | L70: =J70+K70 -> 0 | O70: =IF(L70<10000,10%,IF(L70<13000,25%,30%)) -> 0.1 | P70: =L70*O70 -> 0 | Q70: =-PMT(W70/12,X70,V70) -> #NUM! | R70: =M70-N70+Q70 -> #NUM! | S70: =J70+K70-R70 -> #NUM! | T70: =IF(N70>0,"RENEWAL","NEW") -> NEW | U70: =-PV(W70/12,X70,P70) -> 0 | V70: ='COMPUTATION SHEET'!AA57 -> 0 | W70: =IF(X70>36,15.81%,12.651%) -> 0.12651 | X70: ='COMPUTATION SHEET'!AC57 -> 0 | Y70: =C70 -> 0 | AT70: DBP
C71: 18 | D71: =CB37 -> , | E71: =CB13 -> 0 | F71: =CB14 -> 0 | G71: =IF(E71>0,ROUNDDOWN((NOW()-E71)/365,0),0) -> 0 | H71: =IF(F71>0,ROUNDDOWN((NOW()-F71)/365,0),0) -> 0 | I71: =CB17 -> 0 | J71: =CB18 -> 0 | K71: =CB19 -> 0 | L71: =J71+K71 -> 0 | M71: =CB20 -> 0 | N71: =CB21 -> 0 | O71: =IF(L71<10000,10%,IF(L71<13000,25%,30%)) -> 0.1 | P71: =L71*O71 -> 0 | Q71: =-PMT(W71/12,X71,V71) -> #NUM! | R71: =M71-N71+Q71 -> #NUM! | S71: =J71+K71-R71 -> #NUM! | T71: =IF(N71>0,"RENEWAL","NEW") -> NEW | U71: =-PV(W71/12,X71,P71) -> 0 | V71: ='COMPUTATION SHEET'!AA58 -> 0 | W71: =IF(X71>36,15.81%,12.651%) -> 0.12651 | X71: ='COMPUTATION SHEET'!AC58 -> 0 | Y71: =C71 -> 18 | Z71: =CB23 -> 0 | AA71: =$CB24 -> 0 | AB71: =$CB25 -> 0 | AC71: =$CB26 -> 0 | AD71: =$CB27 -> 0 | AE71: =$CB28 -> 0 | AF71: =$CB29 -> 0 | AG71: =$CB30 -> 0 | AH71: =$CB31 -> 0 | AI71: =$CB32 -> 0 | AJ71: =$CB33 -> 0 | AL71: =$CB7 -> 0 | AM71: =$CB8 -> 0 | AN71: =$CB9 -> 0 | AO71: =$CB10 -> 0 | AP71: =$CB11 -> 0 | AQ71: =$CB12 -> 0 | AR71: =$CB13 -> 0 | AS71: =$CB15 -> 0 | AT71: DBP
G72: =IF(E72>0,ROUNDDOWN((NOW()-E72)/365,0),0) -> 0 | H72: =IF(F72>0,ROUNDDOWN((NOW()-F72)/365,0),0) -> 0 | L72: =J72+K72 -> 0 | O72: =IF(L72<10000,10%,IF(L72<13000,25%,30%)) -> 0.1 | P72: =L72*O72 -> 0 | Q72: =-PMT(W72/12,X72,V72) -> #NUM! | R72: =M72-N72+Q72 -> #NUM! | S72: =J72+K72-R72 -> #NUM! | T72: =IF(N72>0,"RENEWAL","NEW") -> NEW | U72: =-PV(W72/12,X72,P72) -> 0 | V72: ='COMPUTATION SHEET'!AA59 -> 0 | W72: =IF(X72>36,15.81%,12.651%) -> 0.12651 | X72: ='COMPUTATION SHEET'!AC59 -> 0 | Y72: =C72 -> 0 | AT72: DBP
C73: 19 | D73: =CD37 -> , | E73: =CD13 -> 0 | F73: =CD14 -> 0 | G73: =IF(E73>0,ROUNDDOWN((NOW()-E73)/365,0),0) -> 0 | H73: =IF(F73>0,ROUNDDOWN((NOW()-F73)/365,0),0) -> 0 | I73: =CD17 -> 0 | J73: =CD18 -> 0 | K73: =CD19 -> 0 | L73: =J73+K73 -> 0 | M73: =CD20 -> 0 | N73: =CD21 -> 0 | O73: =IF(L73<10000,10%,IF(L73<13000,25%,30%)) -> 0.1 | P73: =L73*O73 -> 0 | Q73: =-PMT(W73/12,X73,V73) -> #NUM! | R73: =M73-N73+Q73 -> #NUM! | S73: =J73+K73-R73 -> #NUM! | T73: =IF(N73>0,"RENEWAL","NEW") -> NEW | U73: =-PV(W73/12,X73,P73) -> 0 | V73: ='COMPUTATION SHEET'!AA60 -> 0 | W73: =IF(X73>36,15.81%,12.651%) -> 0.12651 | X73: ='COMPUTATION SHEET'!AC60 -> 0 | Y73: =C73 -> 19 | Z73: =CD23 -> 0 | AA73: =$CD24 -> 0 | AB73: =$CD25 -> 0 | AC73: =$CD26 -> 0 | AD73: =$CD27 -> 0 | AE73: =$CD28 -> 0 | AF73: =$CD29 -> 0 | AG73: =$CD30 -> 0 | AH73: =$CD31 -> 0 | AI73: =$CD32 -> 0 | AJ73: =$CD33 -> 0 | AL73: =$CD7 -> 0 | AM73: =$CD8 -> 0 | AN73: =$CD9 -> 0 | AO73: =$CD10 -> 0 | AP73: =$CD11 -> 0 | AQ73: =$CD12 -> 0 | AR73: =$CD13 -> 0 | AS73: =$CD15 -> 0 | AT73: DBP
G74: =IF(E74>0,ROUNDDOWN((NOW()-E74)/365,0),0) -> 0 | H74: =IF(F74>0,ROUNDDOWN((NOW()-F74)/365,0),0) -> 0 | L74: =J74+K74 -> 0 | O74: =IF(L74<10000,10%,IF(L74<13000,25%,30%)) -> 0.1 | P74: =L74*O74 -> 0 | Q74: =-PMT(W74/12,X74,V74) -> #NUM! | R74: =M74-N74+Q74 -> #NUM! | S74: =J74+K74-R74 -> #NUM! | T74: =IF(N74>0,"RENEWAL","NEW") -> NEW | U74: =-PV(W74/12,X74,P74) -> 0 | V74: ='COMPUTATION SHEET'!AA61 -> 0 | W74: =IF(X74>36,15.81%,12.651%) -> 0.12651 | X74: ='COMPUTATION SHEET'!AC61 -> 0 | Y74: =C74 -> 0 | AT74: DBP
C75: 20 | D75: =CF37 -> , | E75: =CF13 -> 0 | F75: =CF14 -> 0 | G75: =IF(E75>0,ROUNDDOWN((NOW()-E75)/365,0),0) -> 0 | H75: =IF(F75>0,ROUNDDOWN((NOW()-F75)/365,0),0) -> 0 | I75: =CF17 -> 0 | J75: =CF18 -> 0 | K75: =CF19 -> 0 | L75: =J75+K75 -> 0 | M75: =CF20 -> 0 | N75: =CF21 -> 0 | O75: =IF(L75<10000,10%,IF(L75<13000,25%,30%)) -> 0.1 | P75: =L75*O75 -> 0 | Q75: =-PMT(W75/12,X75,V75) -> #NUM! | R75: =M75-N75+Q75 -> #NUM! | S75: =J75+K75-R75 -> #NUM! | T75: =IF(N75>0,"RENEWAL","NEW") -> NEW | U75: =-PV(W75/12,X75,P75) -> 0 | V75: ='COMPUTATION SHEET'!AA62 -> 0 | W75: =IF(X75>36,15.81%,12.651%) -> 0.12651 | X75: ='COMPUTATION SHEET'!AC62 -> 0 | Y75: =C75 -> 20 | Z75: =CF23 -> 15-0070 | AA75: =$CF24 -> 0 | AB75: =$CF25 -> 0 | AC75: =$CF26 -> 0 | AD75: =$CF27 -> 0 | AE75: =$CF28 -> 0 | AF75: =$CF29 -> 0 | AG75: =$CF30 -> 0 | AH75: =$CF31 -> 0 | AI75: =$CF32 -> 0 | AJ75: =$CF33 -> - | AL75: =$CF7 -> 0 | AM75: =$CF8 -> 0 | AN75: =$CF9 -> 0 | AO75: =$CF10 -> 0 | AP75: =$CF11 -> 0 | AQ75: =$CF12 -> 0 | AR75: =$CF13 -> 0 | AS75: =$CF15 -> 0 | AT75: DBP
Z76: 19 | AA76: 20 | AB76: 21 | AC76: 22 | AD76: 23 | AE76: 24 | AF76: 25 | AG76: 26 | AH76: 27 | AI76: 28 | AJ76: 29
AL87: IB_FNAM | AM87: IB_MNAM | AN87: IB_LNAM | AO87: IB_BIRTH | AP87: IB_TAN | AQ87: IB_SPOUSE | AR87: IB_ADDR1 | AS87: RECKEY | AT87: IB_BANKCD

Sheet COMPUTATION SHEET
F1: DEVELOPMENT BANK OF THE PHILIPPINES | AH1: GUIDE
F2: =CONCATENATE(Signatories!C13," BRANCH, ",Signatories!C14) -> CATBALOGAN BRANCH, CATBALOGAN CITY, SAMAR | AH2: Years | AI2: Loanable | AJ2: Loan | AK2: Loan
AH3: in Service | AI3: Amount | AJ3: Term | AK3: Renewal
AH4: 1 | AI4: 3 | AJ4: 1 | AK4: 6 mos
F5: =LEFT('INPUT FIELDS'!D15,LEN('INPUT FIELDS'!D15)-1) -> PROVINCE OF SAMAR
F6: ='INPUT FIELDS'!D6 -> OT N0. 15-005 DATED APRIL 7, 2015 | AH6: 2 | AI6: 4 | AJ6: 2 | AK6: 1 year
AH7: 3 | AI7: 5 | AJ7: 3 | AK7: 1 year
B8: INPUT | C8: INPUT | H8: No. of Years in Service | J8: Monthly Basic Pay | K8: ACA/PERA/ RATA/ Others | L8: Gross | M8: Total Deductions Per Cert. of NTHP | N8: Less: Existing DBP Loan | P8: Maximum | R8: Maximum | S8: Add: New Amortization | T8: New Total Deductions | U8: Monthly Net Take Home pay | V8: Loan Type (New/Ren) | W8: NTHP | X8: NTHP | Y8: AMORT | AA8: Amount of Loan | AC8: Term of Loan (Months) | AD8: EVALUATION CHECK | AH8: 4 | AI8: 6 | AJ8: 3 | AK8: 1 year
B9: BIRTHDAY | C9: DATE | F9: Name of Applicant | G9: Age | I9: Position | L9: Monthly | O9: IGIR % | P9: Loan | Q9: IGIR % | R9: Loan | W9: add dbp | X9: less | Y9: TO | Z9: Maximum | AB9: Interest | AH9: 5 | AI9: 7 | AJ9: 3 | AK9: 1 year
C10: PERMANENT | L10: Income | P10: Installment | Q10: (if RENEWAL) | R10: Installment | W10: loan | X10: 4K GAA | Y10: USE | Z10: Loanable Amount | AB10: Rate | AH10: 6 | AI10: 8 | AJ10: 3 | AK10: 1 year
R11: (If RENEWAL) | Y11: (LI VS GAA) | AE11: IGIR | AF11: 4K NTHP
F12: PROVINCIAL ENGINEERING OFFICE
E14: 1 | G14: =ROUNDDOWN((NOW()-B14)/365,0) -> 126 | H14: =ROUNDDOWN((NOW()-C14)/365,0) -> 126 | N14: 0 | S14: =-PMT(15%/12,AC14,AA14) -> #REF! | T14: =M14-N14+S14 -> #REF! | U14: =J14+K14-T14 -> #REF! | V14: NEW | AA14: =ROUNDDOWN(J14*#REF!,-2) -> #REF! | AC14: 36 | AF14: =IF(U14<3000,"ALERT - NTHP IS BELOW 3K","GO") -> #REF! | AG14: =S14*2 -> #REF!
G15: =ROUNDDOWN((NOW()-B15)/365,0) -> 126 | H15: =ROUNDDOWN((NOW()-C15)/365,0) -> 126 | N15: 0 | T15: =M15-N15+S15 -> 0 | U15: =J15+K15-T15 -> 0 | AF15: =IF(J15<J14,"ALERT - ADD CO-MAKER", "GO") -> GO
G16: =ROUNDDOWN((NOW()-B16)/365,0) -> 126 | H16: =ROUNDDOWN((NOW()-C16)/365,0) -> 126 | N16: 0 | T16: =M16-N16+S16 -> 0 | U16: =J16+K16-T16 -> 0 | AF16: =IF(J16<J15,"ALERT - ADD CO-MAKER", "GO") -> GO
E18: 2 | G18: =ROUNDDOWN((NOW()-B18)/365,0) -> 126 | H18: =ROUNDDOWN((NOW()-C18)/365,0) -> 126 | N18: 0 | S18: =-PMT(15%/12,AC18,AA18) -> #REF! | T18: =M18-N18+S18 -> #REF! | U18: =J18+K18-T18 -> #REF! | V18: NEW | AA18: =ROUNDDOWN(J18*#REF!,-2) -> #REF! | AC18: 36 | AF18: =IF(U18<3000,"ALERT - NTHP IS BELOW 3K","GO") -> #REF! | AG18: =S18*2 -> #REF!
G19: =ROUNDDOWN((NOW()-B19)/365,0) -> 126 | H19: =ROUNDDOWN((NOW()-C19)/365,0) -> 126 | T19: =M19-N19+S19 -> 0 | U19: =J19+K19-T19 -> 0 | AF19: =IF(J19<J18,"ALERT - ADD CO-MAKER", "GO") -> GO
G20: =ROUNDDOWN((NOW()-B20)/365,0) -> 126 | H20: =ROUNDDOWN((NOW()-C20)/365,0) -> 126 | T20: =M20-N20+S20 -> 0 | U20: =J20+K20-T20 -> 0 | AF20: =IF(J20<J19,"ALERT - ADD CO-MAKER", "GO") -> GO
F23: =IF('INPUT FIELDS'!D16>0,'INPUT FIELDS'!D16,"") -> PROVINCIAL TREASURER OFFICE
B24: ='INPUT FIELDS'!E37 -> 29144 | C24: ='INPUT FIELDS'!F37 -> 39218 | E24: =IF(B24>0,1," ") -> 1 | F24: =IF(B24>0,'INPUT FIELDS'!D37," ") -> RABADAM, MARIA EMY TAN | G24: =IF(B24>0,'INPUT FIELDS'!G37," ") -> 46 | H24: =IF(B24>0,'INPUT FIELDS'!H37," ") -> 18 | I24: =IF(B24>0,'INPUT FIELDS'!I37," ") -> ADMIN AIDE I | J24: =IF(B24>0,'INPUT FIELDS'!J37," ") -> 38000 | K24: =IF(B24>0,'INPUT FIELDS'!K37," ") -> 2000 | L24: =IF(B24>0,'INPUT FIELDS'!L37," ") -> 40000 | M24: =IF(B24>0,'INPUT FIELDS'!M37," ") -> 26000 | N24: =IF(B24>0,'INPUT FIELDS'!N37," ") -> 5000 | O24: =IF(B24>0,IF(V24="NEW",'INPUT FIELDS'!O37,Q24)," ") -> 0.4 | P24: =IF(B24>0,IF(V24="NEW",'INPUT FIELDS'!P37,R24)," ") -> 16000 | Q24: =IF(L24<10000,20%,IF(L24<13000,30%,IF(L24<38000,35%,40%))) -> 0.4 | R24: =Q24*L24 -> 16000 | S24: =IF(B24>0,'INPUT FIELDS'!Q37," ") -> 6392.3145 | T24: =IF(B24>0,'INPUT FIELDS'!R37," ") -> 27392.315 | U24: =IF(B24>0,'INPUT FIELDS'!S37," ") -> 12607.685 | V24: =IF(B24>0,'INPUT FIELDS'!T37," ") -> RENEWAL | W24: =L24-M24+N24 -> 19000 | X24: =W24-4000 -> 15000 | Y24: =IF(P24<X24,P24,X24) -> 15000 | Z24: =IF(B24>0,-PV(AB24/12,AC24,Y24),"") -> 168248.92 | AA24: 71700 | AB24: =IF(B24>0,'INPUT FIELDS'!W37," ") -> 0.12651 | AC24: 12 | AE24: =IF(AA24>0,IF(P24<S24,"CHK IGIR","GO")," ") -> GO | AF24: =IF(AA24>0,IF(U24<4000," NTHP BELOW 4K","GO")," ") -> GO
F25: =IF('INPUT FIELDS'!AV16>0,'INPUT FIELDS'!AV16,"") -> PROVINCIAL ENGINEERING OFFICE | G25: =IF(E25>0,'INPUT FIELDS'!G38," ") | H25: =IF(E25>0,'INPUT FIELDS'!H38," ") | I25: =IF(E25>0,'INPUT FIELDS'!I38," ") | J25: =IF(E25>0,'INPUT FIELDS'!J38," ") | K25: =IF(E25>0,'INPUT FIELDS'!K38," ") | L25: =IF(E25>0,'INPUT FIELDS'!L38," ") | M25: =IF(E25>0,'INPUT FIELDS'!M38," ") | N25: =IF(E25>0,'INPUT FIELDS'!N38," ") | O25: =IF(E25>0,'INPUT FIELDS'!O38," ") | P25: =IF(E25>0,'INPUT FIELDS'!P38," ") | S25: =IF(E25>0,'INPUT FIELDS'!Q38," ") | T25: =IF(E25>0,'INPUT FIELDS'!R38," ") | U25: =IF(E25>0,'INPUT FIELDS'!S38," ") | V25: =IF(E25>0,'INPUT FIELDS'!T38," ") | Z25: =IF(E25>0,'INPUT FIELDS'!U38," ")
B26: ='INPUT FIELDS'!E39 -> 30469 | C26: ='INPUT FIELDS'!F39 -> 40525 | E26: =IF(B26>0,2," ") -> 2 | F26: =IF(B26>0,'INPUT FIELDS'!D39," ") -> LEJAS, ALLAN GULFERIC | G26: =IF(B26>0,'INPUT FIELDS'!G39," ") -> 42 | H26: =IF(B26>0,'INPUT FIELDS'!H39," ") -> 15 | I26: =IF(B26>0,'INPUT FIELDS'!I39," ") -> CM CAPATAZ | J26: =IF(B26>0,'INPUT FIELDS'!J39," ") -> 12139 | K26: =IF(B26>0,'INPUT FIELDS'!K39," ") -> 2000 | L26: =IF(B26>0,'INPUT FIELDS'!L39," ") -> 14139 | M26: =IF(B26>0,'INPUT FIELDS'!M39," ") -> 6939.36 | N26: =IF(B26>0,'INPUT FIELDS'!N39," ") -> 0 | O26: =IF(B26>0,IF(V26="NEW",'INPUT FIELDS'!O39,Q26)," ") -> 0.3 | P26: =IF(B26>0,IF(V26="NEW",'INPUT FIELDS'!P39,R26)," ") -> 4241.7 | Q26: =IF(L26<10000,20%,IF(L26<13000,30%,IF(L26<38000,35%,40%))) -> 0.35 | R26: =Q26*L26 -> 4948.65 | S26: =IF(B26>0,'INPUT FIELDS'!Q39," ") -> 3191.4665 | T26: =IF(B26>0,'INPUT FIELDS'!R39," ") -> 10130.826 | U26: =IF(B26>0,'INPUT FIELDS'!S39," ") -> 4008.1735 | V26: =IF(B26>0,'INPUT FIELDS'!T39," ") -> NEW | W26: =L26-M26+N26 -> 7199.64 | X26: =W26-4000 -> 3199.64 | Y26: =IF(P26<X26,P26,X26) -> 3199.64 | Z26: =IF(B26>0,-PV(AB26/12,AC26,Y26),"") -> 113289.4 | AA26: 113000 | AB26: =IF(B26>0,'INPUT FIELDS'!W39," ") -> 0.1581 | AC26: 48 | AE26: =IF(AA26>0,IF(P26<S26,"CHK IGIR","GO")," ") -> GO | AF26: =IF(AA26>0,IF(U26<4000," NTHP BELOW 4K","GO")," ") -> GO
F27: =IF('INPUT FIELDS'!AX16>0,'INPUT FIELDS'!AX16,"") -> PROVINCIAL AGRICULTURE OFFICE | G27: =IF(E27>0,'INPUT FIELDS'!G40," ") | H27: =IF(E27>0,'INPUT FIELDS'!H40," ") | I27: =IF(E27>0,'INPUT FIELDS'!I40," ") | J27: =IF(E27>0,'INPUT FIELDS'!J40," ") | K27: =IF(E27>0,'INPUT FIELDS'!K40," ") | L27: =IF(E27>0,'INPUT FIELDS'!L40," ") | M27: =IF(E27>0,'INPUT FIELDS'!M40," ") | N27: =IF(E27>0,'INPUT FIELDS'!N40," ") | O27: =IF(E27>0,'INPUT FIELDS'!O40," ") | P27: =IF(E27>0,'INPUT FIELDS'!P40," ") | S27: =IF(E27>0,'INPUT FIELDS'!Q40," ") | T27: =IF(E27>0,'INPUT FIELDS'!R40," ") | U27: =IF(E27>0,'INPUT FIELDS'!S40," ") | V27: =IF(E27>0,'INPUT FIELDS'!T40," ") | Z27: =IF(E27>0,'INPUT FIELDS'!U40," ")
B28: ='INPUT FIELDS'!E41 -> 112566 | C28: ='INPUT FIELDS'!F41 -> 34541 | E28: =IF(B28>0,3," ") -> 3 | F28: =IF(B28>0,'INPUT FIELDS'!D41," ") -> NUNEZ, JOSE JR ADESAS | G28: =IF(B28>0,'INPUT FIELDS'!G41," ") -> -182 | H28: =IF(B28>0,'INPUT FIELDS'!H41," ") -> 31 | I28: =IF(B28>0,'INPUT FIELDS'!I41," ") -> DRAFTSMAN I | J28: =IF(B28>0,'INPUT FIELDS'!J41," ") -> 13853 | K28: =IF(B28>0,'INPUT FIELDS'!K41," ") -> 2000 | L28: =IF(B28>0,'INPUT FIELDS'!L41," ") -> 15853 | M28: =IF(B28>0,'INPUT FIELDS'!M41," ") -> 9753.9 | N28: =IF(B28>0,'INPUT FIELDS'!N41," ") -> 3714.69 | O28: =IF(B28>0,IF(V28="NEW",'INPUT FIELDS'!O41,Q28)," ") -> 0.35 | P28: =IF(B28>0,IF(V28="NEW",'INPUT FIELDS'!P41,R28)," ") -> 5548.55 | Q28: =IF(L28<10000,20%,IF(L28<13000,30%,IF(L28<38000,35%,40%))) -> 0.35 | R28: =Q28*L28 -> 5548.55 | S28: =IF(B28>0,'INPUT FIELDS'!Q41," ") -> 5546.9382 | T28: =IF(B28>0,'INPUT FIELDS'!R41," ") -> 11586.148 | U28: =IF(B28>0,'INPUT FIELDS'!S41," ") -> 4266.8518 | V28: =IF(B28>0,'INPUT FIELDS'!T41," ") -> RENEWAL | W28: =L28-M28+N28 -> 9813.79 | X28: =W28-4000 -> 5813.79 | Y28: =IF(P28<X28,P28,X28) -> 5548.55 | Z28: =IF(B28>0,-PV(AB28/12,AC28,Y28),"") -> 196457.07 | AA28: 196400 | AB28: =IF(B28>0,'INPUT FIELDS'!W41," ") -> 0.1581 | AC28: 48 | AE28: =IF(AA28>0,IF(P28<S28,"CHK IGIR","GO")," ") -> GO | AF28: =IF(AA28>0,IF(U28<4000," NTHP BELOW 4K","GO")," ") -> GO
F29: =IF('INPUT FIELDS'!AZ16>0,'INPUT FIELDS'!AZ16,"") -> PROVINCIAL WARDENS OFFICE | G29: =IF(E29>0,'INPUT FIELDS'!G42," ") | H29: =IF(E29>0,'INPUT FIELDS'!H42," ") | I29: =IF(E29>0,'INPUT FIELDS'!I42," ") | J29: =IF(E29>0,'INPUT FIELDS'!J42," ") | K29: =IF(E29>0,'INPUT FIELDS'!K42," ") | L29: =IF(E29>0,'INPUT FIELDS'!L42," ") | M29: =IF(E29>0,'INPUT FIELDS'!M42," ") | N29: =IF(E29>0,'INPUT FIELDS'!N42," ") | O29: =IF(E29>0,'INPUT FIELDS'!O42," ") | P29: =IF(E29>0,'INPUT FIELDS'!P42," ") | S29: =IF(E29>0,'INPUT FIELDS'!Q42," ") | T29: =IF(E29>0,'INPUT FIELDS'!R42," ") | U29: =IF(E29>0,'INPUT FIELDS'!S42," ") | V29: =IF(E29>0,'INPUT FIELDS'!T42," ") | Z29: =IF(E29>0,'INPUT FIELDS'!U42," ")
B30: ='INPUT FIELDS'!E43 -> 20219 | C30: ='INPUT FIELDS'!F43 -> 31048 | E30: =IF(B30>0,4," ") -> 4 | F30: =IF(B30>0,'INPUT FIELDS'!D43," ") -> LIMA, NESTOR PELENO | G30: =IF(B30>0,'INPUT FIELDS'!G43," ") -> 70 | H30: =IF(B30>0,'INPUT FIELDS'!H43," ") -> 41 | I30: =IF(B30>0,'INPUT FIELDS'!I43," ") -> PRISON GUARD I | J30: =IF(B30>0,'INPUT FIELDS'!J43," ") -> 12886 | K30: =IF(B30>0,'INPUT FIELDS'!K43," ") -> 2000 | L30: =IF(B30>0,'INPUT FIELDS'!L43," ") -> 14886 | M30: =IF(B30>0,'INPUT FIELDS'!M43," ") -> 10386 | N30: =IF(B30>0,'INPUT FIELDS'!N43," ") -> 3453.19 | O30: =IF(B30>0,IF(V30="NEW",'INPUT FIELDS'!O43,Q30)," ") -> 0.35 | P30: =IF(B30>0,IF(V30="NEW",'INPUT FIELDS'!P43,R30)," ") -> 5210.1 | Q30: =IF(L30<10000,20%,IF(L30<13000,30%,IF(L30<38000,35%,40%))) -> 0.35 | R30: =Q30*L30 -> 5210.1 | S30: =IF(B30>0,'INPUT FIELDS'!Q43," ") -> 3939.9077 | T30: =IF(B30>0,'INPUT FIELDS'!R43," ") -> 10872.718 | U30: =IF(B30>0,'INPUT FIELDS'!S43," ") -> 4013.2823 | V30: =IF(B30>0,'INPUT FIELDS'!T43," ") -> RENEWAL | W30: =L30-M30+N30 -> 7953.19 | X30: =W30-4000 -> 3953.19 | Y30: =IF(P30<X30,P30,X30) -> 3953.19 | Z30: =IF(B30>0,-PV(AB30/12,AC30,Y30),"") -> 139970.28 | AA30: 139500 | AB30: =IF(B30>0,'INPUT FIELDS'!W43," ") -> 0.1581 | AC30: 48 | AE30: =IF(AA30>0,IF(P30<S30,"CHK IGIR","GO")," ") -> GO | AF30: =IF(AA30>0,IF(U30<4000," NTHP BELOW 4K","GO")," ") -> GO
F31: =IF('INPUT FIELDS'!BB16>0,'INPUT FIELDS'!BB16,"") -> PROVINCIAL WARDENS OFFICE | G31: =IF(E31>0,'INPUT FIELDS'!G44," ") | H31: =IF(E31>0,'INPUT FIELDS'!H44," ") | I31: =IF(E31>0,'INPUT FIELDS'!I44," ") | J31: =IF(E31>0,'INPUT FIELDS'!J44," ") | K31: =IF(E31>0,'INPUT FIELDS'!K44," ") | L31: =IF(E31>0,'INPUT FIELDS'!L44," ") | M31: =IF(E31>0,'INPUT FIELDS'!M44," ") | N31: =IF(E31>0,'INPUT FIELDS'!N44," ") | O31: =IF(E31>0,'INPUT FIELDS'!O44," ") | P31: =IF(E31>0,'INPUT FIELDS'!P44," ") | S31: =IF(E31>0,'INPUT FIELDS'!Q44," ") | T31: =IF(E31>0,'INPUT FIELDS'!R44," ") | U31: =IF(E31>0,'INPUT FIELDS'!S44," ") | V31: =IF(E31>0,'INPUT FIELDS'!T44," ") | Z31: =IF(E31>0,'INPUT FIELDS'!U44," ")
B32: ='INPUT FIELDS'!E45 -> 26900 | C32: ='INPUT FIELDS'!F45 -> 36297 | E32: =IF(B32>0,5," ") -> 5 | F32: =IF(B32>0,'INPUT FIELDS'!D45," ") -> ALEGRIA, MARCIANO JR HERNANDEZ | G32: =IF(B32>0,'INPUT FIELDS'!G45," ") -> 52 | H32: =IF(B32>0,'INPUT FIELDS'!H45," ") -> 26 | I32: =IF(B32>0,'INPUT FIELDS'!I45," ") -> ADMIN AIDE III | J32: =IF(B32>0,'INPUT FIELDS'!J45," ") -> 10931 | K32: =IF(B32>0,'INPUT FIELDS'!K45," ") -> 2000 | L32: =IF(B32>0,'INPUT FIELDS'!L45," ") -> 12931 | M32: =IF(B32>0,'INPUT FIELDS'!M45," ") -> 7761 | N32: =IF(B32>0,'INPUT FIELDS'!N45," ") -> 2999.23 | O32: =IF(B32>0,IF(V32="NEW",'INPUT FIELDS'!O45,Q32)," ") -> 0.3 | P32: =IF(B32>0,IF(V32="NEW",'INPUT FIELDS'!P45,R32)," ") -> 3879.3 | Q32: =IF(L32<10000,20%,IF(L32<13000,30%,IF(L32<38000,35%,40%))) -> 0.3 | R32: =Q32*L32 -> 3879.3 | S32: =IF(B32>0,'INPUT FIELDS'!Q45," ") -> 3879.1852 | T32: =IF(B32>0,'INPUT FIELDS'!R45," ") -> 8640.9552 | U32: =IF(B32>0,'INPUT FIELDS'!S45," ") -> 4290.0448 | V32: =IF(B32>0,'INPUT FIELDS'!T45," ") -> RENEWAL | W32: =L32-M32+N32 -> 8169.23 | X32: =W32-4000 -> 4169.23 | Y32: =IF(P32<X32,P32,X32) -> 3879.3 | Z32: =IF(B32>0,-PV(AB32/12,AC32,Y32),"") -> 137354.07 | AA32: 137350 | AB32: =IF(B32>0,'INPUT FIELDS'!W45," ") -> 0.1581 | AC32: 48 | AE32: =IF(AA32>0,IF(P32<S32,"CHK IGIR","GO")," ") -> GO | AF32: =IF(AA32>0,IF(U32<4000," NTHP BELOW 4K","GO")," ") -> GO
F33: =IF('INPUT FIELDS'!BD16>0,'INPUT FIELDS'!BD16,"") -> PROVINCIAL HEALTH OFFICE | G33: =IF(E33>0,'INPUT FIELDS'!G46," ") | H33: =IF(E33>0,'INPUT FIELDS'!H46," ") | I33: =IF(E33>0,'INPUT FIELDS'!I46," ") | J33: =IF(E33>0,'INPUT FIELDS'!J46," ") | K33: =IF(E33>0,'INPUT FIELDS'!K46," ") | L33: =IF(E33>0,'INPUT FIELDS'!L46," ") | M33: =IF(E33>0,'INPUT FIELDS'!M46," ") | N33: =IF(E33>0,'INPUT FIELDS'!N46," ") | O33: =IF(E33>0,'INPUT FIELDS'!O46," ") | P33: =IF(E33>0,'INPUT FIELDS'!P46," ") | S33: =IF(E33>0,'INPUT FIELDS'!Q46," ") | T33: =IF(E33>0,'INPUT FIELDS'!R46," ") | U33: =IF(E33>0,'INPUT FIELDS'!S46," ") | V33: =IF(E33>0,'INPUT FIELDS'!T46," ") | Z33: =IF(E33>0,'INPUT FIELDS'!U46," ")
B34: ='INPUT FIELDS'!E47 -> 28260 | C34: ='INPUT FIELDS'!F47 -> 40252 | E34: =IF(B34>0,6," ") -> 6 | F34: =IF(B34>0,'INPUT FIELDS'!D47," ") -> GACELOS, MANOLITO ABARRACOSO | G34: =IF(B34>0,'INPUT FIELDS'!G47," ") -> 48 | H34: =IF(B34>0,'INPUT FIELDS'!H47," ") -> 15 | I34: =IF(B34>0,'INPUT FIELDS'!I47," ") -> DRIVER I | J34: =IF(B34>0,'INPUT FIELDS'!J47," ") -> 10505 | K34: =IF(B34>0,'INPUT FIELDS'!K47," ") -> 3650 | L34: =IF(B34>0,'INPUT FIELDS'!L47," ") -> 14155 | M34: =IF(B34>0,'INPUT FIELDS'!M47," ") -> 2357.99 | N34: =IF(B34>0,'INPUT FIELDS'!N47," ") -> 0 | O34: =IF(B34>0,IF(V34="NEW",'INPUT FIELDS'!O47,Q34)," ") -> 0.3 | P34: =IF(B34>0,IF(V34="NEW",'INPUT FIELDS'!P47,R34)," ") -> 4246.5 | Q34: =IF(L34<10000,20%,IF(L34<13000,30%,IF(L34<38000,35%,40%))) -> 0.35 | R34: =Q34*L34 -> 4954.25 | S34: =IF(B34>0,'INPUT FIELDS'!Q47," ") -> 4244.9329 | T34: =IF(B34>0,'INPUT FIELDS'!R47," ") -> 6602.9229 | U34: =IF(B34>0,'INPUT FIELDS'!S47," ") -> 7552.0771 | V34: =IF(B34>0,'INPUT FIELDS'!T47," ") -> NEW | W34: =L34-M34+N34 -> 11797.01 | X34: =W34-4000 -> 7797.01 | Y34: =IF(P34<X34,P34,X34) -> 4246.5 | Z34: =IF(B34>0,-PV(AB34/12,AC34,Y34),"") -> 150355.49 | AA34: 150300 | AB34: =IF(B34>0,'INPUT FIELDS'!W47," ") -> 0.1581 | AC34: 48 | AE34: =IF(AA34>0,IF(P34<S34,"CHK IGIR","GO")," ") -> GO | AF34: =IF(AA34>0,IF(U34<4000," NTHP BELOW 4K","GO")," ") -> GO
F35: =IF('INPUT FIELDS'!BF16>0,'INPUT FIELDS'!BF16,"") | G35: =IF(E35>0,'INPUT FIELDS'!G48," ") | H35: =IF(E35>0,'INPUT FIELDS'!H48," ") | I35: =IF(E35>0,'INPUT FIELDS'!I48," ") | J35: =IF(E35>0,'INPUT FIELDS'!J48," ") | K35: =IF(E35>0,'INPUT FIELDS'!K48," ") | L35: =IF(E35>0,'INPUT FIELDS'!L48," ") | M35: =IF(E35>0,'INPUT FIELDS'!M48," ") | N35: =IF(E35>0,'INPUT FIELDS'!N48," ") | O35: =IF(E35>0,'INPUT FIELDS'!O48," ") | P35: =IF(E35>0,'INPUT FIELDS'!P48," ") | S35: =IF(E35>0,'INPUT FIELDS'!Q48," ") | T35: =IF(E35>0,'INPUT FIELDS'!R48," ") | U35: =IF(E35>0,'INPUT FIELDS'!S48," ") | V35: =IF(E35>0,'INPUT FIELDS'!T48," ") | Z35: =IF(E35>0,'INPUT FIELDS'!U48," ")
B36: ='INPUT FIELDS'!E49 -> 20852 | C36: ='INPUT FIELDS'!F49 -> 30376 | E36: =IF(B36>0,7," ") -> 7 | F36: =IF(B36>0,'INPUT FIELDS'!D49," ") -> GONZALES, LEONILA HILONGO | G36: =IF(B36>0,'INPUT FIELDS'!G49," ") -> 69 | H36: =IF(B36>0,'INPUT FIELDS'!H49," ") -> 43 | I36: =IF(B36>0,'INPUT FIELDS'!I49," ") -> DENTIST II | J36: =IF(B36>0,'INPUT FIELDS'!J49," ") -> 31339 | K36: =IF(B36>0,'INPUT FIELDS'!K49," ") -> 3650 | L36: =IF(B36>0,'INPUT FIELDS'!L49," ") -> 34989 | M36: =IF(B36>0,'INPUT FIELDS'!M49," ") -> 21547.08 | N36: =IF(B36>0,'INPUT FIELDS'!N49," ") -> 8404.99 | O36: =IF(B36>0,IF(V36="NEW",'INPUT FIELDS'!O49,Q36)," ") -> 0.35 | P36: =IF(B36>0,IF(V36="NEW",'INPUT FIELDS'!P49,R36)," ") -> 12246.15 | Q36: =IF(L36<10000,20%,IF(L36<13000,30%,IF(L36<38000,35%,40%))) -> 0.35 | R36: =Q36*L36 -> 12246.15 | S36: =IF(B36>0,'INPUT FIELDS'!Q49," ") -> 12243.369 | T36: =IF(B36>0,'INPUT FIELDS'!R49," ") -> 25385.459 | U36: =IF(B36>0,'INPUT FIELDS'!S49," ") -> 9603.5408 | V36: =IF(B36>0,'INPUT FIELDS'!T49," ") -> RENEWAL | W36: =L36-M36+N36 -> 21846.91 | X36: =W36-4000 -> 17846.91 | Y36: =IF(P36<X36,P36,X36) -> 12246.15 | Z36: =IF(B36>0,-PV(AB36/12,AC36,Y36),"") -> 433598.46 | AA36: 433500 | AB36: =IF(B36>0,'INPUT FIELDS'!W49," ") -> 0.1581 | AC36: 48 | AE36: =IF(AA36>0,IF(P36<S36,"CHK IGIR","GO")," ") -> GO | AF36: =IF(AA36>0,IF(U36<4000," NTHP BELOW 4K","GO")," ") -> GO
F37: =IF('INPUT FIELDS'!BH16>0,'INPUT FIELDS'!BH16,"")
B38: ='INPUT FIELDS'!E51 -> 24599 | C38: ='INPUT FIELDS'!F51 -> 39114 | E38: =IF(B38>0,8," ") -> 8 | F38: =IF(B38>0,'INPUT FIELDS'!D51," ") -> MAYOR, CHONA BRANZUELA | G38: =IF(B38>0,'INPUT FIELDS'!G51," ") -> 58 | H38: =IF(B38>0,'INPUT FIELDS'!H51," ") -> 19 | I38: =IF(B38>0,'INPUT FIELDS'!I51," ") -> DENTAL AIDE | J38: =IF(B38>0,'INPUT FIELDS'!J51," ") -> 11405 | K38: =IF(B38>0,'INPUT FIELDS'!K51," ") -> 3650 | L38: =IF(B38>0,'INPUT FIELDS'!L51," ") -> 15055 | M38: =IF(B38>0,'INPUT FIELDS'!M51," ") -> 8448.62 | N38: =IF(B38>0,'INPUT FIELDS'!N51," ") -> 3057.58 | O38: =IF(B38>0,IF(V38="NEW",'INPUT FIELDS'!O51,Q38)," ") -> 0.35 | P38: =IF(B38>0,IF(V38="NEW",'INPUT FIELDS'!P51,R38)," ") -> 5269.25 | Q38: =IF(L38<10000,20%,IF(L38<13000,30%,IF(L38<38000,35%,40%))) -> 0.35 | R38: =Q38*L38 -> 5269.25 | S38: =IF(B38>0,'INPUT FIELDS'!Q51," ") -> 5267.3319 | T38: =IF(B38>0,'INPUT FIELDS'!R51," ") -> 10658.372 | U38: =IF(B38>0,'INPUT FIELDS'!S51," ") -> 4396.6281 | V38: =IF(B38>0,'INPUT FIELDS'!T51," ") -> RENEWAL | W38: =L38-M38+N38 -> 9663.96 | X38: =W38-4000 -> 5663.96 | Y38: =IF(P38<X38,P38,X38) -> 5269.25 | Z38: =IF(B38>0,-PV(AB38/12,AC38,Y38),"") -> 186567.92 | AA38: 186500 | AB38: =IF(B38>0,'INPUT FIELDS'!W51," ") -> 0.1581 | AC38: 48 | AE38: =IF(AA38>0,IF(P38<S38,"CHK IGIR","GO")," ") -> GO | AF38: =IF(AA38>0,IF(U38<4000," NTHP BELOW 4K","GO")," ") -> GO
F39: =IF('INPUT FIELDS'!BJ16>0,'INPUT FIELDS'!BJ16,"")
B40: ='INPUT FIELDS'!E53 -> 25868 | C40: ='INPUT FIELDS'!F53 -> 35492 | E40: =IF(B40>0,9," ") -> 9 | F40: =IF(B40>0,'INPUT FIELDS'!D53," ") -> YBOA, JONAS ABELIDO | G40: =IF(B40>0,'INPUT FIELDS'!G53," ") -> 55 | H40: =IF(B40>0,'INPUT FIELDS'!H53," ") -> 29 | I40: =IF(B40>0,'INPUT FIELDS'!I53," ") -> ADMIN AIDE VI | J40: =IF(B40>0,'INPUT FIELDS'!J53," ") -> 13580 | K40: =IF(B40>0,'INPUT FIELDS'!K53," ") -> 2000 | L40: =IF(B40>0,'INPUT FIELDS'!L53," ") -> 15580 | M40: =IF(B40>0,'INPUT FIELDS'!M53," ") -> 10473.62 | N40: =IF(B40>0,'INPUT FIELDS'!N53," ") -> 3640.94 | O40: =IF(B40>0,IF(V40="NEW",'INPUT FIELDS'!O53,Q40)," ") -> 0.35 | P40: =IF(B40>0,IF(V40="NEW",'INPUT FIELDS'!P53,R40)," ") -> 5453 | Q40: =IF(L40<10000,20%,IF(L40<13000,30%,IF(L40<38000,35%,40%))) -> 0.35 | R40: =Q40*L40 -> 5453 | S40: =IF(B40>0,'INPUT FIELDS'!Q53," ") -> 4671.4032 | T40: =IF(B40>0,'INPUT FIELDS'!R53," ") -> 11504.083 | U40: =IF(B40>0,'INPUT FIELDS'!S53," ") -> 4075.9168 | V40: =IF(B40>0,'INPUT FIELDS'!T53," ") -> RENEWAL | W40: =L40-M40+N40 -> 8747.32 | X40: =W40-4000 -> 4747.32 | Y40: =IF(P40<X40,P40,X40) -> 4747.32 | Z40: =IF(B40>0,-PV(AB40/12,AC40,Y40),"") -> 168087.98 | AA40: 165400 | AB40: =IF(B40>0,'INPUT FIELDS'!W53," ") -> 0.1581 | AC40: 48 | AE40: =IF(AA40>0,IF(P40<S40,"CHK IGIR","GO")," ") -> GO | AF40: =IF(AA40>0,IF(U40<4000," NTHP BELOW 4K","GO")," ") -> GO
F41: =IF('INPUT FIELDS'!BL16>0,'INPUT FIELDS'!BL16,"")
B42: ='INPUT FIELDS'!E55 -> 22656 | C42: ='INPUT FIELDS'!F55 -> 34319 | E42: =IF(B42>0,10," ") -> 10 | F42: =IF(B42>0,'INPUT FIELDS'!D55," ") -> GONZALES, RUBIA ABARCAR | G42: =IF(B42>0,'INPUT FIELDS'!G55," ") -> 64 | H42: =IF(B42>0,'INPUT FIELDS'!H55," ") -> 32 | I42: =IF(B42>0,'INPUT FIELDS'!I55," ") -> LABORATORY AIDE I | J42: =IF(B42>0,'INPUT FIELDS'!J55," ") -> 10373 | K42: =IF(B42>0,'INPUT FIELDS'!K55," ") -> 3650 | L42: =IF(B42>0,'INPUT FIELDS'!L55," ") -> 14023 | M42: =IF(B42>0,'INPUT FIELDS'!M55," ") -> 7735.27 | N42: =IF(B42>0,'INPUT FIELDS'!N55," ") -> 2752.49 | O42: =IF(B42>0,IF(V42="NEW",'INPUT FIELDS'!O55,Q42)," ") -> 0.35 | P42: =IF(B42>0,IF(V42="NEW",'INPUT FIELDS'!P55,R42)," ") -> 4908.05 | Q42: =IF(L42<10000,20%,IF(L42<13000,30%,IF(L42<38000,35%,40%))) -> 0.35 | R42: =Q42*L42 -> 4908.05 | S42: =IF(B42>0,'INPUT FIELDS'!Q55," ") -> 4205.3926 | T42: =IF(B42>0,'INPUT FIELDS'!R55," ") -> 9188.1726 | U42: =IF(B42>0,'INPUT FIELDS'!S55," ") -> 4834.8274 | V42: =IF(B42>0,'INPUT FIELDS'!T55," ") -> RENEWAL | W42: =L42-M42+N42 -> 9040.22 | X42: =W42-4000 -> 5040.22 | Y42: =IF(P42<X42,P42,X42) -> 4908.05 | Z42: =IF(B42>0,-PV(AB42/12,AC42,Y42),"") -> 173778.94 | AA42: 148900 | AB42: =IF(B42>0,'INPUT FIELDS'!W55," ") -> 0.1581 | AC42: 48 | AE42: =IF(AA42>0,IF(P42<S42,"CHK IGIR","GO")," ") -> GO | AF42: =IF(AA42>0,IF(U42<4000," NTHP BELOW 4K","GO")," ") -> GO
F43: =IF('INPUT FIELDS'!BN16>0,'INPUT FIELDS'!BN16,"") -> PROVINCIAL AGRICULTURE OFFICE
B44: ='INPUT FIELDS'!E57 -> 24098 | C44: ='INPUT FIELDS'!F57 -> 35506 | E44: =IF(B44>0,11," ") -> 11 | F44: =IF(B44>0,'INPUT FIELDS'!D57," ") -> ARCALES, DOMINGO JR JADLOC | G44: =IF(B44>0,'INPUT FIELDS'!G57," ") -> 60 | H44: =IF(B44>0,'INPUT FIELDS'!H57," ") -> 28 | I44: =IF(B44>0,'INPUT FIELDS'!I57," ") -> AGRICULTURAL TECHNICIAN II | J44: =IF(B44>0,'INPUT FIELDS'!J57," ") -> 15768.87 | K44: =IF(B44>0,'INPUT FIELDS'!K57," ") -> 2000 | L44: =IF(B44>0,'INPUT FIELDS'!L57," ") -> 17768.87 | M44: =IF(B44>0,'INPUT FIELDS'!M57," ") -> 12313.58 | N44: =IF(B44>0,'INPUT FIELDS'!N57," ") -> 4207.52 | O44: =IF(B44>0,IF(V44="NEW",'INPUT FIELDS'!O57,Q44)," ") -> 0.35 | P44: =IF(B44>0,IF(V44="NEW",'INPUT FIELDS'!P57,R44)," ") -> 6219.1045 | Q44: =IF(L44<10000,20%,IF(L44<13000,30%,IF(L44<38000,35%,40%))) -> 0.35 | R44: =Q44*L44 -> 6219.1045 | S44: =IF(B44>0,'INPUT FIELDS'!Q57," ") -> 5329.4666 | T44: =IF(B44>0,'INPUT FIELDS'!R57," ") -> 13435.527 | U44: =IF(B44>0,'INPUT FIELDS'!S57," ") -> 4333.3434 | V44: =IF(B44>0,'INPUT FIELDS'!T57," ") -> RENEWAL | W44: =L44-M44+N44 -> 9662.81 | X44: =W44-4000 -> 5662.81 | Y44: =IF(P44<X44,P44,X44) -> 5662.81 | Z44: =IF(B44>0,-PV(AB44/12,AC44,Y44),"") -> 200502.66 | AA44: 188700 | AB44: =IF(B44>0,'INPUT FIELDS'!W57," ") -> 0.1581 | AC44: 48 | AE44: =IF(AA44>0,IF(P44<S44,"CHK IGIR","GO")," ") -> GO | AF44: =IF(AA44>0,IF(U44<4000," NTHP BELOW 4K","GO")," ") -> GO
F45: =IF('INPUT FIELDS'!BP16>0,'INPUT FIELDS'!BP16,"")
B46: ='INPUT FIELDS'!E59 -> 19920 | C46: ='INPUT FIELDS'!F59 -> 29859 | E46: =IF(B46>0,12," ") -> 12 | F46: =IF(B46>0,'INPUT FIELDS'!D59," ") -> GACELOS, REBECCA TILLES | G46: =IF(B46>0,'INPUT FIELDS'!G59," ") -> 71 | H46: =IF(B46>0,'INPUT FIELDS'!H59," ") -> 44 | I46: =IF(B46>0,'INPUT FIELDS'!I59," ") -> AGRICULTURAL TECHNOLOGIST I | J46: =IF(B46>0,'INPUT FIELDS'!J59," ") -> 18135 | K46: =IF(B46>0,'INPUT FIELDS'!K59," ") -> 2000 | L46: =IF(B46>0,'INPUT FIELDS'!L59," ") -> 20135 | M46: =IF(B46>0,'INPUT FIELDS'!M59," ") -> 14037.39 | N46: =IF(B46>0,'INPUT FIELDS'!N59," ") -> 4652.09 | O46: =IF(B46>0,IF(V46="NEW",'INPUT FIELDS'!O59,Q46)," ") -> 0.35 | P46: =IF(B46>0,IF(V46="NEW",'INPUT FIELDS'!P59,R46)," ") -> 7047.25 | Q46: =IF(L46<10000,20%,IF(L46<13000,30%,IF(L46<38000,35%,40%))) -> 0.35 | R46: =Q46*L46 -> 7047.25 | S46: =IF(B46>0,'INPUT FIELDS'!Q59," ") -> 6747.2685 | T46: =IF(B46>0,'INPUT FIELDS'!R59," ") -> 16132.569 | U46: =IF(B46>0,'INPUT FIELDS'!S59," ") -> 4002.4315 | V46: =IF(B46>0,'INPUT FIELDS'!T59," ") -> RENEWAL | W46: =L46-M46+N46 -> 10749.7 | X46: =W46-4000 -> 6749.7 | Y46: =IF(P46<X46,P46,X46) -> 6749.7 | Z46: =IF(B46>0,-PV(AB46/12,AC46,Y46),"") -> 238986.09 | AA46: 238900 | AB46: =IF(B46>0,'INPUT FIELDS'!W59," ") -> 0.1581 | AC46: 48 | AE46: =IF(AA46>0,IF(P46<S46,"CHK IGIR","GO")," ") -> GO | AF46: =IF(AA46>0,IF(U46<4000," NTHP BELOW 4K","GO")," ") -> GO
F47: =IF('INPUT FIELDS'!BR16>0,'INPUT FIELDS'!BR16,"") -> PROVINCIAL SANGGUNIANG PANLALAWIGAN
B48: ='INPUT FIELDS'!E61 -> 21917 | C48: ='INPUT FIELDS'!F61 -> 29692 | E48: =IF(B48>0,13," ") -> 13 | F48: =IF(B48>0,'INPUT FIELDS'!D61," ") -> TONELETE, NARCISA CAMUIN | G48: =IF(B48>0,'INPUT FIELDS'!G61," ") -> 66 | H48: =IF(B48>0,'INPUT FIELDS'!H61," ") -> 44 | I48: =IF(B48>0,'INPUT FIELDS'!I61," ") -> BOARD SECRETARY I | J48: =IF(B48>0,'INPUT FIELDS'!J61," ") -> 23979 | K48: =IF(B48>0,'INPUT FIELDS'!K61," ") -> 2000 | L48: =IF(B48>0,'INPUT FIELDS'!L61," ") -> 25979 | M48: =IF(B48>0,'INPUT FIELDS'!M61," ") -> 16345.01 | N48: =IF(B48>0,'INPUT FIELDS'!N61," ") -> 6583.07 | O48: =IF(B48>0,IF(V48="NEW",'INPUT FIELDS'!O61,Q48)," ") -> 0.35 | P48: =IF(B48>0,IF(V48="NEW",'INPUT FIELDS'!P61,R48)," ") -> 9092.65 | Q48: =IF(L48<10000,20%,IF(L48<13000,30%,IF(L48<38000,35%,40%))) -> 0.35 | R48: =Q48*L48 -> 9092.65 | S48: =IF(B48>0,'INPUT FIELDS'!Q61," ") -> 9066.0243 | T48: =IF(B48>0,'INPUT FIELDS'!R61," ") -> 18827.964 | U48: =IF(B48>0,'INPUT FIELDS'!S61," ") -> 7151.0357 | V48: =IF(B48>0,'INPUT FIELDS'!T61," ") -> RENEWAL | W48: =L48-M48+N48 -> 16217.06 | X48: =W48-4000 -> 12217.06 | Y48: =IF(P48<X48,P48,X48) -> 9092.65 | Z48: =IF(B48>0,-PV(AB48/12,AC48,Y48),"") -> 321942.74 | AA48: 321000 | AB48: =IF(B48>0,'INPUT FIELDS'!W61," ") -> 0.1581 | AC48: 48 | AE48: =IF(AA48>0,IF(P48<S48,"CHK IGIR","GO")," ") -> GO | AF48: =IF(AA48>0,IF(U48<4000," NTHP BELOW 4K","GO")," ") -> GO
F49: =IF('INPUT FIELDS'!BT16>0,'INPUT FIELDS'!BT16,"")
B50: ='INPUT FIELDS'!E63 -> 25812 | C50: ='INPUT FIELDS'!F63 -> 37097 | E50: =IF(B50>0,14," ") -> 14 | F50: =IF(B50>0,'INPUT FIELDS'!D63," ") -> GABON, MA WINONA CON UI | G50: =IF(B50>0,'INPUT FIELDS'!G63," ") -> 55 | H50: =IF(B50>0,'INPUT FIELDS'!H63," ") -> 24 | I50: =IF(B50>0,'INPUT FIELDS'!I63," ") -> COMPUTER MAINTENANCE TECHNICIAN | J50: =IF(B50>0,'INPUT FIELDS'!J63," ") -> 19495 | K50: =IF(B50>0,'INPUT FIELDS'!K63," ") -> 2000 | L50: =IF(B50>0,'INPUT FIELDS'!L63," ") -> 21495 | M50: =IF(B50>0,'INPUT FIELDS'!M63," ") -> 8580.2 | N50: =IF(B50>0,'INPUT FIELDS'!N63," ") -> 5176.43 | O50: =IF(B50>0,IF(V50="NEW",'INPUT FIELDS'!O63,Q50)," ") -> 0.35 | P50: =IF(B50>0,IF(V50="NEW",'INPUT FIELDS'!P63,R50)," ") -> 7523.25 | Q50: =IF(L50<10000,20%,IF(L50<13000,30%,IF(L50<38000,35%,40%))) -> 0.35 | R50: =Q50*L50 -> 7523.25 | S50: =IF(B50>0,'INPUT FIELDS'!Q63," ") -> 7521.1285 | T50: =IF(B50>0,'INPUT FIELDS'!R63," ") -> 10924.899 | U50: =IF(B50>0,'INPUT FIELDS'!S63," ") -> 10570.101 | V50: =IF(B50>0,'INPUT FIELDS'!T63," ") -> RENEWAL | W50: =L50-M50+N50 -> 18091.23 | X50: =W50-4000 -> 14091.23 | Y50: =IF(P50<X50,P50,X50) -> 7523.25 | Z50: =IF(B50>0,-PV(AB50/12,AC50,Y50),"") -> 266375.11 | AA50: 266300 | AB50: =IF(B50>0,'INPUT FIELDS'!W63," ") -> 0.1581 | AC50: 48 | AE50: =IF(AA50>0,IF(P50<S50,"CHK IGIR","GO")," ") -> GO | AF50: =IF(AA50>0,IF(U50<4000," NTHP BELOW 4K","GO")," ") -> GO
F51: =IF('INPUT FIELDS'!BV16>0,'INPUT FIELDS'!BV16,"")
B52: ='INPUT FIELDS'!E65 -> 0 | C52: ='INPUT FIELDS'!F65 -> 0 | E52: =IF(B52>0,15," ") | F52: =IF(B52>0,'INPUT FIELDS'!D65," ") | G52: =IF(B52>0,'INPUT FIELDS'!G65," ") | H52: =IF(B52>0,'INPUT FIELDS'!H65," ") | I52: =IF(B52>0,'INPUT FIELDS'!I65," ") | J52: =IF(B52>0,'INPUT FIELDS'!J65," ") | K52: =IF(B52>0,'INPUT FIELDS'!K65," ") | L52: =IF(B52>0,'INPUT FIELDS'!L65," ") | M52: =IF(B52>0,'INPUT FIELDS'!M65," ") | N52: =IF(B52>0,'INPUT FIELDS'!N65," ") | O52: =IF(B52>0,IF(V52="NEW",'INPUT FIELDS'!O65,Q52)," ") | P52: =IF(B52>0,IF(V52="NEW",'INPUT FIELDS'!P65,R52)," ") | Q52: =IF(L52<10000,20%,IF(L52<13000,30%,IF(L52<38000,35%,40%))) -> 0.4 | R52: =Q52*L52 -> #VALUE! | S52: =IF(B52>0,'INPUT FIELDS'!Q65," ") | T52: =IF(B52>0,'INPUT FIELDS'!R65," ") | U52: =IF(B52>0,'INPUT FIELDS'!S65," ") | V52: =IF(B52>0,'INPUT FIELDS'!T65," ") | W52: =L52-M52+N52 -> #VALUE! | X52: =W52-4000 -> #VALUE! | Y52: =IF(P52<X52,P52,X52) -> #VALUE! | Z52: =IF(B52>0,-PV(AB52/12,AC52,Y52),"") | AB52: =IF(B52>0,'INPUT FIELDS'!W65," ") | AE52: =IF(AA52>0,IF(P52<S52,"CHK IGIR","GO")," ") | AF52: =IF(AA52>0,IF(U52<4000," NTHP BELOW 4K","GO")," ")
F53: =IF('INPUT FIELDS'!BX16>0,'INPUT FIELDS'!BX16,"")
B54: ='INPUT FIELDS'!E67 -> 0 | C54: ='INPUT FIELDS'!F67 -> 0 | E54: =IF(B54>0,16," ") | F54: =IF(B54>0,'INPUT FIELDS'!D67," ") | G54: =IF(B54>0,'INPUT FIELDS'!G67," ") | H54: =IF(B54>0,'INPUT FIELDS'!H67," ") | I54: =IF(B54>0,'INPUT FIELDS'!I67," ") | J54: =IF(B54>0,'INPUT FIELDS'!J67," ") | K54: =IF(B54>0,'INPUT FIELDS'!K67," ") | L54: =IF(B54>0,'INPUT FIELDS'!L67," ") | M54: =IF(B54>0,'INPUT FIELDS'!M67," ") | N54: =IF(B54>0,'INPUT FIELDS'!N67," ") | O54: =IF(B54>0,IF(V54="NEW",'INPUT FIELDS'!O67,Q54)," ") | P54: =IF(B54>0,IF(V54="NEW",'INPUT FIELDS'!P67,R54)," ") | Q54: =IF(L54<10000,20%,IF(L54<13000,30%,IF(L54<38000,35%,40%))) -> 0.4 | R54: =Q54*L54 -> #VALUE! | S54: =IF(B54>0,'INPUT FIELDS'!Q67," ") | T54: =IF(B54>0,'INPUT FIELDS'!R67," ") | U54: =IF(B54>0,'INPUT FIELDS'!S67," ") | V54: =IF(B54>0,'INPUT FIELDS'!T67," ") | W54: =L54-M54+N54 -> #VALUE! | X54: =W54-4000 -> #VALUE! | Y54: =IF(P54<X54,P54,X54) -> #VALUE! | Z54: =IF(B54>0,-PV(AB54/12,AC54,Y54),"") | AB54: =IF(B54>0,'INPUT FIELDS'!W67," ") | AE54: =IF(AA54>0,IF(P54<S54,"CHK IGIR","GO")," ") | AF54: =IF(AA54>0,IF(U54<4000," NTHP BELOW 4K","GO")," ")
F55: =IF('INPUT FIELDS'!BZ16>0,'INPUT FIELDS'!BZ16,"")
B56: ='INPUT FIELDS'!E69 -> 0 | C56: ='INPUT FIELDS'!F69 -> 0 | E56: =IF(B56>0,17," ") | F56: =IF(B56>0,'INPUT FIELDS'!D69," ") | G56: =IF(B56>0,'INPUT FIELDS'!G69," ") | H56: =IF(B56>0,'INPUT FIELDS'!H69," ") | I56: =IF(B56>0,'INPUT FIELDS'!I69," ") | J56: =IF(B56>0,'INPUT FIELDS'!J69," ") | K56: =IF(B56>0,'INPUT FIELDS'!K69," ") | L56: =IF(B56>0,'INPUT FIELDS'!L69," ") | M56: =IF(B56>0,'INPUT FIELDS'!M69," ") | N56: =IF(B56>0,'INPUT FIELDS'!N69," ") | O56: =IF(B56>0,IF(V56="NEW",'INPUT FIELDS'!O69,Q56)," ") | P56: =IF(B56>0,IF(V56="NEW",'INPUT FIELDS'!P69,R56)," ") | Q56: =IF(L56<10000,20%,IF(L56<13000,30%,IF(L56<38000,35%,40%))) -> 0.4 | R56: =Q56*L56 -> #VALUE! | S56: =IF(B56>0,'INPUT FIELDS'!Q69," ") | T56: =IF(B56>0,'INPUT FIELDS'!R69," ") | U56: =IF(B56>0,'INPUT FIELDS'!S69," ") | V56: =IF(B56>0,'INPUT FIELDS'!T69," ") | W56: =L56-M56+N56 -> #VALUE! | X56: =W56-4000 -> #VALUE! | Y56: =IF(P56<X56,P56,X56) -> #VALUE! | Z56: =IF(B56>0,-PV(AB56/12,AC56,Y56),"") | AB56: =IF(B56>0,'INPUT FIELDS'!W69," ") | AE56: =IF(AA56>0,IF(P56<S56,"CHK IGIR","GO")," ") | AF56: =IF(AA56>0,IF(U56<4000," NTHP BELOW 4K","GO")," ")
F57: =IF('INPUT FIELDS'!CB16>0,'INPUT FIELDS'!CB16,"")
B58: ='INPUT FIELDS'!E71 -> 0 | C58: ='INPUT FIELDS'!F71 -> 0 | E58: =IF(B58>0,18," ") | F58: =IF(B58>0,'INPUT FIELDS'!D71," ") | G58: =IF(B58>0,'INPUT FIELDS'!G71," ") | H58: =IF(B58>0,'INPUT FIELDS'!H71," ") | I58: =IF(B58>0,'INPUT FIELDS'!I71," ") | J58: =IF(B58>0,'INPUT FIELDS'!J71," ") | K58: =IF(B58>0,'INPUT FIELDS'!K71," ") | L58: =IF(B58>0,'INPUT FIELDS'!L71," ") | M58: =IF(B58>0,'INPUT FIELDS'!M71," ") | N58: =IF(B58>0,'INPUT FIELDS'!N71," ") | O58: =IF(B58>0,IF(V58="NEW",'INPUT FIELDS'!O71,Q58)," ") | P58: =IF(B58>0,IF(V58="NEW",'INPUT FIELDS'!P71,R58)," ") | Q58: =IF(L58<10000,20%,IF(L58<13000,30%,IF(L58<38000,35%,40%))) -> 0.4 | R58: =Q58*L58 -> #VALUE! | S58: =IF(B58>0,'INPUT FIELDS'!Q71," ") | T58: =IF(B58>0,'INPUT FIELDS'!R71," ") | U58: =IF(B58>0,'INPUT FIELDS'!S71," ") | V58: =IF(B58>0,'INPUT FIELDS'!T71," ") | W58: =L58-M58+N58 -> #VALUE! | X58: =W58-4000 -> #VALUE! | Y58: =IF(P58<X58,P58,X58) -> #VALUE! | Z58: =IF(B58>0,-PV(AB58/12,AC58,Y58),"") | AB58: =IF(B58>0,'INPUT FIELDS'!W71," ") | AE58: =IF(AA58>0,IF(P58<S58,"CHK IGIR","GO")," ") | AF58: =IF(AA58>0,IF(U58<4000," NTHP BELOW 4K","GO")," ")
F59: =IF('INPUT FIELDS'!CD16>0,'INPUT FIELDS'!CD16,"")
B60: ='INPUT FIELDS'!E73 -> 0 | C60: ='INPUT FIELDS'!F73 -> 0 | E60: =IF(B60>0,19," ") | F60: =IF(B60>0,'INPUT FIELDS'!D73," ") | G60: =IF(B60>0,'INPUT FIELDS'!G73," ") | H60: =IF(B60>0,'INPUT FIELDS'!H73," ") | I60: =IF(B60>0,'INPUT FIELDS'!I73," ") | J60: =IF(B60>0,'INPUT FIELDS'!J73," ") | K60: =IF(B60>0,'INPUT FIELDS'!K73," ") | L60: =IF(B60>0,'INPUT FIELDS'!L73," ") | M60: =IF(B60>0,'INPUT FIELDS'!M73," ") | N60: =IF(B60>0,'INPUT FIELDS'!N73," ") | O60: =IF(B60>0,IF(V60="NEW",'INPUT FIELDS'!O73,Q60)," ") | P60: =IF(B60>0,IF(V60="NEW",'INPUT FIELDS'!P73,R60)," ") | Q60: =IF(L60<10000,20%,IF(L60<13000,30%,IF(L60<38000,35%,40%))) -> 0.4 | R60: =Q60*L60 -> #VALUE! | S60: =IF(B60>0,'INPUT FIELDS'!Q73," ") | T60: =IF(B60>0,'INPUT FIELDS'!R73," ") | U60: =IF(B60>0,'INPUT FIELDS'!S73," ") | V60: =IF(B60>0,'INPUT FIELDS'!T73," ") | W60: =L60-M60+N60 -> #VALUE! | X60: =W60-4000 -> #VALUE! | Y60: =IF(P60<X60,P60,X60) -> #VALUE! | Z60: =IF(B60>0,-PV(AB60/12,AC60,Y60),"") | AB60: =IF(B60>0,'INPUT FIELDS'!W73," ") | AE60: =IF(AA60>0,IF(P60<S60,"CHK IGIR","GO")," ") | AF60: =IF(AA60>0,IF(U60<4000," NTHP BELOW 4K","GO")," ")
F61: =IF('INPUT FIELDS'!CF16>0,'INPUT FIELDS'!CF16,"")
B62: ='INPUT FIELDS'!E75 -> 0 | C62: ='INPUT FIELDS'!F75 -> 0 | E62: =IF(B62>0,20," ") | F62: =IF(B62>0,'INPUT FIELDS'!D75," ") | G62: =IF(B62>0,'INPUT FIELDS'!G75," ") | H62: =IF(B62>0,'INPUT FIELDS'!H75," ") | I62: =IF(B62>0,'INPUT FIELDS'!I75," ") | J62: =IF(B62>0,'INPUT FIELDS'!J75," ") | K62: =IF(B62>0,'INPUT FIELDS'!K75," ") | L62: =IF(B62>0,'INPUT FIELDS'!L75," ") | M62: =IF(B62>0,'INPUT FIELDS'!M75," ") | N62: =IF(B62>0,'INPUT FIELDS'!N75," ") | O62: =IF(B62>0,IF(V62="NEW",'INPUT FIELDS'!O75,Q62)," ") | P62: =IF(B62>0,IF(V62="NEW",'INPUT FIELDS'!P75,R62)," ") | Q62: =IF(L62<10000,20%,IF(L62<13000,30%,IF(L62<38000,35%,40%))) -> 0.4 | R62: =Q62*L62 -> #VALUE! | S62: =IF(B62>0,'INPUT FIELDS'!Q75," ") | T62: =IF(B62>0,'INPUT FIELDS'!R75," ") | U62: =IF(B62>0,'INPUT FIELDS'!S75," ") | V62: =IF(B62>0,'INPUT FIELDS'!T75," ") | W62: =L62-M62+N62 -> #VALUE! | X62: =W62-4000 -> #VALUE! | Y62: =IF(P62<X62,P62,X62) -> #VALUE! | Z62: =IF(B62>0,-PV(AB62/12,AC62,Y62),"") | AB62: =IF(B62>0,'INPUT FIELDS'!W75," ") | AE62: =IF(AA62>0,IF(P62<S62,"CHK IGIR","GO")," ") | AF62: =IF(AA62>0,IF(U62<4000," NTHP BELOW 4K","GO")," ")
AA64: =SUM(AA24:AA62) -> 2757450
F65: Prepared by: | J65: Checked by: | S65: Approved by:
F67: =Signatories!C9 -> JANICE B. SOLAYAO | J67: =Signatories!C10 -> AM IRISH MAE N. CREER | S67: =Signatories!C11 -> SM HELBERT ANTOINE A. ACHAY
F68: Relationship Officer | J68: Branch Operations Officer | S68: Branch Head
H86: Total Deductions | K86: Add: New Amort | M86: Less: ACA/PERA | N86: New Total Deductions
G87: =#REF! -> #REF! | H87: 19695.44 | K87: =PMT(15%/12,36,#REF!)*-1 -> #REF! | M87: 2000 | N87: =+H87-#REF!+K87-M87 -> #REF!
G88: =F15 -> 0 | H88: 17019.8 | K88: =PMT(15%/12,36,V15)*-1 -> 0 | M88: 2000 | N88: =+H88-#REF!+K88-M88 -> #REF!
G89: =#REF! -> #REF! | H89: 8531.37 | K89: =PMT(15%/12,36,#REF!)*-1 -> #REF! | M89: 2000 | N89: =+H89-#REF!+K89-M89 -> #REF!
G90: =#REF! -> #REF! | H90: 3677.8 | K90: =PMT(15%/12,36,#REF!)*-1 -> #REF! | M90: 2000 | N90: =+H90-#REF!+K90-M90 -> #REF!
G91: =F18 -> 0 | H91: 9762.13 | K91: =PMT(15%/12,36,V18)*-1 -> #VALUE! | M91: 2000 | N91: =+H91-#REF!+K91-M91 -> #REF!
G92: =#REF! -> #REF! | H92: 8459.17 | K92: =PMT(15%/12,36,#REF!)*-1 -> #REF! | M92: 2000 | N92: =+H92-#REF!+K92-M92 -> #REF!
G93: =#REF! -> #REF! | H93: 9161.53 | K93: =PMT(15%/12,36,#REF!)*-1 -> #REF! | M93: 2000 | N93: =+H93-#REF!+K93-M93 -> #REF!
G94: =#REF! -> #REF! | H94: 3937.24 | K94: =PMT(15%/12,36,#REF!)*-1 -> #REF! | M94: 2000 | N94: =+H94-#REF!+K94-M94 -> #REF!
G95: =#REF! -> #REF! | H95: 9376.55 | K95: =PMT(15%/12,36,#REF!)*-1 -> #REF! | M95: 2000 | N95: =+H95-#REF!+K95-M95 -> #REF!
G96: =#REF! -> #REF! | H96: 8999.56 | K96: =PMT(15%/12,36,#REF!)*-1 -> #REF! | M96: 2000 | N96: =+H96-#REF!+K96-M96 -> #REF!

Sheet RSLP - FORM A
D7: Development Bank of the Philippines
N9: RSLP - FORM A
C11: C E R T I F I C A T I O N
C13: The undersigned hereby certify the completeness and validity of all documents stated below for the approved transaction per: | L13: ='COMPUTATION SHEET'!F6 -> OT N0. 15-005 DATED APRIL 7, 2015
E15: Salary Loan Application/ | G15: Special Power of Attorney | H15: Certification (on): | K15: Service Record | L15: Cert of Net Take Home Pay | M15: Oath of Office | N15: BIR Form 2316/ ITR | O15: (Others)
E16: Agreement Form | M16: For Elected Officials | O16: NFIS Checking
H18: As Permanent Employee | I18: No Pending Admin. Case | J18: Unexpended Leave credits
E19: Application No. | F19: Date Filed | G19: Date Executed | H19: Date Issued | I19: Date Issued | J19: Date Issued | K19: Date Issued | L19: Date Issued | M19: Date Sworn | N19: For Year | O19: Date Issued
B20: 1 | C20: ='COMPUTATION SHEET'!E24 -> 1 | D20: ='COMPUTATION SHEET'!F24 -> RABADAM, MARIA EMY TAN | E20: =IF(B20=C20,'INPUT FIELDS'!Z37," ") -> 15-0070 | F20: =IF(B20=C20,'INPUT FIELDS'!AA37," ") -> 42094 | G20: =IF(B20=C20,'INPUT FIELDS'!AB37," ") -> 42081 | H20: =IF(B20=C20,'INPUT FIELDS'!AC37," ") -> 42081 | I20: =IF(B20=C20,'INPUT FIELDS'!AD37," ") -> 42081 | J20: =IF(B20=C20,'INPUT FIELDS'!AE37," ") -> 42081 | K20: =IF(B20=C20,'INPUT FIELDS'!AF37," ") -> 42081 | L20: =IF(B20=C20,'INPUT FIELDS'!AG37," ") -> 42081 | M20: =IF(B20=C20,'INPUT FIELDS'!AH37," ") -> NA | N20: =IF(B20=C20,'INPUT FIELDS'!AI37," ") -> 2014 | O20: =IF(B20=C20,'INPUT FIELDS'!AJ37," ") -> -
B22: 2 | C22: ='COMPUTATION SHEET'!E26 -> 2 | D22: ='COMPUTATION SHEET'!F26 -> LEJAS, ALLAN GULFERIC | E22: =IF(B22=C22,'INPUT FIELDS'!Z39," ") -> 15-0070 | F22: =IF(B22=C22,'INPUT FIELDS'!AA39," ") -> 42094 | G22: =IF(B22=C22,'INPUT FIELDS'!AB39," ") -> 34409 | H22: =IF(B22=C22,'INPUT FIELDS'!AC39," ") -> 42097 | I22: =IF(B22=C22,'INPUT FIELDS'!AD39," ") -> 42135 | J22: =IF(B22=C22,'INPUT FIELDS'!AE39," ") -> 42463 | K22: =IF(B22=C22,'INPUT FIELDS'!AF39," ") -> 42463 | L22: =IF(B22=C22,'INPUT FIELDS'!AG39," ") -> 42463 | M22: =IF(B22=C22,'INPUT FIELDS'!AH39," ") -> NA | N22: =IF(B22=C22,'INPUT FIELDS'!AI39," ") -> 2014 | O22: =IF(B22=C22,'INPUT FIELDS'!AJ39," ") -> -
B24: 3 | C24: ='COMPUTATION SHEET'!E28 -> 3 | D24: ='COMPUTATION SHEET'!F28 -> NUNEZ, JOSE JR ADESAS | E24: =IF(B24=C24,'INPUT FIELDS'!Z41," ") -> 15-0070 | F24: =IF(B24=C24,'INPUT FIELDS'!AA41," ") -> 42094 | G24: =IF(B24=C24,'INPUT FIELDS'!AB41," ") -> 42095 | H24: =IF(B24=C24,'INPUT FIELDS'!AC41," ") -> 42095 | I24: =IF(B24=C24,'INPUT FIELDS'!AD41," ") -> 42093 | J24: =IF(B24=C24,'INPUT FIELDS'!AE41," ") -> 42095 | K24: =IF(B24=C24,'INPUT FIELDS'!AF41," ") -> 42095 | L24: =IF(B24=C24,'INPUT FIELDS'!AG41," ") -> 42095 | M24: =IF(B24=C24,'INPUT FIELDS'!AH41," ") -> NA | N24: =IF(B24=C24,'INPUT FIELDS'!AI41," ") -> 2014 | O24: =IF(B24=C24,'INPUT FIELDS'!AJ41," ") -> -
B26: 4 | C26: ='COMPUTATION SHEET'!E30 -> 4 | D26: ='COMPUTATION SHEET'!F30 -> LIMA, NESTOR PELENO | E26: =IF(B26=C26,'INPUT FIELDS'!Z43," ") -> 15-0080 | F26: =IF(B26=C26,'INPUT FIELDS'!AA43," ") -> 42094 | G26: =IF(B26=C26,'INPUT FIELDS'!AB43," ") -> 42087 | H26: =IF(B26=C26,'INPUT FIELDS'!AC43," ") -> 42093 | I26: =IF(B26=C26,'INPUT FIELDS'!AD43," ") -> 42087 | J26: =IF(B26=C26,'INPUT FIELDS'!AE43," ") -> 42087 | K26: =IF(B26=C26,'INPUT FIELDS'!AF43," ") -> 42087 | L26: =IF(B26=C26,'INPUT FIELDS'!AG43," ") -> 42087 | M26: =IF(B26=C26,'INPUT FIELDS'!AH43," ") -> NA | N26: =IF(B26=C26,'INPUT FIELDS'!AI43," ") -> 2014 | O26: =IF(B26=C26,'INPUT FIELDS'!AJ43," ") -> -
B28: 5 | C28: ='COMPUTATION SHEET'!E32 -> 5 | D28: ='COMPUTATION SHEET'!F32 -> ALEGRIA, MARCIANO JR HERNANDEZ | E28: =IF(B28=C28,'INPUT FIELDS'!Z45," ") -> 0 | F28: =IF(B28=C28,'INPUT FIELDS'!AA45," ") -> 42100 | G28: =IF(B28=C28,'INPUT FIELDS'!AB45," ") -> 42095 | H28: =IF(B28=C28,'INPUT FIELDS'!AC45," ") -> 42100 | I28: =IF(B28=C28,'INPUT FIELDS'!AD45," ") -> 42090 | J28: =IF(B28=C28,'INPUT FIELDS'!AE45," ") -> 42100 | K28: =IF(B28=C28,'INPUT FIELDS'!AF45," ") -> 42089 | L28: =IF(B28=C28,'INPUT FIELDS'!AG45," ") -> 42089 | M28: =IF(B28=C28,'INPUT FIELDS'!AH45," ") -> NA | N28: =IF(B28=C28,'INPUT FIELDS'!AI45," ") -> 2014 | O28: =IF(B28=C28,'INPUT FIELDS'!AJ45," ") -> 0
B30: 6 | C30: ='COMPUTATION SHEET'!E34 -> 6 | D30: ='COMPUTATION SHEET'!F34 -> GACELOS, MANOLITO ABARRACOSO | E30: =IF(B30=C30,'INPUT FIELDS'!Z47," ") -> 0 | F30: =IF(B30=C30,'INPUT FIELDS'!AA47," ") -> 42101 | G30: =IF(B30=C30,'INPUT FIELDS'!AB47," ") -> 42101 | H30: =IF(B30=C30,'INPUT FIELDS'!AC47," ") -> 42101 | I30: =IF(B30=C30,'INPUT FIELDS'!AD47," ") -> 42101 | J30: =IF(B30=C30,'INPUT FIELDS'!AE47," ") -> 42101 | K30: =IF(B30=C30,'INPUT FIELDS'!AF47," ") -> 42101 | L30: =IF(B30=C30,'INPUT FIELDS'!AG47," ") -> 42101 | M30: =IF(B30=C30,'INPUT FIELDS'!AH47," ") -> NA | N30: =IF(B30=C30,'INPUT FIELDS'!AI47," ") -> 2014 | O30: =IF(B30=C30,'INPUT FIELDS'!AJ47," ") -> 0
B32: 7 | C32: ='COMPUTATION SHEET'!E36 -> 7 | D32: ='COMPUTATION SHEET'!F36 -> GONZALES, LEONILA HILONGO | E32: =IF(B32=C32,'INPUT FIELDS'!Z49," ") -> 0 | F32: =IF(B32=C32,'INPUT FIELDS'!AA49," ") -> 42100 | G32: =IF(B32=C32,'INPUT FIELDS'!AB49," ") -> 42100 | H32: =IF(B32=C32,'INPUT FIELDS'!AC49," ") -> 42095 | I32: =IF(B32=C32,'INPUT FIELDS'!AD49," ") -> 42095 | J32: =IF(B32=C32,'INPUT FIELDS'!AE49," ") -> 42095 | K32: =IF(B32=C32,'INPUT FIELDS'!AF49," ") -> 42095 | L32: =IF(B32=C32,'INPUT FIELDS'!AG49," ") -> 42095 | M32: =IF(B32=C32,'INPUT FIELDS'!AH49," ") -> NA | N32: =IF(B32=C32,'INPUT FIELDS'!AI49," ") -> 2014 | O32: =IF(B32=C32,'INPUT FIELDS'!AJ49," ") -> 0
B34: 8 | C34: ='COMPUTATION SHEET'!E38 -> 8 | D34: ='COMPUTATION SHEET'!F38 -> MAYOR, CHONA BRANZUELA | E34: =IF(B34=C34,'INPUT FIELDS'!Z51," ") -> 0 | F34: =IF(B34=C34,'INPUT FIELDS'!AA51," ") -> 42100 | G34: =IF(B34=C34,'INPUT FIELDS'!AB51," ") -> 42100 | H34: =IF(B34=C34,'INPUT FIELDS'!AC51," ") -> 42100 | I34: =IF(B34=C34,'INPUT FIELDS'!AD51," ") -> 42095 | J34: =IF(B34=C34,'INPUT FIELDS'!AE51," ") -> 42095 | K34: =IF(B34=C34,'INPUT FIELDS'!AF51," ") -> 42095 | L34: =IF(B34=C34,'INPUT FIELDS'!AG51," ") -> 42094 | M34: =IF(B34=C34,'INPUT FIELDS'!AH51," ") -> NA | N34: =IF(B34=C34,'INPUT FIELDS'!AI51," ") -> 2014 | O34: =IF(B34=C34,'INPUT FIELDS'!AJ51," ") -> 0
B36: 9 | C36: ='COMPUTATION SHEET'!E40 -> 9 | D36: ='COMPUTATION SHEET'!F40 -> YBOA, JONAS ABELIDO | E36: =IF(B36=C36,'INPUT FIELDS'!Z53," ") -> 0 | F36: =IF(B36=C36,'INPUT FIELDS'!AA53," ") -> 42100 | G36: =IF(B36=C36,'INPUT FIELDS'!AB53," ") -> 42093 | H36: =IF(B36=C36,'INPUT FIELDS'!AC53," ") -> 42090 | I36: =IF(B36=C36,'INPUT FIELDS'!AD53," ") -> 42093 | J36: =IF(B36=C36,'INPUT FIELDS'!AE53," ") -> 42090 | K36: =IF(B36=C36,'INPUT FIELDS'!AF53," ") -> 42093 | L36: =IF(B36=C36,'INPUT FIELDS'!AG53," ") -> 42090 | M36: =IF(B36=C36,'INPUT FIELDS'!AH53," ") -> NA | N36: =IF(B36=C36,'INPUT FIELDS'!AI53," ") -> 2014 | O36: =IF(B36=C36,'INPUT FIELDS'!AJ53," ") -> 0
B38: 10 | C38: ='COMPUTATION SHEET'!E42 -> 10 | D38: ='COMPUTATION SHEET'!F42 -> GONZALES, RUBIA ABARCAR | E38: =IF(B38=C38,'INPUT FIELDS'!Z55," ") -> 0 | F38: =IF(B38=C38,'INPUT FIELDS'!AA55," ") -> 42100 | G38: =IF(B38=C38,'INPUT FIELDS'!AB55," ") -> 42093 | H38: =IF(B38=C38,'INPUT FIELDS'!AC55," ") -> 42100 | I38: =IF(B38=C38,'INPUT FIELDS'!AD55," ") -> 42095 | J38: =IF(B38=C38,'INPUT FIELDS'!AE55," ") -> 42095 | K38: =IF(B38=C38,'INPUT FIELDS'!AF55," ") -> 42095 | L38: =IF(B38=C38,'INPUT FIELDS'!AG55," ") -> 42094 | M38: =IF(B38=C38,'INPUT FIELDS'!AH55," ") -> NA | N38: =IF(B38=C38,'INPUT FIELDS'!AI55," ") -> 2014 | O38: =IF(B38=C38,'INPUT FIELDS'!AJ55," ") -> 0
B40: 11 | C40: ='COMPUTATION SHEET'!E44 -> 11 | D40: ='COMPUTATION SHEET'!F44 -> ARCALES, DOMINGO JR JADLOC | E40: =IF(B40=C40,'INPUT FIELDS'!Z57," ") -> 0 | F40: =IF(B40=C40,'INPUT FIELDS'!AA57," ") -> 42100 | G40: =IF(B40=C40,'INPUT FIELDS'!AB57," ") -> 42100 | H40: =IF(B40=C40,'INPUT FIELDS'!AC57," ") -> 42095 | I40: =IF(B40=C40,'INPUT FIELDS'!AD57," ") -> 42093 | J40: =IF(B40=C40,'INPUT FIELDS'!AE57," ") -> 42093 | K40: =IF(B40=C40,'INPUT FIELDS'!AF57," ") -> 42093 | L40: =IF(B40=C40,'INPUT FIELDS'!AG57," ") -> 42095 | M40: =IF(B40=C40,'INPUT FIELDS'!AH57," ") -> NA | N40: =IF(B40=C40,'INPUT FIELDS'!AI57," ") -> 2014 | O40: =IF(B40=C40,'INPUT FIELDS'!AJ57," ") -> 0
B42: 12 | C42: ='COMPUTATION SHEET'!E46 -> 12 | D42: ='COMPUTATION SHEET'!F46 -> GACELOS, REBECCA TILLES | E42: =IF(B42=C42,'INPUT FIELDS'!Z59," ") -> 0 | F42: =IF(B42=C42,'INPUT FIELDS'!AA59," ") -> 42101 | G42: =IF(B42=C42,'INPUT FIELDS'!AB59," ") -> 42100 | H42: =IF(B42=C42,'INPUT FIELDS'!AC59," ") -> 42100 | I42: =IF(B42=C42,'INPUT FIELDS'!AD59," ") -> 42093 | J42: =IF(B42=C42,'INPUT FIELDS'!AE59," ") -> 42093 | K42: =IF(B42=C42,'INPUT FIELDS'!AF59," ") -> 42100 | L42: =IF(B42=C42,'INPUT FIELDS'!AG59," ") -> 42093 | M42: =IF(B42=C42,'INPUT FIELDS'!AH59," ") -> NA | N42: =IF(B42=C42,'INPUT FIELDS'!AI59," ") -> 2014 | O42: =IF(B42=C42,'INPUT FIELDS'!AJ59," ") -> 0
... B58: 20 | C58: ='COMPUTATION SHEET'!E62 | D58: ='COMPUTATION SHEET'!F62 | E58: =IF(B58=C58,'INPUT FIELDS'!Z75," ") | F58: =IF(B58=C58,'INPUT FIELDS'!AA75," ") | G58: =IF(B58=C58,'INPUT FIELDS'!AB75," ") | H58: =IF(B58=C58,'INPUT FIELDS'!AC75," ") | I58: =IF(B58=C58,'INPUT FIELDS'!AD75," ") | J58: =IF(B58=C58,'INPUT FIELDS'!AE75," ") | K58: =IF(B58=C58,'INPUT FIELDS'!AF75," ") | L58: =IF(B58=C58,'INPUT FIELDS'!AG75," ") | M58: =IF(B58=C58,'INPUT FIELDS'!AH75," ") | N58: =IF(B58=C58,'INPUT FIELDS'!AI75," ") | O58: =IF(B58=C58,'INPUT FIELDS'!AJ75," ")
D61: =Signatories!C9 -> JANICE B. SOLAYAO | E61: Date:__________________________ | I61: =Signatories!C11 -> SM HELBERT ANTOINE A. ACHAY | M61: Date:____________________
D62: Relationship Officer | I62: Head, Catbalogan Branch
D63: (Signature over Printed Name) | I63: (Signature over Printed Name)

Sheet NFIS REQUEST
B3: DEVELOPMENT BANK OF THE PHILIPPINES | H3: ANNEX C-1
B4: BRANCH: | C4: =Signatories!C13 -> CATBALOGAN
B5: RMC: | C5: =Signatories!C15 -> EASTERN VISAYAS
B6: INQUIRY DATE: | C6: ='INPUT FIELDS'!D24 -> 42094
B8: LIST OF INQUIRIES
B10: BEGIN
B11: IB_FNAM | C11: IB_MNAM | D11: IB_LNAM | E11: IB_BIRTH | F11: IB_TAN | G11: IB_SPOUSE | H11: IB_ADDR1 | I11: RECKEY | J11: IB_BANKCD
A12: 1 | B12: ='INPUT FIELDS'!AM37 -> MARIA EMY | C12: ='INPUT FIELDS'!AN37 -> TAN | D12: ='INPUT FIELDS'!AL37 -> RABADAM | E12: ='INPUT FIELDS'!AR37 -> 29144 | F12: ='INPUT FIELDS'!AQ37 -> 943994147 | G12: ='INPUT FIELDS'!AO37 -> ARNEL B RABADAM | H12: ='INPUT FIELDS'!AP37 -> 202 CURRY AVENUE CATBALOGAN CITY SAMAR | I12: ='INPUT FIELDS'!AS37 -> PROVINCE OF SAMAR1 | J12: ='INPUT FIELDS'!AT37 -> DBP
A14: 2 | B14: ='INPUT FIELDS'!AM39 -> ALLAN | C14: ='INPUT FIELDS'!AN39 -> GULFERIC | D14: ='INPUT FIELDS'!AL39 -> LEJAS | E14: ='INPUT FIELDS'!AR39 -> 30469 | F14: ='INPUT FIELDS'!AQ39 -> 273165815 | G14: ='INPUT FIELDS'!AO39 -> MARIAN DAGANZO LEJAS | H14: ='INPUT FIELDS'!AP39 -> PUROK 1 BRGY CANLAPWAS CATBALOGAN CITY SAMAR | I14: ='INPUT FIELDS'!AS39 -> PROVINCE OF SAMAR2 | J14: ='INPUT FIELDS'!AT39 -> DBP
A16: 3 | B16: ='INPUT FIELDS'!AM41 -> JOSE JR | C16: ='INPUT FIELDS'!AN41 -> ADESAS | D16: ='INPUT FIELDS'!AL41 -> NUNEZ | E16: ='INPUT FIELDS'!AR41 -> 112566 | F16: ='INPUT FIELDS'!AQ41 -> 184693732 | G16: ='INPUT FIELDS'!AO41 -> ERLINDA BACUETES NUNEZ | H16: ='INPUT FIELDS'!AP41 -> 352 RIZAL AVENUE BRGY 12 CATBALOGAN CITY SAMAR | I16: ='INPUT FIELDS'!AS41 -> PROVINCE OF SAMAR3 | J16: ='INPUT FIELDS'!AT41 -> DBP
A18: 4 | B18: ='INPUT FIELDS'!AM43 -> NESTOR | C18: ='INPUT FIELDS'!AN43 -> PELENO | D18: ='INPUT FIELDS'!AL43 -> LIMA | E18: ='INPUT FIELDS'!AR43 -> 20219 | F18: ='INPUT FIELDS'!AQ43 -> 130157835 | G18: ='INPUT FIELDS'!AO43 -> MARY GEN ISANAN LIMA | H18: ='INPUT FIELDS'!AP43 -> PATONG STREET BRGY GUINSORONGAN CATBALOGAN CITY | I18: ='INPUT FIELDS'!AS43 -> PROVINCE OF SAMAR4 | J18: ='INPUT FIELDS'!AT43 -> DBP
A20: 5 | B20: ='INPUT FIELDS'!AM45 -> MARCIANO JR | C20: ='INPUT FIELDS'!AN45 -> HERNANDEZ | D20: ='INPUT FIELDS'!AL45 -> ALEGRIA | E20: ='INPUT FIELDS'!AR45 -> 26900 | F20: ='INPUT FIELDS'!AQ45 -> 905838005 | G20: ='INPUT FIELDS'!AO45 -> MARILYN SOLAYAO ALEGRIA | H20: ='INPUT FIELDS'!AP45 -> P2 BRGY JIA AN JIABONG SAMAR | I20: ='INPUT FIELDS'!AS45 -> PROVINCE OF SAMAR5 | J20: ='INPUT FIELDS'!AT45 -> DBP
A22: 6 | B22: ='INPUT FIELDS'!AM47 -> MANOLITO | C22: ='INPUT FIELDS'!AN47 -> ABARRACOSO | D22: ='INPUT FIELDS'!AL47 -> GACELOS | E22: ='INPUT FIELDS'!AR47 -> 28260 | F22: ='INPUT FIELDS'!AQ47 -> 400532413 | G22: ='INPUT FIELDS'!AO47 -> CHERIE N GACELOS | H22: ='INPUT FIELDS'!AP47 -> BRGY RAWIS HINABANGAN SAMAR | I22: ='INPUT FIELDS'!AS47 -> PROVINCE OF SAMAR6 | J22: ='INPUT FIELDS'!AT47 -> DBP
A24: 7 | B24: ='INPUT FIELDS'!AM49 -> LEONILA | C24: ='INPUT FIELDS'!AN49 -> HILONGO | D24: ='INPUT FIELDS'!AL49 -> GONZALES | E24: ='INPUT FIELDS'!AR49 -> 20852 | F24: ='INPUT FIELDS'!AQ49 -> 129842327 | G24: ='INPUT FIELDS'!AO49 -> 0 | H24: ='INPUT FIELDS'!AP49 -> BRGY SAN JOSE ALMAGRO WESTERN SAMAR | I24: ='INPUT FIELDS'!AS49 -> PROVINCE OF SAMAR7 | J24: ='INPUT FIELDS'!AT49 -> DBP
A26: 8 | B26: ='INPUT FIELDS'!AM51 -> CHONA | C26: ='INPUT FIELDS'!AN51 -> BRANZUELA | D26: ='INPUT FIELDS'!AL51 -> MAYOR | E26: ='INPUT FIELDS'!AR51 -> 24599 | F26: ='INPUT FIELDS'!AQ51 -> 947543937 | G26: ='INPUT FIELDS'!AO51 -> VENG JAYCO B MAYOR | H26: ='INPUT FIELDS'!AP51 -> BRGY PANJOBJOBAN ALMAGRO SAMAR | I26: ='INPUT FIELDS'!AS51 -> PROVINCE OF SAMAR4 | J26: ='INPUT FIELDS'!AT51 -> DBP
A28: 9 | B28: ='INPUT FIELDS'!AM53 -> JONAS | C28: ='INPUT FIELDS'!AN53 -> ABELIDO | D28: ='INPUT FIELDS'!AL53 -> YBOA | E28: ='INPUT FIELDS'!AR53 -> 25868 | F28: ='INPUT FIELDS'!AQ53 -> 174344327 | G28: ='INPUT FIELDS'!AO53 -> NANCY ALBOS YBOA | H28: ='INPUT FIELDS'!AP53 -> 5TH ST COR BANOYO ST BRGY 10 CATBALOGAN CITY SAMAR | I28: ='INPUT FIELDS'!AS53 -> PROVINCE OF SAMAR9 | J28: ='INPUT FIELDS'!AT53 -> DBP
A30: 10 | B30: ='INPUT FIELDS'!AM55 -> RUBIA | C30: ='INPUT FIELDS'!AN55 -> ABARCAR | D30: ='INPUT FIELDS'!AL55 -> GONZALES | E30: ='INPUT FIELDS'!AR55 -> 22656 | F30: ='INPUT FIELDS'!AQ55 -> 166545733 | G30: ='INPUT FIELDS'!AO55 -> NELSON VILLANUEVA GONZALES | H30: ='INPUT FIELDS'!AP55 -> NO 20 B 2 LOT 8 BLISS CANLAPWAS CATBALOGAN CITY | I30: ='INPUT FIELDS'!AS55 -> PROVINCE OF SAMAR10 | J30: ='INPUT FIELDS'!AT55 -> DBP
A32: 11 | B32: ='INPUT FIELDS'!AM57 -> DOMINGO JR | C32: ='INPUT FIELDS'!AN57 -> JADLOC | D32: ='INPUT FIELDS'!AL57 -> ARCALES | E32: ='INPUT FIELDS'!AR57 -> 24098 | F32: ='INPUT FIELDS'!AQ57 -> 914894035 | G32: ='INPUT FIELDS'!AO57 -> 0 | H32: ='INPUT FIELDS'!AP57 -> 491 PUROK 3 BRGY MERCEDES CATBALOGAN CITY | I32: ='INPUT FIELDS'!AS57 -> PROVINCE OF SAMAR11 | J32: ='INPUT FIELDS'!AT57 -> DBP
A34: 12 | B34: ='INPUT FIELDS'!AM59 -> REBECCA | C34: ='INPUT FIELDS'!AN59 -> TILLES | D34: ='INPUT FIELDS'!AL59 -> GACELOS | E34: ='INPUT FIELDS'!AR59 -> 19920 | F34: ='INPUT FIELDS'!AQ59 -> 131439004 | G34: ='INPUT FIELDS'!AO59 -> 0 | H34: ='INPUT FIELDS'!AP59 -> 117 P 2 BRGY MAULONG CATBALOGAN CITY SAMAR | I34: ='INPUT FIELDS'!AS59 -> PROVINCE OF SAMAR12 | J34: ='INPUT FIELDS'!AT59 -> DBP
... A50: 20 | B50: ='INPUT FIELDS'!AM75 -> 0 | C50: ='INPUT FIELDS'!AN75 -> 0 | D50: ='INPUT FIELDS'!AL75 -> 0 | E50: ='INPUT FIELDS'!AR75 -> 0 | F50: ='INPUT FIELDS'!AQ75 -> 0 | G50: ='INPUT FIELDS'!AO75 -> 0 | H50: ='INPUT FIELDS'!AP75 -> 0 | I50: ='INPUT FIELDS'!AS75 -> 0 | J50: ='INPUT FIELDS'!AT75 -> DBP
B51: END
D53: notes: | E53: 1. Encode in all caps
E54: 2. No special characters
E55: 3. File name should include branch name.
E56: (Format: INQ + first three letters of branch name + date of inquiry mmddyy)
E57: Example: INQCLA121013 for Clark Branch inquiry on December 10, 2013
B59: PREPARED BY: | F59: NOTED BY:
B62: =Signatories!C9 -> JANICE B. SOLAYAO | F62: =Signatories!C11 -> SM HELBERT ANTOINE A. ACHAY
B63: (Relationship Officer) | F63: (Branch Head)

Sheet 3YR TERM
A2: 3 | B2: DBP SALARY LOAN PROGRAM | J2: MRI PER 1,000.00
B3: AMORTIZATION & NET PROCEEDS COMPUTATION | J3: 1-12 MOS | K3: 5.35
B4: (FOR TERM OF LOAN OF 3 YEARS ONLY) | J4: 13-24 MOS | K4: 6.58
B5: Loan Amount | C5: Monthly Amort | D5: MRI Premium | E5: Service Fee | F5: Doc Stamps | G5: Net-Take Loan Proceeds | J5: 25-36 MOS | K5: 9.04
G6: No Hold-out | H6: with 2 mos Hold-out
A8: 1 | B8: 48000 | C8: =-PMT(12.651%/12,36,B8) -> 1609.2527 | D8: =(B8/1000)*9.04 -> 433.92 | E8: =0.01*B8 -> 480 | F8: =IF(B8<250000,0,B8/200) -> 0 | G8: =B8-D8-E8-F8 -> 47086.08 | H8: =B8-D8-E8-F8-(2*C8) -> 43867.575 | J8: =C8*2 -> 3218.5054
A9: 2 | B9: 20000 | C9: =-PMT(12.651%/12,36,B9) -> 670.52195 | D9: =(B9/1000)*9.04 -> 180.8 | E9: =0.01*B9 -> 200 | F9: =IF(B9<250000,0,B9/200) -> 0 | G9: =B9-D9-E9-F9 -> 19619.2 | H9: =B9-D9-E9-F9-(2*C9) -> 18278.156
A10: 3 | B10: 25000 | C10: =-PMT(12.651%/12,36,B10) -> 838.15244 | D10: =(B10/1000)*9.04 -> 226 | E10: =0.01*B10 -> 250 | F10: =IF(B10<250000,0,B10/200) -> 0 | G10: =B10-D10-E10-F10 -> 24524 | H10: =B10-D10-E10-F10-(2*C10) -> 22847.695
A11: 4 | B11: 30000 | C11: =-PMT(12.651%/12,36,B11) -> 1005.7829 | D11: =(B11/1000)*9.04 -> 271.2 | E11: =0.01*B11 -> 300 | F11: =IF(B11<250000,0,B11/200) -> 0 | G11: =B11-D11-E11-F11 -> 29428.8 | H11: =B11-D11-E11-F11-(2*C11) -> 27417.234
A12: 5 | B12: 35000 | C12: =-PMT(12.651%/12,36,B12) -> 1173.4134 | D12: =(B12/1000)*9.04 -> 316.4 | E12: =0.01*B12 -> 350 | F12: =IF(B12<250000,0,B12/200) -> 0 | G12: =B12-D12-E12-F12 -> 34333.6 | H12: =B12-D12-E12-F12-(2*C12) -> 31986.773
A13: 6 | B13: 40000 | C13: =-PMT(12.651%/12,36,B13) -> 1341.0439 | D13: =(B13/1000)*9.04 -> 361.6 | E13: =0.01*B13 -> 400 | F13: =IF(B13<250000,0,B13/200) -> 0 | G13: =B13-D13-E13-F13 -> 39238.4 | H13: =B13-D13-E13-F13-(2*C13) -> 36556.312
A14: 7 | B14: 45000 | C14: =-PMT(12.651%/12,36,B14) -> 1508.6744 | D14: =(B14/1000)*9.04 -> 406.8 | E14: =0.01*B14 -> 450 | F14: =IF(B14<250000,0,B14/200) -> 0 | G14: =B14-D14-E14-F14 -> 44143.2 | H14: =B14-D14-E14-F14-(2*C14) -> 41125.851
A15: 8 | B15: 50000 | C15: =-PMT(12.651%/12,36,B15) -> 1676.3049 | D15: =(B15/1000)*9.04 -> 452 | E15: =0.01*B15 -> 500 | F15: =IF(B15<250000,0,B15/200) -> 0 | G15: =B15-D15-E15-F15 -> 49048 | H15: =B15-D15-E15-F15-(2*C15) -> 45695.39
A16: 9 | B16: 55000 | C16: =-PMT(12.651%/12,36,B16) -> 1843.9354 | D16: =(B16/1000)*9.04 -> 497.2 | E16: =0.01*B16 -> 550 | F16: =IF(B16<250000,0,B16/200) -> 0 | G16: =B16-D16-E16-F16 -> 53952.8 | H16: =B16-D16-E16-F16-(2*C16) -> 50264.929
A17: 10 | B17: 60000 | C17: =-PMT(12.651%/12,36,B17) -> 2011.5659 | D17: =(B17/1000)*9.04 -> 542.4 | E17: =0.01*B17 -> 600 | F17: =IF(B17<250000,0,B17/200) -> 0 | G17: =B17-D17-E17-F17 -> 58857.6 | H17: =B17-D17-E17-F17-(2*C17) -> 54834.468
A18: 11 | B18: 65000 | C18: =-PMT(12.651%/12,36,B18) -> 2179.1964 | D18: =(B18/1000)*9.04 -> 587.6 | E18: =0.01*B18 -> 650 | F18: =IF(B18<250000,0,B18/200) -> 0 | G18: =B18-D18-E18-F18 -> 63762.4 | H18: =B18-D18-E18-F18-(2*C18) -> 59404.007
A19: 12 | B19: 70000 | C19: =-PMT(12.651%/12,36,B19) -> 2346.8268 | D19: =(B19/1000)*9.04 -> 632.8 | E19: =0.01*B19 -> 700 | F19: =IF(B19<250000,0,B19/200) -> 0 | G19: =B19-D19-E19-F19 -> 68667.2 | H19: =B19-D19-E19-F19-(2*C19) -> 63973.546
A20: 13 | B20: 75000 | C20: =-PMT(12.651%/12,36,B20) -> 2514.4573 | D20: =(B20/1000)*9.04 -> 678 | E20: =0.01*B20 -> 750 | F20: =IF(B20<250000,0,B20/200) -> 0 | G20: =B20-D20-E20-F20 -> 73572 | H20: =B20-D20-E20-F20-(2*C20) -> 68543.085
... A85: 78 | B85: 400000 | C85: =-PMT(12.651%/12,36,B85) -> 13410.439 | D85: =(B85/1000)*9.04 -> 3616 | E85: =0.01*B85 -> 4000 | F85: =IF(B85<250000,0,B85/200) -> 2000 | G85: =B85-D85-E85-F85 -> 390384 | H85: =B85-D85-E85-F85-(2*C85) -> 363563.12

Sheet 2YR TERM
A2: 2 | B2: DBP SALARY LOAN PROGRAM | J2: MRI PER 1,000.00
B3: AMORTIZATION & NET PROCEEDS COMPUTATION | J3: 1-12 MOS | K3: 5.35
B4: (FOR TERM OF LOAN OF 2 YEARS ONLY) | J4: 13-24 MOS | K4: 6.58
B5: Loan Amount | C5: Monthly Amort | D5: MRI Premium | E5: Service Fee | F5: Doc Stamps | G5: Net-Take Loan Proceeds | J5: 25-36 MOS | K5: 9.04
G6: No Hold-out | H6: with 2 mos Hold-out
A8: 1 | B8: =9500*3 -> 28500 | C8: =-PMT(12.651%/12,24,B8) -> 1350.2747 | D8: =(B8/1000)*6.58 -> 187.53 | E8: =0.01*B8 -> 285 | F8: =IF(B8<250000,0,B8/200) -> 0 | G8: =B8-D8-E8-F8 -> 28027.47 | H8: =B8-D8-E8-F8-(2*C8) -> 25326.921
A9: 2 | B9: 20000 | C9: =-PMT(12.651%/12,24,B9) -> 947.5612 | D9: =(B9/1000)*6.58 -> 131.6 | E9: =0.01*B9 -> 200 | F9: =IF(B9<250000,0,B9/200) -> 0 | G9: =B9-D9-E9-F9 -> 19668.4 | H9: =B9-D9-E9-F9-(2*C9) -> 17773.278
A10: 3 | B10: 25000 | C10: =-PMT(12.651%/12,24,B10) -> 1184.4515 | D10: =(B10/1000)*6.58 -> 164.5 | E10: =0.01*B10 -> 250 | F10: =IF(B10<250000,0,B10/200) -> 0 | G10: =B10-D10-E10-F10 -> 24585.5 | H10: =B10-D10-E10-F10-(2*C10) -> 22216.597
A11: 4 | B11: 30000 | C11: =-PMT(12.651%/12,24,B11) -> 1421.3418 | D11: =(B11/1000)*6.58 -> 197.4 | E11: =0.01*B11 -> 300 | F11: =IF(B11<250000,0,B11/200) -> 0 | G11: =B11-D11-E11-F11 -> 29502.6 | H11: =B11-D11-E11-F11-(2*C11) -> 26659.916
A12: 5 | B12: 35000 | C12: =-PMT(12.651%/12,24,B12) -> 1658.2321 | D12: =(B12/1000)*6.58 -> 230.3 | E12: =0.01*B12 -> 350 | F12: =IF(B12<250000,0,B12/200) -> 0 | G12: =B12-D12-E12-F12 -> 34419.7 | H12: =B12-D12-E12-F12-(2*C12) -> 31103.236
A13: 6 | B13: 40000 | C13: =-PMT(12.651%/12,24,B13) -> 1895.1224 | D13: =(B13/1000)*6.58 -> 263.2 | E13: =0.01*B13 -> 400 | F13: =IF(B13<250000,0,B13/200) -> 0 | G13: =B13-D13-E13-F13 -> 39336.8 | H13: =B13-D13-E13-F13-(2*C13) -> 35546.555
A14: 7 | B14: 45000 | C14: =-PMT(12.651%/12,24,B14) -> 2132.0127 | D14: =(B14/1000)*6.58 -> 296.1 | E14: =0.01*B14 -> 450 | F14: =IF(B14<250000,0,B14/200) -> 0 | G14: =B14-D14-E14-F14 -> 44253.9 | H14: =B14-D14-E14-F14-(2*C14) -> 39989.875
A15: 8 | B15: 50000 | C15: =-PMT(12.651%/12,24,B15) -> 2368.903 | D15: =(B15/1000)*6.58 -> 329 | E15: =0.01*B15 -> 500 | F15: =IF(B15<250000,0,B15/200) -> 0 | G15: =B15-D15-E15-F15 -> 49171 | H15: =B15-D15-E15-F15-(2*C15) -> 44433.194
A16: 9 | B16: 55000 | C16: =-PMT(12.651%/12,24,B16) -> 2605.7933 | D16: =(B16/1000)*6.58 -> 361.9 | E16: =0.01*B16 -> 550 | F16: =IF(B16<250000,0,B16/200) -> 0 | G16: =B16-D16-E16-F16 -> 54088.1 | H16: =B16-D16-E16-F16-(2*C16) -> 48876.513
A17: 10 | B17: 60000 | C17: =-PMT(12.651%/12,24,B17) -> 2842.6836 | D17: =(B17/1000)*6.58 -> 394.8 | E17: =0.01*B17 -> 600 | F17: =IF(B17<250000,0,B17/200) -> 0 | G17: =B17-D17-E17-F17 -> 59005.2 | H17: =B17-D17-E17-F17-(2*C17) -> 53319.833
A18: 11 | B18: 65000 | C18: =-PMT(12.651%/12,24,B18) -> 3079.5739 | D18: =(B18/1000)*6.58 -> 427.7 | E18: =0.01*B18 -> 650 | F18: =IF(B18<250000,0,B18/200) -> 0 | G18: =B18-D18-E18-F18 -> 63922.3 | H18: =B18-D18-E18-F18-(2*C18) -> 57763.152
A19: 12 | B19: 70000 | C19: =-PMT(12.651%/12,24,B19) -> 3316.4642 | D19: =(B19/1000)*6.58 -> 460.6 | E19: =0.01*B19 -> 700 | F19: =IF(B19<250000,0,B19/200) -> 0 | G19: =B19-D19-E19-F19 -> 68839.4 | H19: =B19-D19-E19-F19-(2*C19) -> 62206.472
A20: 13 | B20: 75000 | C20: =-PMT(12.651%/12,24,B20) -> 3553.3545 | D20: =(B20/1000)*6.58 -> 493.5 | E20: =0.01*B20 -> 750 | F20: =IF(B20<250000,0,B20/200) -> 0 | G20: =B20-D20-E20-F20 -> 73756.5 | H20: =B20-D20-E20-F20-(2*C20) -> 66649.791
... A85: 78 | B85: 400000 | C85: =-PMT(12.651%/12,24,B85) -> 18951.224 | D85: =(B85/1000)*6.58 -> 2632 | E85: =0.01*B85 -> 4000 | F85: =IF(B85<250000,0,B85/200) -> 2000 | G85: =B85-D85-E85-F85 -> 391368 | H85: =B85-D85-E85-F85-(2*C85) -> 353465.55

Sheet 1YR TERM
A2: 1 | B2: DBP SALARY LOAN PROGRAM | J2: MRI PER 1,000.00
B3: AMORTIZATION & NET PROCEEDS COMPUTATION | J3: 1-12 MOS | K3: 5.35
B4: (FOR TERM OF LOAN OF 1 YEAR ONLY) | J4: 13-24 MOS | K4: 6.58
B5: Loan Amount | C5: Monthly Amort | D5: MRI Premium | E5: Service Fee | F5: Doc Stamps | G5: Net-Take Loan Proceeds | J5: 25-36 MOS | K5: 9.04
G6: No Hold-out | H6: with 2 mos Hold-out
A8: 1 | B8: 15000 | C8: =-PMT(12.651%/12,12,B8) -> 1337.3043 | D8: =(B8/1000)*5.35 -> 80.25 | E8: =0.01*B8 -> 150 | F8: =IF(B8<250000,0,B8/200) -> 0 | G8: =B8-D8-E8-F8 -> 14769.75 | H8: =B8-D8-E8-F8-(2*C8) -> 12095.141
A9: 2 | B9: 20000 | C9: =-PMT(12.651%/12,12,B9) -> 1783.0724 | D9: =(B9/1000)*5.35 -> 107 | E9: =0.01*B9 -> 200 | F9: =IF(B9<250000,0,B9/200) -> 0 | G9: =B9-D9-E9-F9 -> 19693 | H9: =B9-D9-E9-F9-(2*C9) -> 16126.855
A10: 3 | B10: 25000 | C10: =-PMT(12.651%/12,12,B10) -> 2228.8405 | D10: =(B10/1000)*5.35 -> 133.75 | E10: =0.01*B10 -> 250 | F10: =IF(B10<250000,0,B10/200) -> 0 | G10: =B10-D10-E10-F10 -> 24616.25 | H10: =B10-D10-E10-F10-(2*C10) -> 20158.569
A11: 4 | B11: 30000 | C11: =-PMT(12.651%/12,12,B11) -> 2674.6086 | D11: =(B11/1000)*5.35 -> 160.5 | E11: =0.01*B11 -> 300 | F11: =IF(B11<250000,0,B11/200) -> 0 | G11: =B11-D11-E11-F11 -> 29539.5 | H11: =B11-D11-E11-F11-(2*C11) -> 24190.283
A12: 5 | B12: 35000 | C12: =-PMT(12.651%/12,12,B12) -> 3120.3767 | D12: =(B12/1000)*5.35 -> 187.25 | E12: =0.01*B12 -> 350 | F12: =IF(B12<250000,0,B12/200) -> 0 | G12: =B12-D12-E12-F12 -> 34462.75 | H12: =B12-D12-E12-F12-(2*C12) -> 28221.997
A13: 6 | B13: 40000 | C13: =-PMT(12.651%/12,12,B13) -> 3566.1448 | D13: =(B13/1000)*5.35 -> 214 | E13: =0.01*B13 -> 400 | F13: =IF(B13<250000,0,B13/200) -> 0 | G13: =B13-D13-E13-F13 -> 39386 | H13: =B13-D13-E13-F13-(2*C13) -> 32253.71
A14: 7 | B14: 45000 | C14: =-PMT(12.651%/12,12,B14) -> 4011.9129 | D14: =(B14/1000)*5.35 -> 240.75 | E14: =0.01*B14 -> 450 | F14: =IF(B14<250000,0,B14/200) -> 0 | G14: =B14-D14-E14-F14 -> 44309.25 | H14: =B14-D14-E14-F14-(2*C14) -> 36285.424
A15: 8 | B15: 50000 | C15: =-PMT(12.651%/12,12,B15) -> 4457.681 | D15: =(B15/1000)*5.35 -> 267.5 | E15: =0.01*B15 -> 500 | F15: =IF(B15<250000,0,B15/200) -> 0 | G15: =B15-D15-E15-F15 -> 49232.5 | H15: =B15-D15-E15-F15-(2*C15) -> 40317.138
A16: 9 | B16: 55000 | C16: =-PMT(12.651%/12,12,B16) -> 4903.4491 | D16: =(B16/1000)*5.35 -> 294.25 | E16: =0.01*B16 -> 550 | F16: =IF(B16<250000,0,B16/200) -> 0 | G16: =B16-D16-E16-F16 -> 54155.75 | H16: =B16-D16-E16-F16-(2*C16) -> 44348.852
A17: 10 | B17: 60000 | C17: =-PMT(12.651%/12,12,B17) -> 5349.2172 | D17: =(B17/1000)*5.35 -> 321 | E17: =0.01*B17 -> 600 | F17: =IF(B17<250000,0,B17/200) -> 0 | G17: =B17-D17-E17-F17 -> 59079 | H17: =B17-D17-E17-F17-(2*C17) -> 48380.566
A18: 11 | B18: 65000 | C18: =-PMT(12.651%/12,12,B18) -> 5794.9853 | D18: =(B18/1000)*5.35 -> 347.75 | E18: =0.01*B18 -> 650 | F18: =IF(B18<250000,0,B18/200) -> 0 | G18: =B18-D18-E18-F18 -> 64002.25 | H18: =B18-D18-E18-F18-(2*C18) -> 52412.279
A19: 12 | B19: 70000 | C19: =-PMT(12.651%/12,12,B19) -> 6240.7534 | D19: =(B19/1000)*5.35 -> 374.5 | E19: =0.01*B19 -> 700 | F19: =IF(B19<250000,0,B19/200) -> 0 | G19: =B19-D19-E19-F19 -> 68925.5 | H19: =B19-D19-E19-F19-(2*C19) -> 56443.993
... A85: 78 | B85: 400000 | C85: =-PMT(12.651%/12,12,B85) -> 35661.448 | D85: =(B85/1000)*5.35 -> 2140 | E85: =0.01*B85 -> 4000 | F85: =IF(B85<250000,0,B85/200) -> 2000 | G85: =B85-D85-E85-F85 -> 391860 | H85: =B85-D85-E85-F85-(2*C85) -> 320537.1

Sheet NOTICE OF APPROVAL and PNs
F5: Development Bank of the Philippines | R5: Development Bank of the Philippines | AD5: Development Bank of the Philippines | AP5: Development Bank of the Philippines | BB5: Development Bank of the Philippines | BN5: Development Bank of the Philippines | BZ5: Development Bank of the Philippines | CL5: Development Bank of the Philippines | CX5: Development Bank of the Philippines | DJ5: Development Bank of the Philippines | DV5: Development Bank of the Philippines | EH5: Development Bank of the Philippines | EU5: Development Bank of the Philippines | FG5: Development Bank of the Philippines | FS5: Development Bank of the Philippines | GE5: Development Bank of the Philippines | GQ5: Development Bank of the Philippines | HC5: Development Bank of the Philippines | HO5: Development Bank of the Philippines | IA5: Development Bank of the Philippines
I9: =NOW() -> 46084.283 | U9: =NOW() -> 46084.283 | AG9: =NOW() -> 46084.283 | AS9: =NOW() -> 46084.283 | BE9: =NOW() -> 46084.283 | BQ9: =NOW() -> 46084.283 | CC9: =NOW() -> 46084.283 | CO9: =NOW() -> 46084.283 | DA9: =NOW() -> 46084.283 | DM9: =NOW() -> 46084.283 | DY9: =NOW() -> 46084.283 | EK9: =NOW() -> 46084.283 | EX9: =NOW() -> 46084.283 | FJ9: =NOW() -> 46084.283 | FV9: =NOW() -> 46084.283 | GH9: =NOW() -> 46084.283 | GT9: =NOW() -> 46084.283 | HF9: =NOW() -> 46084.283 | HR9: =NOW() -> 46084.283 | ID9: =NOW() -> 46084.283
C13: =CONCATENATE('INPUT FIELDS'!D8," ",'INPUT FIELDS'!D9," ",'INPUT FIELDS'!D7) -> MARIA EMY TAN RABADAM | O13: =CONCATENATE('INPUT FIELDS'!AV8," ",'INPUT FIELDS'!AV9," ",'INPUT FIELDS'!AV7) -> ALLAN GULFERIC LEJAS | AA13: =CONCATENATE('INPUT FIELDS'!AX8," ",'INPUT FIELDS'!AX9," ",'INPUT FIELDS'!AX7) -> JOSE JR ADESAS NUNEZ | AM13: =CONCATENATE('INPUT FIELDS'!AZ8," ",'INPUT FIELDS'!AZ9," ",'INPUT FIELDS'!AZ7) -> NESTOR PELENO LIMA | AY13: =CONCATENATE('INPUT FIELDS'!BB8," ",'INPUT FIELDS'!BB9," ",'INPUT FIELDS'!BB7) -> MARCIANO JR HERNANDEZ ALEGRIA | BK13: =CONCATENATE('INPUT FIELDS'!BD8," ",'INPUT FIELDS'!BD9," ",'INPUT FIELDS'!BD7) -> MANOLITO ABARRACOSO GACELOS | BW13: =CONCATENATE('INPUT FIELDS'!BF8," ",'INPUT FIELDS'!BF9," ",'INPUT FIELDS'!BF7) -> LEONILA HILONGO GONZALES | CI13: =CONCATENATE('INPUT FIELDS'!BH8," ",'INPUT FIELDS'!BH9," ",'INPUT FIELDS'!BH7) -> CHONA BRANZUELA MAYOR | CU13: =CONCATENATE('INPUT FIELDS'!BJ8," ",'INPUT FIELDS'!BJ9," ",'INPUT FIELDS'!BJ7) -> JONAS ABELIDO YBOA | DG13: =CONCATENATE('INPUT FIELDS'!BL8," ",'INPUT FIELDS'!BL9," ",'INPUT FIELDS'!BL7) -> RUBIA ABARCAR GONZALES | DS13: =CONCATENATE('INPUT FIELDS'!BN8," ",'INPUT FIELDS'!BN9," ",'INPUT FIELDS'!BN7) -> DOMINGO JR JADLOC ARCALES | EE13: =CONCATENATE('INPUT FIELDS'!BP8," ",'INPUT FIELDS'!BP9," ",'INPUT FIELDS'!BP7) -> REBECCA TILLES GACELOS | ER13: =CONCATENATE('INPUT FIELDS'!BR8," ",'INPUT FIELDS'!BR9," ",'INPUT FIELDS'!BR7) -> NARCISA CAMUIN TONELETE | FD13: =CONCATENATE('INPUT FIELDS'!BT8," ",'INPUT FIELDS'!BT9," ",'INPUT FIELDS'!BT7) -> MA WINONA CON UI GABON | FP13: =CONCATENATE('INPUT FIELDS'!BV8," ",'INPUT FIELDS'!BV9," ",'INPUT FIELDS'!BV7) | GB13: =CONCATENATE('INPUT FIELDS'!BX8," ",'INPUT FIELDS'!BX9," ",'INPUT FIELDS'!BX7) | GN13: =CONCATENATE('INPUT FIELDS'!BZ8," ",'INPUT FIELDS'!BZ9," ",'INPUT FIELDS'!BZ7) | GZ13: =CONCATENATE('INPUT FIELDS'!CB8," ",'INPUT FIELDS'!CB9," ",'INPUT FIELDS'!CB7) | HL13: =CONCATENATE('INPUT FIELDS'!CD8," ",'INPUT FIELDS'!CD9," ",'INPUT FIELDS'!CD7) | HX13: =CONCATENATE('INPUT FIELDS'!CF8," ",'INPUT FIELDS'!CF9," ",'INPUT FIELDS'!CF7)
C14: ='INPUT FIELDS'!D11 -> 202 CURRY AVENUE CATBALOGAN CITY SAMAR | O14: ='INPUT FIELDS'!AV11 -> PUROK 1 BRGY CANLAPWAS CATBALOGAN CITY SAMAR | AA14: ='INPUT FIELDS'!AX11 -> 352 RIZAL AVENUE BRGY 12 CATBALOGAN CITY SAMAR | AM14: ='INPUT FIELDS'!AZ11 -> PATONG STREET BRGY GUINSORONGAN CATBALOGAN CITY | AY14: ='INPUT FIELDS'!BB11 -> P2 BRGY JIA AN JIABONG SAMAR | BK14: ='INPUT FIELDS'!BD11 -> BRGY RAWIS HINABANGAN SAMAR | BW14: ='INPUT FIELDS'!BF11 -> BRGY SAN JOSE ALMAGRO WESTERN SAMAR | CI14: ='INPUT FIELDS'!BH11 -> BRGY PANJOBJOBAN ALMAGRO SAMAR | CU14: ='INPUT FIELDS'!BJ11 -> 5TH ST COR BANOYO ST BRGY 10 CATBALOGAN CITY SAMAR | DG14: ='INPUT FIELDS'!BL11 -> NO 20 B 2 LOT 8 BLISS CANLAPWAS CATBALOGAN CITY | DS14: ='INPUT FIELDS'!BN11 -> 491 PUROK 3 BRGY MERCEDES CATBALOGAN CITY | EE14: ='INPUT FIELDS'!BP11 -> 117 P 2 BRGY MAULONG CATBALOGAN CITY SAMAR | ER14: ='INPUT FIELDS'!BR11 -> 270 BRGY MAULONG CATBALOGAN CITY SAMAR | FD14: ='INPUT FIELDS'!BT11 -> 451 GABON BLVD BRGY 3 PARANAS WRIGHT SAMAR | FP14: ='INPUT FIELDS'!BV11 -> 0 | GB14: ='INPUT FIELDS'!BX11 -> 0 | GN14: ='INPUT FIELDS'!BZ11 -> 0 | GZ14: ='INPUT FIELDS'!CB11 -> 0 | HL14: ='INPUT FIELDS'!CD11 -> 0 | HX14: ='INPUT FIELDS'!CF11 -> 0
C15: =CONCATENATE("C/O : LGU ", 'COMPUTATION SHEET'!F5) -> C/O : LGU PROVINCE OF SAMAR | O15: =C15 -> C/O : LGU PROVINCE OF SAMAR | AA15: =O15 -> C/O : LGU PROVINCE OF SAMAR | AM15: =AA15 -> C/O : LGU PROVINCE OF SAMAR | AY15: =AM15 -> C/O : LGU PROVINCE OF SAMAR | BK15: =AY15 -> C/O : LGU PROVINCE OF SAMAR | BW15: =BK15 -> C/O : LGU PROVINCE OF SAMAR | CI15: =BW15 -> C/O : LGU PROVINCE OF SAMAR | CU15: =CI15 -> C/O : LGU PROVINCE OF SAMAR | DG15: =CU15 -> C/O : LGU PROVINCE OF SAMAR | DS15: =DG15 -> C/O : LGU PROVINCE OF SAMAR | EE15: =DS15 -> C/O : LGU PROVINCE OF SAMAR | ER15: =EE15 -> C/O : LGU PROVINCE OF SAMAR | FD15: =ER15 -> C/O : LGU PROVINCE OF SAMAR | FP15: =FD15 -> C/O : LGU PROVINCE OF SAMAR | GB15: =FP15 -> C/O : LGU PROVINCE OF SAMAR | GN15: =GB15 -> C/O : LGU PROVINCE OF SAMAR | GZ15: =GN15 -> C/O : LGU PROVINCE OF SAMAR | HL15: =GZ15 -> C/O : LGU PROVINCE OF SAMAR | HX15: =HL15 -> C/O : LGU PROVINCE OF SAMAR
C18: Dear Mr./Ms. | D18: =CONCATENATE(PROPER('INPUT FIELDS'!D7),":") -> Rabadam: | O18: Dear Mr./Ms. | P18: =CONCATENATE(PROPER('INPUT FIELDS'!AV7),":") -> Lejas: | AA18: Dear Mr./Ms. | AB18: =CONCATENATE(PROPER('INPUT FIELDS'!AX7),":") -> Nunez: | AM18: Dear Mr./Ms. | AN18: =CONCATENATE(PROPER('INPUT FIELDS'!AZ7),":") -> Lima: | AY18: Dear Mr./Ms. | AZ18: =CONCATENATE(PROPER('INPUT FIELDS'!BB7),":") -> Alegria: | BK18: Dear Mr./Ms. | BL18: =CONCATENATE(PROPER('INPUT FIELDS'!BD7),":") -> Gacelos: | BW18: Dear Mr./Ms. | BX18: =CONCATENATE(PROPER('INPUT FIELDS'!BF7),":") -> Gonzales: | CI18: Dear Mr./Ms. | CJ18: =CONCATENATE(PROPER('INPUT FIELDS'!BH7),":") -> Mayor: | CU18: Dear Mr./Ms. | CV18: =CONCATENATE(PROPER('INPUT FIELDS'!BJ7),":") -> Yboa: | DG18: Dear Mr./Ms. | DH18: =CONCATENATE(PROPER('INPUT FIELDS'!BL7),":") -> Gonzales: | DS18: Dear Mr./Ms. | DT18: =CONCATENATE(PROPER('INPUT FIELDS'!BN7),":") -> Arcales: | EE18: Dear Mr./Ms. | EF18: =CONCATENATE(PROPER('INPUT FIELDS'!BP7),":") -> Gacelos: | ER18: Dear Mr./Ms. | ES18: =CONCATENATE(PROPER('INPUT FIELDS'!BR7),":") -> Tonelete: | FD18: Dear Mr./Ms. | FE18: =CONCATENATE(PROPER('INPUT FIELDS'!BT7),":") -> Gabon: | FP18: Dear Mr./Ms. | FQ18: =CONCATENATE(PROPER('INPUT FIELDS'!BV7),":") -> : | GB18: Dear Mr./Ms. | GC18: =CONCATENATE(PROPER('INPUT FIELDS'!BX7),":") -> : | GN18: Dear Mr./Ms. | GO18: =CONCATENATE(PROPER('INPUT FIELDS'!BZ7),":") -> : | GZ18: Dear Mr./Ms. | HA18: =CONCATENATE(PROPER('INPUT FIELDS'!CB7),":") -> : | HL18: Dear Mr./Ms. | HM18: =CONCATENATE(PROPER('INPUT FIELDS'!CD7),":") -> : | HX18: Dear Mr./Ms. | HY18: =CONCATENATE(PROPER('INPUT FIELDS'!CF7),":") -> :
C21: We are glad to inform that your salary loan application has been approved today | O21: We are glad to inform that your salary loan application has been approved today | AA21: We are glad to inform that your salary loan application has been approved today | AM21: We are glad to inform that your salary loan application has been approved today | AY21: We are glad to inform that your salary loan application has been approved today | BK21: We are glad to inform that your salary loan application has been approved today | BW21: We are glad to inform that your salary loan application has been approved today | CI21: We are glad to inform that your salary loan application has been approved today | CU21: We are glad to inform that your salary loan application has been approved today | DG21: We are glad to inform that your salary loan application has been approved today | DS21: We are glad to inform that your salary loan application has been approved today | EE21: We are glad to inform that your salary loan application has been approved today | ER21: We are glad to inform that your salary loan application has been approved today | FD21: We are glad to inform that your salary loan application has been approved today | FP21: We are glad to inform that your salary loan application has been approved today | GB21: We are glad to inform that your salary loan application has been approved today | GN21: We are glad to inform that your salary loan application has been approved today | GZ21: We are glad to inform that your salary loan application has been approved today | HL21: We are glad to inform that your salary loan application has been approved today | HX21: We are glad to inform that your salary loan application has been approved today
C22: with the following terms and conditions, to wit; | O22: with the following terms and conditions, to wit; | AA22: with the following terms and conditions, to wit; | AM22: with the following terms and conditions, to wit; | AY22: with the following terms and conditions, to wit; | BK22: with the following terms and conditions, to wit; | BW22: with the following terms and conditions, to wit; | CI22: with the following terms and conditions, to wit; | CU22: with the following terms and conditions, to wit; | DG22: with the following terms and conditions, to wit; | DS22: with the following terms and conditions, to wit; | EE22: with the following terms and conditions, to wit; | ER22: with the following terms and conditions, to wit; | FD22: with the following terms and conditions, to wit; | FP22: with the following terms and conditions, to wit; | GB22: with the following terms and conditions, to wit; | GN22: with the following terms and conditions, to wit; | GZ22: with the following terms and conditions, to wit; | HL22: with the following terms and conditions, to wit; | HX22: with the following terms and conditions, to wit;
C24: Amount | E24: : | F24: ='COMPUTATION SHEET'!AA24 -> 71700 | O24: Amount | Q24: : | R24: ='COMPUTATION SHEET'!AA26 -> 113000 | AA24: Amount | AC24: : | AD24: ='COMPUTATION SHEET'!AA28 -> 196400 | AM24: Amount | AO24: : | AP24: ='COMPUTATION SHEET'!AA30 -> 139500 | AY24: Amount | BA24: : | BB24: ='COMPUTATION SHEET'!AA32 -> 137350 | BK24: Amount | BM24: : | BN24: ='COMPUTATION SHEET'!AA34 -> 150300 | BW24: Amount | BY24: : | BZ24: ='COMPUTATION SHEET'!AA36 -> 433500 | CI24: Amount | CK24: : | CL24: ='COMPUTATION SHEET'!AA38 -> 186500 | CU24: Amount | CW24: : | CX24: ='COMPUTATION SHEET'!AA40 -> 165400 | DG24: Amount | DI24: : | DJ24: ='COMPUTATION SHEET'!AA42 -> 148900 | DS24: Amount | DU24: : | DV24: ='COMPUTATION SHEET'!AA44 -> 188700 | EE24: Amount | EG24: : | EH24: ='COMPUTATION SHEET'!AA46 -> 238900 | ER24: Amount | ET24: : | EU24: ='COMPUTATION SHEET'!AA48 -> 321000 | FD24: Amount | FF24: : | FG24: ='COMPUTATION SHEET'!AA50 -> 266300 | FP24: Amount | FR24: : | FS24: ='COMPUTATION SHEET'!AA52 -> 0 | GB24: Amount | GD24: : | GE24: ='COMPUTATION SHEET'!AA54 -> 0 | GN24: Amount | GP24: : | GQ24: ='COMPUTATION SHEET'!AA56 -> 0 | GZ24: Amount | HB24: : | HC24: ='COMPUTATION SHEET'!AA58 -> 0 | HL24: Amount | HN24: : | HO24: ='COMPUTATION SHEET'!AA60 -> 0 | HX24: Amount | HZ24: : | IA24: ='COMPUTATION SHEET'!AA62 -> 0
C25: Tenor | E25: : | F25: ='COMPUTATION SHEET'!AC24 -> 12 | G25: Months | O25: Tenor | Q25: : | R25: ='COMPUTATION SHEET'!AC26 -> 48 | S25: Months | AA25: Tenor | AC25: : | AD25: ='COMPUTATION SHEET'!AC28 -> 48 | AE25: Months | AM25: Tenor | AO25: : | AP25: ='COMPUTATION SHEET'!AC30 -> 48 | AQ25: Months | AY25: Tenor | BA25: : | BB25: ='COMPUTATION SHEET'!AC32 -> 48 | BC25: Months | BK25: Tenor | BM25: : | BN25: ='COMPUTATION SHEET'!AC34 -> 48 | BO25: Months | BW25: Tenor | BY25: : | BZ25: ='COMPUTATION SHEET'!AC36 -> 48 | CA25: Months | CI25: Tenor | CK25: : | CL25: ='COMPUTATION SHEET'!AC38 -> 48 | CM25: Months | CU25: Tenor | CW25: : | CX25: ='COMPUTATION SHEET'!AC40 -> 48 | CY25: Months | DG25: Tenor | DI25: : | DJ25: ='COMPUTATION SHEET'!AC42 -> 48 | DK25: Months | DS25: Tenor | DU25: : | DV25: ='COMPUTATION SHEET'!AC44 -> 48 | DW25: Months | EE25: Tenor | EG25: : | EH25: ='COMPUTATION SHEET'!AC46 -> 48 | EI25: Months | ER25: Tenor | ET25: : | EU25: ='COMPUTATION SHEET'!AC48 -> 48 | EV25: Months | FD25: Tenor | FF25: : | FG25: ='COMPUTATION SHEET'!AC50 -> 48 | FH25: Months | FP25: Tenor | FR25: : | FS25: ='COMPUTATION SHEET'!AC52 -> 0 | FT25: Months | GB25: Tenor | GD25: : | GE25: ='COMPUTATION SHEET'!AC54 -> 0 | GF25: Months | GN25: Tenor | GP25: : | GQ25: ='COMPUTATION SHEET'!AC56 -> 0 | GR25: Months | GZ25: Tenor | HB25: : | HC25: ='COMPUTATION SHEET'!AC58 -> 0 | HD25: Months | HL25: Tenor | HN25: : | HO25: ='COMPUTATION SHEET'!AC60 -> 0 | HP25: Months | HX25: Tenor | HZ25: : | IA25: ='COMPUTATION SHEET'!AC62 -> 0 | IB25: Months
C26: Interest Rate | E26: : | F26: ='COMPUTATION SHEET'!AB24 -> 0.12651 | G26: Per Annum | O26: Interest Rate | Q26: : | R26: ='COMPUTATION SHEET'!AB26 -> 0.1581 | S26: Per Annum | AA26: Interest Rate | AC26: : | AD26: ='COMPUTATION SHEET'!AB28 -> 0.1581 | AE26: Per Annum | AM26: Interest Rate | AO26: : | AP26: ='COMPUTATION SHEET'!AB30 -> 0.1581 | AQ26: Per Annum | AY26: Interest Rate | BA26: : | BB26: ='COMPUTATION SHEET'!AB32 -> 0.1581 | BC26: Per Annum | BK26: Interest Rate | BM26: : | BN26: ='COMPUTATION SHEET'!AB34 -> 0.1581 | BO26: Per Annum | BW26: Interest Rate | BY26: : | BZ26: ='COMPUTATION SHEET'!AB36 -> 0.1581 | CA26: Per Annum | CI26: Interest Rate | CK26: : | CL26: ='COMPUTATION SHEET'!AB38 -> 0.1581 | CM26: Per Annum | CU26: Interest Rate | CW26: : | CX26: ='COMPUTATION SHEET'!AB40 -> 0.1581 | CY26: Per Annum | DG26: Interest Rate | DI26: : | DJ26: ='COMPUTATION SHEET'!AB42 -> 0.1581 | DK26: Per Annum | DS26: Interest Rate | DU26: : | DV26: ='COMPUTATION SHEET'!AB44 -> 0.1581 | DW26: Per Annum | EE26: Interest Rate | EG26: : | EH26: ='COMPUTATION SHEET'!AB46 -> 0.1581 | EI26: Per Annum | ER26: Interest Rate | ET26: : | EU26: ='COMPUTATION SHEET'!AB48 -> 0.1581 | EV26: Per Annum | FD26: Interest Rate | FF26: : | FG26: ='COMPUTATION SHEET'!AB50 -> 0.1581 | FH26: Per Annum | FP26: Interest Rate | FR26: : | FS26: ='COMPUTATION SHEET'!AB52 | FT26: Per Annum | GB26: Interest Rate | GD26: : | GE26: ='COMPUTATION SHEET'!AB54 | GF26: Per Annum | GN26: Interest Rate | GP26: : | GQ26: ='COMPUTATION SHEET'!AB56 | GR26: Per Annum | GZ26: Interest Rate | HB26: : | HC26: ='COMPUTATION SHEET'!AB58 | HD26: Per Annum | HL26: Interest Rate | HN26: : | HO26: ='COMPUTATION SHEET'!AB60 | HP26: Per Annum | HX26: Interest Rate | HZ26: : | IA26: ='COMPUTATION SHEET'!AB62 | IB26: Per Annum
C27: Availability | E27: : | F27: 30 | G27: Days | O27: Availability | Q27: : | R27: 30 | S27: Days | AA27: Availability | AC27: : | AD27: 30 | AE27: Days | AM27: Availability | AO27: : | AP27: 30 | AQ27: Days | AY27: Availability | BA27: : | BB27: 30 | BC27: Days | BK27: Availability | BM27: : | BN27: 30 | BO27: Days | BW27: Availability | BY27: : | BZ27: 30 | CA27: Days | CI27: Availability | CK27: : | CL27: 30 | CM27: Days | CU27: Availability | CW27: : | CX27: 30 | CY27: Days | DG27: Availability | DI27: : | DJ27: 30 | DK27: Days | DS27: Availability | DU27: : | DV27: 30 | DW27: Days | EE27: Availability | EG27: : | EH27: 30 | EI27: Days | ER27: Availability | ET27: : | EU27: 30 | EV27: Days | FD27: Availability | FF27: : | FG27: 30 | FH27: Days | FP27: Availability | FR27: : | FS27: 30 | FT27: Days | GB27: Availability | GD27: : | GE27: 30 | GF27: Days | GN27: Availability | GP27: : | GQ27: 30 | GR27: Days | GZ27: Availability | HB27: : | HC27: 30 | HD27: Days | HL27: Availability | HN27: : | HO27: 30 | HP27: Days | HX27: Availability | HZ27: : | IA27: 30 | IB27: Days
C28: Others | E28: : | F28: 1. Payment of processing fee of 1% of loan amount with max. of P1,500.00 deducted from loan proceeds | O28: Others | Q28: : | R28: 1. Payment of processing fee of 1% of loan amount with max. of P1,500.00 deducted from loan proceeds | AA28: Others | AC28: : | AD28: 1. Payment of processing fee of 1% of loan amount with max. of P1,500.00 deducted from loan proceeds | AM28: Others | AO28: : | AP28: 1. Payment of processing fee of 1% of loan amount with max. of P1,500.00 deducted from loan proceeds | AY28: Others | BA28: : | BB28: 1. Payment of processing fee of 1% of loan amount with max. of P1,500.00 deducted from loan proceeds | BK28: Others | BM28: : | BN28: 1. Payment of processing fee of 1% of loan amount with max. of P1,500.00 deducted from loan proceeds | BW28: Others | BY28: : | BZ28: 1. Payment of processing fee of 1% of loan amount with max. of P1,500.00 deducted from loan proceeds | CI28: Others | CK28: : | CL28: 1. Payment of processing fee of 1% of loan amount with max. of P1,500.00 deducted from loan proceeds | CU28: Others | CW28: : | CX28: 1. Payment of processing fee of 1% of loan amount with max. of P1,500.00 deducted from loan proceeds | DG28: Others | DI28: : | DJ28: 1. Payment of processing fee of 1% of loan amount with max. of P1,500.00 deducted from loan proceeds | DS28: Others | DU28: : | DV28: 1. Payment of processing fee of 1% of loan amount with max. of P1,500.00 deducted from loan proceeds | EE28: Others | EG28: : | EH28: 1. Payment of processing fee of 1% of loan amount with max. of P1,500.00 deducted from loan proceeds | ER28: Others | ET28: : | EU28: 1. Payment of processing fee of 1% of loan amount with max. of P1,500.00 deducted from loan proceeds | FD28: Others | FF28: : | FG28: 1. Payment of processing fee of 1% of loan amount with max. of P1,500.00 deducted from loan proceeds | FP28: Others | FR28: : | FS28: 1. Payment of processing fee of 1% of loan amount with max. of P1,500.00 deducted from loan proceeds | GB28: Others | GD28: : | GE28: 1. Payment of processing fee of 1% of loan amount with max. of P1,500.00 deducted from loan proceeds | GN28: Others | GP28: : | GQ28: 1. Payment of processing fee of 1% of loan amount with max. of P1,500.00 deducted from loan proceeds | GZ28: Others | HB28: : | HC28: 1. Payment of processing fee of 1% of loan amount with max. of P1,500.00 deducted from loan proceeds | HL28: Others | HN28: : | HO28: 1. Payment of processing fee of 1% of loan amount with max. of P1,500.00 deducted from loan proceeds | HX28: Others | HZ28: : | IA28: 1. Payment of processing fee of 1% of loan amount with max. of P1,500.00 deducted from loan proceeds
F29: 2. GRT for all other fees and charges for the account of the borrower | R29: 2. GRT for all other fees and charges for the account of the borrower | AD29: 2. GRT for all other fees and charges for the account of the borrower | AP29: 2. GRT for all other fees and charges for the account of the borrower | BB29: 2. GRT for all other fees and charges for the account of the borrower | BN29: 2. GRT for all other fees and charges for the account of the borrower | BZ29: 2. GRT for all other fees and charges for the account of the borrower | CL29: 2. GRT for all other fees and charges for the account of the borrower | CX29: 2. GRT for all other fees and charges for the account of the borrower | DJ29: 2. GRT for all other fees and charges for the account of the borrower | DV29: 2. GRT for all other fees and charges for the account of the borrower | EH29: 2. GRT for all other fees and charges for the account of the borrower | EU29: 2. GRT for all other fees and charges for the account of the borrower | FG29: 2. GRT for all other fees and charges for the account of the borrower | FS29: 2. GRT for all other fees and charges for the account of the borrower | GE29: 2. GRT for all other fees and charges for the account of the borrower | GQ29: 2. GRT for all other fees and charges for the account of the borrower | HC29: 2. GRT for all other fees and charges for the account of the borrower | HO29: 2. GRT for all other fees and charges for the account of the borrower | IA29: 2. GRT for all other fees and charges for the account of the borrower
C31: Should you need for more clarification, please feel free to visit our branch or call our Relationship Officer, | O31: Should you need for more clarification, please feel free to visit our branch or call our Relationship Officer, | AA31: Should you need for more clarification, please feel free to visit our branch or call our Relationship Officer, | AM31: Should you need for more clarification, please feel free to visit our branch or call our Relationship Officer, | AY31: Should you need for more clarification, please feel free to visit our branch or call our Relationship Officer, | BK31: Should you need for more clarification, please feel free to visit our branch or call our Relationship Officer, | BW31: Should you need for more clarification, please feel free to visit our branch or call our Relationship Officer, | CI31: Should you need for more clarification, please feel free to visit our branch or call our Relationship Officer, | CU31: Should you need for more clarification, please feel free to visit our branch or call our Relationship Officer, | DG31: Should you need for more clarification, please feel free to visit our branch or call our Relationship Officer, | DS31: Should you need for more clarification, please feel free to visit our branch or call our Relationship Officer, | EE31: Should you need for more clarification, please feel free to visit our branch or call our Relationship Officer, | ER31: Should you need for more clarification, please feel free to visit our branch or call our Relationship Officer, | FD31: Should you need for more clarification, please feel free to visit our branch or call our Relationship Officer, | FP31: Should you need for more clarification, please feel free to visit our branch or call our Relationship Officer, | GB31: Should you need for more clarification, please feel free to visit our branch or call our Relationship Officer, | GN31: Should you need for more clarification, please feel free to visit our branch or call our Relationship Officer, | GZ31: Should you need for more clarification, please feel free to visit our branch or call our Relationship Officer, | HL31: Should you need for more clarification, please feel free to visit our branch or call our Relationship Officer, | HX31: Should you need for more clarification, please feel free to visit our branch or call our Relationship Officer,
C32: Ms. Janice B. Solayao at Telephone No. (055) 251-2046. | O32: Ms. Janice B. Solayao at Telephone No. (055) 251-2046. | AA32: Ms. Janice B. Solayao at Telephone No. (055) 251-2046. | AM32: Ms. Janice B. Solayao at Telephone No. (055) 251-2046. | AY32: Ms. Janice B. Solayao at Telephone No. (055) 251-2046. | BK32: Ms. Janice B. Solayao at Telephone No. (055) 251-2046. | BW32: Ms. Janice B. Solayao at Telephone No. (055) 251-2046. | CI32: Ms. Janice B. Solayao at Telephone No. (055) 251-2046. | CU32: Ms. Janice B. Solayao at Telephone No. (055) 251-2046. | DG32: Ms. Janice B. Solayao at Telephone No. (055) 251-2046. | DS32: Ms. Janice B. Solayao at Telephone No. (055) 251-2046. | EE32: Ms. Janice B. Solayao at Telephone No. (055) 251-2046. | ER32: Ms. Janice B. Solayao at Telephone No. (055) 251-2046. | FD32: Ms. Janice B. Solayao at Telephone No. (055) 251-2046. | FP32: Ms. Janice B. Solayao at Telephone No. (055) 251-2046. | GB32: Ms. Janice B. Solayao at Telephone No. (055) 251-2046. | GN32: Ms. Janice B. Solayao at Telephone No. (055) 251-2046. | GZ32: Ms. Janice B. Solayao at Telephone No. (055) 251-2046. | HL32: Ms. Janice B. Solayao at Telephone No. (055) 251-2046. | HX32: Ms. Janice B. Solayao at Telephone No. (055) 251-2046.
C34: Thank you. | O34: Thank you. | AA34: Thank you. | AM34: Thank you. | AY34: Thank you. | BK34: Thank you. | BW34: Thank you. | CI34: Thank you. | CU34: Thank you. | DG34: Thank you. | DS34: Thank you. | EE34: Thank you. | ER34: Thank you. | FD34: Thank you. | FP34: Thank you. | GB34: Thank you. | GN34: Thank you. | GZ34: Thank you. | HL34: Thank you. | HX34: Thank you.
I37: Very truly yours, | U37: Very truly yours, | AG37: Very truly yours, | AS37: Very truly yours, | BE37: Very truly yours, | BQ37: Very truly yours, | CC37: Very truly yours, | CO37: Very truly yours, | DA37: Very truly yours, | DM37: Very truly yours, | DY37: Very truly yours, | EK37: Very truly yours, | EX37: Very truly yours, | FJ37: Very truly yours, | FV37: Very truly yours, | GH37: Very truly yours, | GT37: Very truly yours, | HF37: Very truly yours, | HR37: Very truly yours, | ID37: Very truly yours,
I41: =Signatories!C11 -> SM HELBERT ANTOINE A. ACHAY | U41: =I41 -> SM HELBERT ANTOINE A. ACHAY | AG41: =U41 -> SM HELBERT ANTOINE A. ACHAY | AS41: =AG41 -> SM HELBERT ANTOINE A. ACHAY | BE41: =AS41 -> SM HELBERT ANTOINE A. ACHAY | BQ41: =BE41 -> SM HELBERT ANTOINE A. ACHAY | CC41: =BQ41 -> SM HELBERT ANTOINE A. ACHAY | CO41: =CC41 -> SM HELBERT ANTOINE A. ACHAY | DA41: =CO41 -> SM HELBERT ANTOINE A. ACHAY | DM41: =DA41 -> SM HELBERT ANTOINE A. ACHAY | DY41: =DM41 -> SM HELBERT ANTOINE A. ACHAY | EK41: =DY41 -> SM HELBERT ANTOINE A. ACHAY | EX41: =EK41 -> SM HELBERT ANTOINE A. ACHAY | FJ41: =EX41 -> SM HELBERT ANTOINE A. ACHAY | FV41: =FJ41 -> SM HELBERT ANTOINE A. ACHAY | GH41: =FV41 -> SM HELBERT ANTOINE A. ACHAY | GT41: =GH41 -> SM HELBERT ANTOINE A. ACHAY | HF41: =GT41 -> SM HELBERT ANTOINE A. ACHAY | HR41: =HF41 -> SM HELBERT ANTOINE A. ACHAY | ID41: =HR41 -> SM HELBERT ANTOINE A. ACHAY
I42: Branch Head | U42: Branch Head | AG42: Branch Head | AS42: Branch Head | BE42: Branch Head | BQ42: Branch Head | CC42: Branch Head | CO42: Branch Head | DA42: Branch Head | DM42: Branch Head | DY42: Branch Head | EK42: Branch Head | EX42: Branch Head | FJ42: Branch Head | FV42: Branch Head | GH42: Branch Head | GT42: Branch Head | HF42: Branch Head | HR42: Branch Head | ID42: Branch Head
F49: Development Bank of the Philippines | R49: Development Bank of the Philippines | AD49: Development Bank of the Philippines | AP49: Development Bank of the Philippines | BB49: Development Bank of the Philippines | BN49: Development Bank of the Philippines | BZ49: Development Bank of the Philippines | CL49: Development Bank of the Philippines | CX49: Development Bank of the Philippines | DJ49: Development Bank of the Philippines | DV49: Development Bank of the Philippines | EH49: Development Bank of the Philippines | EU49: Development Bank of the Philippines | FG49: Development Bank of the Philippines | FS49: Development Bank of the Philippines | GE49: Development Bank of the Philippines | GQ49: Development Bank of the Philippines | HC49: Development Bank of the Philippines | HO49: Development Bank of the Philippines | IA49: Development Bank of the Philippines
C54: PROMISSORY NOTE | O54: PROMISSORY NOTE | AA54: PROMISSORY NOTE | AM54: PROMISSORY NOTE | AY54: PROMISSORY NOTE | BK54: PROMISSORY NOTE | BW54: PROMISSORY NOTE | CI54: PROMISSORY NOTE | CU54: PROMISSORY NOTE | DG54: PROMISSORY NOTE | DS54: PROMISSORY NOTE | EE54: PROMISSORY NOTE | ER54: PROMISSORY NOTE | FD54: PROMISSORY NOTE | FP54: PROMISSORY NOTE | GB54: PROMISSORY NOTE | GN54: PROMISSORY NOTE | GZ54: PROMISSORY NOTE | HL54: PROMISSORY NOTE | HX54: PROMISSORY NOTE
J57: PN No. | V57: PN No. | AH57: PN No. | AT57: PN No. | BF57: PN No. | BR57: PN No. | CD57: PN No. | CP57: PN No. | DB57: PN No. | DN57: PN No. | DZ57: PN No. | EL57: PN No. | EY57: PN No. | FK57: PN No. | FW57: PN No. | GI57: PN No. | GU57: PN No. | HG57: PN No. | HS57: PN No. | IE57: PN No.
J58: (Date) | V58: (Date) | AH58: (Date) | AT58: (Date) | BF58: (Date) | BR58: (Date) | CD58: (Date) | CP58: (Date) | DB58: (Date) | DN58: (Date) | DZ58: (Date) | EL58: (Date) | EY58: (Date) | FK58: (Date) | FW58: (Date) | GI58: (Date) | GU58: (Date) | HG58: (Date) | HS58: (Date) | IE58: (Date)
C59: =F24 -> 71700 | O59: =R24 -> 113000 | AA59: =AD24 -> 196400 | AM59: =AP24 -> 139500 | AY59: =BB24 -> 137350 | BK59: =BN24 -> 150300 | BW59: =BZ24 -> 433500 | CI59: =CL24 -> 186500 | CU59: =CX24 -> 165400 | DG59: =DJ24 -> 148900 | DS59: =DV24 -> 188700 | EE59: =EH24 -> 238900 | ER59: =EU24 -> 321000 | FD59: =FG24 -> 266300 | FP59: =FS24 -> 0 | GB59: =GE24 -> 0 | GN59: =GQ24 -> 0 | GZ59: =HC24 -> 0 | HL59: =HO24 -> 0 | HX59: =IA24 -> 0
C61: I/We promise to pay to the order of the DBP the sum of | O61: I/We promise to pay to the order of the DBP the sum of | AA61: I/We promise to pay to the order of the DBP the sum of | AM61: I/We promise to pay to the order of the DBP the sum of | AY61: I/We promise to pay to the order of the DBP the sum of | BK61: I/We promise to pay to the order of the DBP the sum of | BW61: I/We promise to pay to the order of the DBP the sum of | CI61: I/We promise to pay to the order of the DBP the sum of | CU61: I/We promise to pay to the order of the DBP the sum of | DG61: I/We promise to pay to the order of the DBP the sum of | DS61: I/We promise to pay to the order of the DBP the sum of | EE61: I/We promise to pay to the order of the DBP the sum of | ER61: I/We promise to pay to the order of the DBP the sum of | FD61: I/We promise to pay to the order of the DBP the sum of | FP61: I/We promise to pay to the order of the DBP the sum of | GB61: I/We promise to pay to the order of the DBP the sum of | GN61: I/We promise to pay to the order of the DBP the sum of | GZ61: I/We promise to pay to the order of the DBP the sum of | HL61: I/We promise to pay to the order of the DBP the sum of | HX61: I/We promise to pay to the order of the DBP the sum of
C62: =CONCATENATE("Pesos: ",words(C59)) -> #NAME? | J62: ( | K62: =C59 -> 71700 | N62: ) | O62: =CONCATENATE("Pesos: ",words(O59)) -> #NAME? | V62: ( | W62: =O59 -> 113000 | Z62: ) | AA62: =CONCATENATE("Pesos: ",words(AA59)) -> #NAME? | AH62: ( | AI62: =AA59 -> 196400 | AL62: ) | AM62: =CONCATENATE("Pesos: ",words(AM59)) -> #NAME? | AT62: ( | AU62: =AM59 -> 139500 | AX62: ) | AY62: =CONCATENATE("Pesos: ",words(AY59)) -> #NAME? | BF62: ( | BG62: =AY59 -> 137350 | BJ62: ) | BK62: =CONCATENATE("Pesos: ",words(BK59)) -> #NAME? | BR62: ( | BS62: =BK59 -> 150300 | BV62: ) | BW62: =CONCATENATE("Pesos: ",words(BW59)) -> #NAME? | CD62: ( | CE62: =BW59 -> 433500 | CH62: ) | CI62: =CONCATENATE("Pesos: ",words(CI59)) -> #NAME? | CP62: ( | CQ62: =CI59 -> 186500 | CT62: ) | CU62: =CONCATENATE("Pesos: ",words(CU59)) -> #NAME? | DB62: ( | DC62: =CU59 -> 165400 | DF62: ) | DG62: =CONCATENATE("Pesos: ",words(DG59)) -> #NAME? | DN62: ( | DO62: =DG59 -> 148900 | DR62: ) | DS62: =CONCATENATE("Pesos: ",words(DS59)) -> #NAME? | DZ62: ( | EA62: =DS59 -> 188700 | ED62: ) | EE62: =CONCATENATE("Pesos: ",words(EE59)) -> #NAME? | EL62: ( | EM62: =EE59 -> 238900 | EP62: ) | ER62: =CONCATENATE("Pesos: ",words(ER59)) -> #NAME? | EY62: ( | EZ62: =ER59 -> 321000 | FC62: ) | FD62: =CONCATENATE("Pesos: ",words(FD59)) -> #NAME? | FK62: ( | FL62: =FD59 -> 266300 | FO62: ) | FP62: =CONCATENATE("Pesos: ",words(FP59)) -> #NAME? | FW62: ( | FX62: =FP59 -> 0 | GA62: ) | GB62: =CONCATENATE("Pesos: ",words(GB59)) -> #NAME? | GI62: ( | GJ62: =GB59 -> 0 | GM62: ) | GN62: =CONCATENATE("Pesos: ",words(GN59)) -> #NAME? | GU62: ( | GV62: =GN59 -> 0 | GY62: ) | GZ62: =CONCATENATE("Pesos: ",words(GZ59)) -> #NAME? | HG62: ( | HH62: =GZ59 -> 0 | HK62: ) | HL62: =CONCATENATE("Pesos: ",words(HL59)) -> #NAME? | HS62: ( | HT62: =HL59 -> 0 | HW62: ) | HX62: =CONCATENATE("Pesos: ",words(HX59)) -> #NAME? | IE62: ( | IF62: =HX59 -> 0 | II62: )
C63: representing the Salary Loan granted by the bank on | H63: =I9 -> 46084.283 | I63: in monthly amortization/ installment in accordance with | O63: representing the Salary Loan granted by the bank on | T63: =U9 -> 46084.283 | U63: in monthly amortization/ installment in accordance with | AA63: representing the Salary Loan granted by the bank on | AF63: =AG9 -> 46084.283 | AG63: in monthly amortization/ installment in accordance with | AM63: representing the Salary Loan granted by the bank on | AR63: =AS9 -> 46084.283 | AS63: in monthly amortization/ installment in accordance with | AY63: representing the Salary Loan granted by the bank on | BD63: =BE9 -> 46084.283 | BE63: in monthly amortization/ installment in accordance with | BK63: representing the Salary Loan granted by the bank on | BP63: =BQ9 -> 46084.283 | BQ63: in monthly amortization/ installment in accordance with | BW63: representing the Salary Loan granted by the bank on | CB63: =CC9 -> 46084.283 | CC63: in monthly amortization/ installment in accordance with | CI63: representing the Salary Loan granted by the bank on | CN63: =CO9 -> 46084.283 | CO63: in monthly amortization/ installment in accordance with | CU63: representing the Salary Loan granted by the bank on | CZ63: =DA9 -> 46084.283 | DA63: in monthly amortization/ installment in accordance with | DG63: representing the Salary Loan granted by the bank on | DL63: =DM9 -> 46084.283 | DM63: in monthly amortization/ installment in accordance with | DS63: representing the Salary Loan granted by the bank on | DX63: =DY9 -> 46084.283 | DY63: in monthly amortization/ installment in accordance with | EE63: representing the Salary Loan granted by the bank on | EJ63: =EK9 -> 46084.283 | EK63: in monthly amortization/ installment in accordance with | ER63: representing the Salary Loan granted by the bank on | EW63: =EX9 -> 46084.283 | EX63: in monthly amortization/ installment in accordance with | FD63: representing the Salary Loan granted by the bank on | FI63: =FJ9 -> 46084.283 | FJ63: in monthly amortization/ installment in accordance with | FP63: representing the Salary Loan granted by the bank on | FU63: =FV9 -> 46084.283 | FV63: in monthly amortization/ installment in accordance with | GB63: representing the Salary Loan granted by the bank on | GG63: =GH9 -> 46084.283 | GH63: in monthly amortization/ installment in accordance with | GN63: representing the Salary Loan granted by the bank on | GS63: =GT9 -> 46084.283 | GT63: in monthly amortization/ installment in accordance with | GZ63: representing the Salary Loan granted by the bank on | HE63: =HF9 -> 46084.283 | HF63: in monthly amortization/ installment in accordance with | HL63: representing the Salary Loan granted by the bank on | HQ63: =HR9 -> 46084.283 | HR63: in monthly amortization/ installment in accordance with | HX63: representing the Salary Loan granted by the bank on | IC63: =ID9 -> 46084.283 | ID63: in monthly amortization/ installment in accordance with
C64: the schedule of amortization/installment attached hereto as Annex "A". | O64: the schedule of amortization/installment attached hereto as Annex "A". | AA64: the schedule of amortization/installment attached hereto as Annex "A". | AM64: the schedule of amortization/installment attached hereto as Annex "A". | AY64: the schedule of amortization/installment attached hereto as Annex "A". | BK64: the schedule of amortization/installment attached hereto as Annex "A". | BW64: the schedule of amortization/installment attached hereto as Annex "A". | CI64: the schedule of amortization/installment attached hereto as Annex "A". | CU64: the schedule of amortization/installment attached hereto as Annex "A". | DG64: the schedule of amortization/installment attached hereto as Annex "A". | DS64: the schedule of amortization/installment attached hereto as Annex "A". | EE64: the schedule of amortization/installment attached hereto as Annex "A". | ER64: the schedule of amortization/installment attached hereto as Annex "A". | FD64: the schedule of amortization/installment attached hereto as Annex "A". | FP64: the schedule of amortization/installment attached hereto as Annex "A". | GB64: the schedule of amortization/installment attached hereto as Annex "A". | GN64: the schedule of amortization/installment attached hereto as Annex "A". | GZ64: the schedule of amortization/installment attached hereto as Annex "A". | HL64: the schedule of amortization/installment attached hereto as Annex "A". | HX64: the schedule of amortization/installment attached hereto as Annex "A".
C69: =C13 -> MARIA EMY TAN RABADAM | O69: =O13 -> ALLAN GULFERIC LEJAS | AA69: =AA13 -> JOSE JR ADESAS NUNEZ | AM69: =AM13 -> NESTOR PELENO LIMA | AY69: =AY13 -> MARCIANO JR HERNANDEZ ALEGRIA | BK69: =BK13 -> MANOLITO ABARRACOSO GACELOS | BW69: =BW13 -> LEONILA HILONGO GONZALES | CI69: =CI13 -> CHONA BRANZUELA MAYOR | CU69: =CU13 -> JONAS ABELIDO YBOA | DG69: =DG13 -> RUBIA ABARCAR GONZALES | DS69: =DS13 -> DOMINGO JR JADLOC ARCALES | EE69: =EE13 -> REBECCA TILLES GACELOS | ER69: =ER13 -> NARCISA CAMUIN TONELETE | FD69: =FD13 -> MA WINONA CON UI GABON | FP69: =FP13 | GB69: =GB13 | GN69: =GN13 | GZ69: =GZ13 | HL69: =HL13 | HX69: =HX13
C70: Signature over Printed Name of Applicant | I70: Signature over Printed Name of Co-maker | O70: Signature over Printed Name of Applicant | U70: Signature over Printed Name of Co-maker | AA70: Signature over Printed Name of Applicant | AG70: Signature over Printed Name of Co-maker | AM70: Signature over Printed Name of Applicant | AS70: Signature over Printed Name of Co-maker | AY70: Signature over Printed Name of Applicant | BE70: Signature over Printed Name of Co-maker | BK70: Signature over Printed Name of Applicant | BQ70: Signature over Printed Name of Co-maker | BW70: Signature over Printed Name of Applicant | CC70: Signature over Printed Name of Co-maker | CI70: Signature over Printed Name of Applicant | CO70: Signature over Printed Name of Co-maker | CU70: Signature over Printed Name of Applicant | DA70: Signature over Printed Name of Co-maker | DG70: Signature over Printed Name of Applicant | DM70: Signature over Printed Name of Co-maker | DS70: Signature over Printed Name of Applicant | DY70: Signature over Printed Name of Co-maker | EE70: Signature over Printed Name of Applicant | EK70: Signature over Printed Name of Co-maker | ER70: Signature over Printed Name of Applicant | EX70: Signature over Printed Name of Co-maker | FD70: Signature over Printed Name of Applicant | FJ70: Signature over Printed Name of Co-maker | FP70: Signature over Printed Name of Applicant | FV70: Signature over Printed Name of Co-maker | GB70: Signature over Printed Name of Applicant | GH70: Signature over Printed Name of Co-maker | GN70: Signature over Printed Name of Applicant | GT70: Signature over Printed Name of Co-maker | GZ70: Signature over Printed Name of Applicant | HF70: Signature over Printed Name of Co-maker | HL70: Signature over Printed Name of Applicant | HR70: Signature over Printed Name of Co-maker | HX70: Signature over Printed Name of Applicant | ID70: Signature over Printed Name of Co-maker
F76: Signed in the presence of: | R76: Signed in the presence of: | AD76: Signed in the presence of: | AP76: Signed in the presence of: | BB76: Signed in the presence of: | BN76: Signed in the presence of: | BZ76: Signed in the presence of: | CL76: Signed in the presence of: | CX76: Signed in the presence of: | DJ76: Signed in the presence of: | DV76: Signed in the presence of: | EH76: Signed in the presence of: | EU76: Signed in the presence of: | FG76: Signed in the presence of: | FS76: Signed in the presence of: | GE76: Signed in the presence of: | GQ76: Signed in the presence of: | HC76: Signed in the presence of: | HO76: Signed in the presence of: | IA76: Signed in the presence of:
F81: =Signatories!C9 -> JANICE B. SOLAYAO | R81: =F81 -> JANICE B. SOLAYAO | AD81: =R81 -> JANICE B. SOLAYAO | AP81: =AD81 -> JANICE B. SOLAYAO | BB81: =AP81 -> JANICE B. SOLAYAO | BN81: =BB81 -> JANICE B. SOLAYAO | BZ81: =BN81 -> JANICE B. SOLAYAO | CL81: =BZ81 -> JANICE B. SOLAYAO | CX81: =CL81 -> JANICE B. SOLAYAO | DJ81: =CX81 -> JANICE B. SOLAYAO | DV81: =DJ81 -> JANICE B. SOLAYAO | EH81: =DV81 -> JANICE B. SOLAYAO | EU81: =EH81 -> JANICE B. SOLAYAO | FG81: =EU81 -> JANICE B. SOLAYAO | FS81: =FG81 -> JANICE B. SOLAYAO | GE81: =FS81 -> JANICE B. SOLAYAO | GQ81: =GE81 -> JANICE B. SOLAYAO | HC81: =GQ81 -> JANICE B. SOLAYAO | HO81: =HC81 -> JANICE B. SOLAYAO | IA81: =HO81 -> JANICE B. SOLAYAO
F82: Signed over Printed Name of the SLF Account Officer | R82: Signed over Printed Name of the SLF Account Officer | AD82: Signed over Printed Name of the SLF Account Officer | AP82: Signed over Printed Name of the SLF Account Officer | BB82: Signed over Printed Name of the SLF Account Officer | BN82: Signed over Printed Name of the SLF Account Officer | BZ82: Signed over Printed Name of the SLF Account Officer | CL82: Signed over Printed Name of the SLF Account Officer | CX82: Signed over Printed Name of the SLF Account Officer | DJ82: Signed over Printed Name of the SLF Account Officer | DV82: Signed over Printed Name of the SLF Account Officer | EH82: Signed over Printed Name of the SLF Account Officer | EU82: Signed over Printed Name of the SLF Account Officer | FG82: Signed over Printed Name of the SLF Account Officer | FS82: Signed over Printed Name of the SLF Account Officer | GE82: Signed over Printed Name of the SLF Account Officer | GQ82: Signed over Printed Name of the SLF Account Officer | HC82: Signed over Printed Name of the SLF Account Officer | HO82: Signed over Printed Name of the SLF Account Officer | IA82: Signed over Printed Name of the SLF Account Officer

Sheet 2
F5: Development Bank of the Philippines
I9: =NOW() -> 46084.283
C13: =CONCATENATE('INPUT FIELDS'!AV8," ",'INPUT FIELDS'!AV9," ",'INPUT FIELDS'!AV7) -> ALLAN GULFERIC LEJAS
C14: LGU Province of Samar
C15: Catbalogan City, Samar
C18: Dear Mr./Ms. | D18: =CONCATENATE(PROPER('INPUT FIELDS'!AV7),":") -> Lejas:
C21: We are glad to inform that your salary loan application has been approved today
C22: with the following terms and conditions, to wit;
C24: Amount | E24: : | F24: ='COMPUTATION SHEET'!AA26 -> 113000 | H24: =words(F24) -> #NAME?
C25: Tenor | E25: : | F25: ='COMPUTATION SHEET'!AC26 -> 48 | G25: Months
C26: Interest Rate | E26: : | F26: ='COMPUTATION SHEET'!AB26 -> 0.1581 | G26: Per Annum
C27: Availability | E27: : | F27: 30 | G27: Days
C28: Others | E28: : | F28: 1. Payment of processing fee of 1% of loan amount with max. of P1,500.00 deducted from loan proceeds
F29: 2. GRT for all other fees and charges for the account of the borrower
C31: Should you need for more clarification, please feel free to visit our branch or call our Relationship Officer,
C32: Ms. Janice B. Solayao at Telephone No. (055) 251-2046.
C34: Thank you.
I37: Very truly yours,
I41: MGR. HELBERT ANTOINE A. ACHAY
I42: Branch Head

Sheet 3
F5: Development Bank of the Philippines
I9: =NOW() -> 46084.283
C13: =CONCATENATE('INPUT FIELDS'!AX8," ",'INPUT FIELDS'!AX9," ",'INPUT FIELDS'!AX7) -> JOSE JR ADESAS NUNEZ
C14: LGU Province of Samar
C15: Catbalogan City, Samar
C18: Dear Mr./Ms. | D18: =CONCATENATE(PROPER('INPUT FIELDS'!AX7),":") -> Nunez:
C21: We are glad to inform that your salary loan application has been approved today
C22: with the following terms and conditions, to wit;
C24: Amount | E24: : | F24: ='COMPUTATION SHEET'!AA28 -> 196400
C25: Tenor | E25: : | F25: ='COMPUTATION SHEET'!AC28 -> 48 | G25: Months
C26: Interest Rate | E26: : | F26: ='COMPUTATION SHEET'!AB28 -> 0.1581 | G26: Per Annum
C27: Availability | E27: : | F27: 30 | G27: Days
C28: Others | E28: : | F28: 1. Payment of processing fee of 1% of loan amount with max. of P1,500.00 deducted from loan proceeds
F29: 2. GRT for all other fees and charges for the account of the borrower
C31: Should you need for more clarification, please feel free to visit our branch or call our Relationship Officer,
C32: Ms. Janice B. Solayao at Telephone No. (055) 251-2046.
C34: Thank you.
I37: Very truly yours,
I41: MGR. HELBERT ANTOINE A. ACHAY
I42: Branch Head

Sheet 4
F5: Development Bank of the Philippines
I9: =NOW() -> 46084.283
C13: =CONCATENATE('INPUT FIELDS'!AZ8," ",'INPUT FIELDS'!AZ9," ",'INPUT FIELDS'!AZ7) -> NESTOR PELENO LIMA
C14: LGU Province of Samar
C15: Catbalogan City, Samar
C18: Dear Mr./Ms. | D18: =CONCATENATE(PROPER('INPUT FIELDS'!AZ7),":") -> Lima:
C21: We are glad to inform that your salary loan application has been approved today
C22: with the following terms and conditions, to wit;
C24: Amount | E24: : | F24: ='COMPUTATION SHEET'!AA30 -> 139500
C25: Tenor | E25: : | F25: ='COMPUTATION SHEET'!AC30 -> 48 | G25: Months
C26: Interest Rate | E26: : | F26: ='COMPUTATION SHEET'!AB30 -> 0.1581 | G26: Per Annum
C27: Availability | E27: : | F27: 30 | G27: Days
C28: Others | E28: : | F28: 1. Payment of processing fee of 1% of loan amount with max. of P1,500.00 deducted from loan proceeds
F29: 2. GRT for all other fees and charges for the account of the borrower
C31: Should you need for more clarification, please feel free to visit our branch or call our Relationship Officer,
C32: Ms. Janice B. Solayao at Telephone No. (055) 251-2046.
C34: Thank you.
I37: Very truly yours,
I41: MGR. HELBERT ANTOINE A. ACHAY
I42: Branch Head

Sheet 5
F5: Development Bank of the Philippines
I9: =NOW() -> 46084.283
C13: =CONCATENATE('INPUT FIELDS'!BB8," ",'INPUT FIELDS'!BB9," ",'INPUT FIELDS'!BB7) -> MARCIANO JR HERNANDEZ ALEGRIA
C14: LGU Province of Samar
C15: Catbalogan City, Samar
C18: Dear Mr./Ms. | D18: =CONCATENATE(PROPER('INPUT FIELDS'!BB7),":") -> Alegria:
C21: We are glad to inform that your salary loan application has been approved today
C22: with the following terms and conditions, to wit;
C24: Amount | E24: : | F24: ='COMPUTATION SHEET'!AA32 -> 137350
C25: Tenor | E25: : | F25: ='COMPUTATION SHEET'!AC32 -> 48 | G25: Months
C26: Interest Rate | E26: : | F26: ='COMPUTATION SHEET'!AB32 -> 0.1581 | G26: Per Annum
C27: Availability | E27: : | F27: 30 | G27: Days
C28: Others | E28: : | F28: 1. Payment of processing fee of 1% of loan amount with max. of P1,500.00 deducted from loan proceeds
F29: 2. GRT for all other fees and charges for the account of the borrower
C31: Should you need for more clarification, please feel free to visit our branch or call our Relationship Officer,
C32: Ms. Janice B. Solayao at Telephone No. (055) 251-2046.
C34: Thank you.
I37: Very truly yours,
I41: MGR. HELBERT ANTOINE A. ACHAY
I42: Branch Head

Sheet 6
F5: Development Bank of the Philippines
I9: =NOW() -> 46084.283
C13: =CONCATENATE('INPUT FIELDS'!BD8," ",'INPUT FIELDS'!BD9," ",'INPUT FIELDS'!BD7) -> MANOLITO ABARRACOSO GACELOS
C14: LGU Province of Samar
C15: Catbalogan City, Samar
C18: Dear Mr./Ms. | D18: =CONCATENATE(PROPER('INPUT FIELDS'!BD7),":") -> Gacelos:
C21: We are glad to inform that your salary loan application has been approved today
C22: with the following terms and conditions, to wit;
C24: Amount | E24: : | F24: ='COMPUTATION SHEET'!AA34 -> 150300
C25: Tenor | E25: : | F25: ='COMPUTATION SHEET'!AC34 -> 48 | G25: Months
C26: Interest Rate | E26: : | F26: ='COMPUTATION SHEET'!AB34 -> 0.1581 | G26: Per Annum
C27: Availability | E27: : | F27: 30 | G27: Days
C28: Others | E28: : | F28: 1. Payment of processing fee of 1% of loan amount with max. of P1,500.00 deducted from loan proceeds
F29: 2. GRT for all other fees and charges for the account of the borrower
C31: Should you need for more clarification, please feel free to visit our branch or call our Relationship Officer,
C32: Ms. Janice B. Solayao at Telephone No. (055) 251-2046.
C34: Thank you.
I37: Very truly yours,
I41: MGR. HELBERT ANTOINE A. ACHAY
I42: Branch Head

Sheet 7
F5: Development Bank of the Philippines
I9: =NOW() -> 46084.283
C13: =CONCATENATE('INPUT FIELDS'!BF8," ",'INPUT FIELDS'!BF9," ",'INPUT FIELDS'!BF7) -> LEONILA HILONGO GONZALES
C14: LGU Province of Samar
C15: Catbalogan City, Samar
C18: Dear Mr./Ms. | D18: =CONCATENATE(PROPER('INPUT FIELDS'!BF7),":") -> Gonzales:
C21: We are glad to inform that your salary loan application has been approved today
C22: with the following terms and conditions, to wit;
C24: Amount | E24: : | F24: ='COMPUTATION SHEET'!AA36 -> 433500
C25: Tenor | E25: : | F25: ='COMPUTATION SHEET'!AC36 -> 48 | G25: Months
C26: Interest Rate | E26: : | F26: ='COMPUTATION SHEET'!AB36 -> 0.1581 | G26: Per Annum
C27: Availability | E27: : | F27: 30 | G27: Days
C28: Others | E28: : | F28: 1. Payment of processing fee of 1% of loan amount with max. of P1,500.00 deducted from loan proceeds
F29: 2. GRT for all other fees and charges for the account of the borrower
C31: Should you need for more clarification, please feel free to visit our branch or call our Relationship Officer,
C32: Ms. Janice B. Solayao at Telephone No. (055) 251-2046.
C34: Thank you.
I37: Very truly yours,
I41: MGR. HELBERT ANTOINE A. ACHAY
I42: Branch Head

Sheet 8
F5: Development Bank of the Philippines
I9: =NOW() -> 46084.283
C13: =CONCATENATE('INPUT FIELDS'!BH8," ",'INPUT FIELDS'!BH9," ",'INPUT FIELDS'!BH7) -> CHONA BRANZUELA MAYOR
C14: LGU Province of Samar
C15: Catbalogan City, Samar
C18: Dear Mr./Ms. | D18: =CONCATENATE(PROPER('INPUT FIELDS'!BH7),":") -> Mayor:
C21: We are glad to inform that your salary loan application has been approved today
C22: with the following terms and conditions, to wit;
C24: Amount | E24: : | F24: ='COMPUTATION SHEET'!AA38 -> 186500
C25: Tenor | E25: : | F25: ='COMPUTATION SHEET'!AC38 -> 48 | G25: Months
C26: Interest Rate | E26: : | F26: ='COMPUTATION SHEET'!AB38 -> 0.1581 | G26: Per Annum
C27: Availability | E27: : | F27: 30 | G27: Days
C28: Others | E28: : | F28: 1. Payment of processing fee of 1% of loan amount with max. of P1,500.00 deducted from loan proceeds
F29: 2. GRT for all other fees and charges for the account of the borrower
C31: Should you need for more clarification, please feel free to visit our branch or call our Relationship Officer,
C32: Ms. Janice B. Solayao at Telephone No. (055) 251-2046.
C34: Thank you.
I37: Very truly yours,
I41: MGR. HELBERT ANTOINE A. ACHAY
I42: Branch Head

Sheet 9
F5: Development Bank of the Philippines
I9: =NOW() -> 46084.283
C13: =CONCATENATE('INPUT FIELDS'!BJ8," ",'INPUT FIELDS'!BJ9," ",'INPUT FIELDS'!BJ7) -> JONAS ABELIDO YBOA
C14: LGU Province of Samar
C15: Catbalogan City, Samar
C18: Dear Mr./Ms. | D18: =CONCATENATE(PROPER('INPUT FIELDS'!BJ7),":") -> Yboa:
C21: We are glad to inform that your salary loan application has been approved today
C22: with the following terms and conditions, to wit;
C24: Amount | E24: : | F24: ='COMPUTATION SHEET'!AA40 -> 165400
C25: Tenor | E25: : | F25: ='COMPUTATION SHEET'!AC40 -> 48 | G25: Months
C26: Interest Rate | E26: : | F26: ='COMPUTATION SHEET'!AB40 -> 0.1581 | G26: Per Annum
C27: Availability | E27: : | F27: 30 | G27: Days
C28: Others | E28: : | F28: 1. Payment of processing fee of 1% of loan amount with max. of P1,500.00 deducted from loan proceeds
F29: 2. GRT for all other fees and charges for the account of the borrower
C31: Should you need for more clarification, please feel free to visit our branch or call our Relationship Officer,
C32: Ms. Janice B. Solayao at Telephone No. (055) 251-2046.
C34: Thank you.
I37: Very truly yours,
I41: MGR. HELBERT ANTOINE A. ACHAY
I42: Branch Head

Sheet 10
F5: Development Bank of the Philippines
I9: =NOW() -> 46084.283
C13: =CONCATENATE('INPUT FIELDS'!BL8," ",'INPUT FIELDS'!BL9," ",'INPUT FIELDS'!BL7) -> RUBIA ABARCAR GONZALES
C14: LGU Province of Samar
C15: Catbalogan City, Samar
C18: Dear Mr./Ms. | D18: =CONCATENATE(PROPER('INPUT FIELDS'!BL7),":") -> Gonzales:
C21: We are glad to inform that your salary loan application has been approved today
C22: with the following terms and conditions, to wit;
C24: Amount | E24: : | F24: ='COMPUTATION SHEET'!AA42 -> 148900
C25: Tenor | E25: : | F25: ='COMPUTATION SHEET'!AC42 -> 48 | G25: Months
C26: Interest Rate | E26: : | F26: ='COMPUTATION SHEET'!AB42 -> 0.1581 | G26: Per Annum
C27: Availability | E27: : | F27: 30 | G27: Days
C28: Others | E28: : | F28: 1. Payment of processing fee of 1% of loan amount with max. of P1,500.00 deducted from loan proceeds
F29: 2. GRT for all other fees and charges for the account of the borrower
C31: Should you need for more clarification, please feel free to visit our branch or call our Relationship Officer,
C32: Ms. Janice B. Solayao at Telephone No. (055) 251-2046.
C34: Thank you.
I37: Very truly yours,
I41: MGR. HELBERT ANTOINE A. ACHAY
I42: Branch Head

Sheet 11
F5: Development Bank of the Philippines
I9: =NOW() -> 46084.283
C13: =CONCATENATE('INPUT FIELDS'!BN8," ",'INPUT FIELDS'!BN9," ",'INPUT FIELDS'!BN7) -> DOMINGO JR JADLOC ARCALES
C14: LGU Province of Samar
C15: Catbalogan City, Samar
C18: Dear Mr./Ms. | D18: =CONCATENATE(PROPER('INPUT FIELDS'!BN7),":") -> Arcales:
C21: We are glad to inform that your salary loan application has been approved today
C22: with the following terms and conditions, to wit;
C24: Amount | E24: : | F24: ='COMPUTATION SHEET'!AA44 -> 188700
C25: Tenor | E25: : | F25: ='COMPUTATION SHEET'!AC44 -> 48 | G25: Months
C26: Interest Rate | E26: : | F26: ='COMPUTATION SHEET'!AB44 -> 0.1581 | G26: Per Annum
C27: Availability | E27: : | F27: 30 | G27: Days
C28: Others | E28: : | F28: 1. Payment of processing fee of 1% of loan amount with max. of P1,500.00 deducted from loan proceeds
F29: 2. GRT for all other fees and charges for the account of the borrower
C31: Should you need for more clarification, please feel free to visit our branch or call our Relationship Officer,
C32: Ms. Janice B. Solayao at Telephone No. (055) 251-2046.
C34: Thank you.
I37: Very truly yours,
I41: MGR. HELBERT ANTOINE A. ACHAY
I42: Branch Head

Sheet 12
F5: Development Bank of the Philippines
I9: =NOW() -> 46084.283
C13: =CONCATENATE('INPUT FIELDS'!BP8," ",'INPUT FIELDS'!BP9," ",'INPUT FIELDS'!BP7) -> REBECCA TILLES GACELOS
C14: LGU Province of Samar
C15: Catbalogan City, Samar
C18: Dear Mr./Ms. | D18: =CONCATENATE(PROPER('INPUT FIELDS'!BP7),":") -> Gacelos:
C21: We are glad to inform that your salary loan application has been approved today
C22: with the following terms and conditions, to wit;
C24: Amount | E24: : | F24: ='COMPUTATION SHEET'!AA46 -> 238900
C25: Tenor | E25: : | F25: ='COMPUTATION SHEET'!AC46 -> 48 | G25: Months
C26: Interest Rate | E26: : | F26: ='COMPUTATION SHEET'!AB46 -> 0.1581 | G26: Per Annum
C27: Availability | E27: : | F27: 30 | G27: Days
C28: Others | E28: : | F28: 1. Payment of processing fee of 1% of loan amount with max. of P1,500.00 deducted from loan proceeds
F29: 2. GRT for all other fees and charges for the account of the borrower
C31: Should you need for more clarification, please feel free to visit our branch or call our Relationship Officer,
C32: Ms. Janice B. Solayao at Telephone No. (055) 251-2046.
C34: Thank you.
I37: Very truly yours,
I41: MGR. HELBERT ANTOINE A. ACHAY
I42: Branch Head

Sheet 13
F5: Development Bank of the Philippines
I9: =NOW() -> 46084.283
C13: =CONCATENATE('INPUT FIELDS'!BR8," ",'INPUT FIELDS'!BR9," ",'INPUT FIELDS'!BR7) -> NARCISA CAMUIN TONELETE
C14: LGU Province of Samar
C15: Catbalogan City, Samar
C18: Dear Mr./Ms. | D18: =CONCATENATE(PROPER('INPUT FIELDS'!BR7),":") -> Tonelete:
C21: We are glad to inform that your salary loan application has been approved today
C22: with the following terms and conditions, to wit;
C24: Amount | E24: : | F24: ='COMPUTATION SHEET'!AA48 -> 321000
C25: Tenor | E25: : | F25: ='COMPUTATION SHEET'!AC48 -> 48 | G25: Months
C26: Interest Rate | E26: : | F26: ='COMPUTATION SHEET'!AB48 -> 0.1581 | G26: Per Annum
C27: Availability | E27: : | F27: 30 | G27: Days
C28: Others | E28: : | F28: 1. Payment of processing fee of 1% of loan amount with max. of P1,500.00 deducted from loan proceeds
F29: 2. GRT for all other fees and charges for the account of the borrower
C31: Should you need for more clarification, please feel free to visit our branch or call our Relationship Officer,
C32: Ms. Janice B. Solayao at Telephone No. (055) 251-2046.
C34: Thank you.
I37: Very truly yours,
I41: MGR. HELBERT ANTOINE A. ACHAY
I42: Branch Head

Sheet 14
F5: Development Bank of the Philippines
I9: =NOW() -> 46084.283
C13: =CONCATENATE('INPUT FIELDS'!BT8," ",'INPUT FIELDS'!BT9," ",'INPUT FIELDS'!BT7) -> MA WINONA CON UI GABON
C14: LGU Province of Samar
C15: Catbalogan City, Samar
C18: Dear Mr./Ms. | D18: =CONCATENATE(PROPER('INPUT FIELDS'!BT7),":") -> Gabon:
C21: We are glad to inform that your salary loan application has been approved today
C22: with the following terms and conditions, to wit;
C24: Amount | E24: : | F24: ='COMPUTATION SHEET'!AA50 -> 266300
C25: Tenor | E25: : | F25: ='COMPUTATION SHEET'!AC50 -> 48 | G25: Months
C26: Interest Rate | E26: : | F26: ='COMPUTATION SHEET'!AB50 -> 0.1581 | G26: Per Annum
C27: Availability | E27: : | F27: 30 | G27: Days
C28: Others | E28: : | F28: 1. Payment of processing fee of 1% of loan amount with max. of P1,500.00 deducted from loan proceeds
F29: 2. GRT for all other fees and charges for the account of the borrower
C31: Should you need for more clarification, please feel free to visit our branch or call our Relationship Officer,
C32: Ms. Janice B. Solayao at Telephone No. (055) 251-2046.
C34: Thank you.
I37: Very truly yours,
I41: MGR. HELBERT ANTOINE A. ACHAY
I42: Branch Head

Sheet 15
F5: Development Bank of the Philippines
I9: =NOW() -> 46084.283
C13: =CONCATENATE('INPUT FIELDS'!BV8," ",'INPUT FIELDS'!BV9," ",'INPUT FIELDS'!BV7)
C14: LGU Province of Samar
C15: Catbalogan City, Samar
C18: Dear Mr./Ms. | D18: =CONCATENATE(PROPER('INPUT FIELDS'!BV7),":") -> :
C21: We are glad to inform that your salary loan application has been approved today
C22: with the following terms and conditions, to wit;
C24: Amount | E24: : | F24: ='COMPUTATION SHEET'!AA52 -> 0
C25: Tenor | E25: : | F25: ='COMPUTATION SHEET'!AC52 -> 0 | G25: Months
C26: Interest Rate | E26: : | F26: ='COMPUTATION SHEET'!AB52 | G26: Per Annum
C27: Availability | E27: : | F27: 30 | G27: Days
C28: Others | E28: : | F28: 1. Payment of processing fee of 1% of loan amount with max. of P1,500.00 deducted from loan proceeds
F29: 2. GRT for all other fees and charges for the account of the borrower
C31: Should you need for more clarification, please feel free to visit our branch or call our Relationship Officer,
C32: Ms. Janice B. Solayao at Telephone No. (055) 251-2046.
C34: Thank you.
I37: Very truly yours,
I41: MGR. HELBERT ANTOINE A. ACHAY
I42: Branch Head

Sheet 16
F5: Development Bank of the Philippines
I9: =NOW() -> 46084.283
C13: =CONCATENATE('INPUT FIELDS'!BX8," ",'INPUT FIELDS'!BX9," ",'INPUT FIELDS'!BX7)
C14: LGU Province of Samar
C15: Catbalogan City, Samar
C18: Dear Mr./Ms. | D18: =CONCATENATE(PROPER('INPUT FIELDS'!BX7),":") -> :
C21: We are glad to inform that your salary loan application has been approved today
C22: with the following terms and conditions, to wit;
C24: Amount | E24: : | F24: ='COMPUTATION SHEET'!AA54 -> 0
C25: Tenor | E25: : | F25: ='COMPUTATION SHEET'!AC54 -> 0 | G25: Months
C26: Interest Rate | E26: : | F26: ='COMPUTATION SHEET'!AB54 | G26: Per Annum
C27: Availability | E27: : | F27: 30 | G27: Days
C28: Others | E28: : | F28: 1. Payment of processing fee of 1% of loan amount with max. of P1,500.00 deducted from loan proceeds
F29: 2. GRT for all other fees and charges for the account of the borrower
C31: Should you need for more clarification, please feel free to visit our branch or call our Relationship Officer,
C32: Ms. Janice B. Solayao at Telephone No. (055) 251-2046.
C34: Thank you.
I37: Very truly yours,
I41: MGR. HELBERT ANTOINE A. ACHAY
I42: Branch Head

Sheet 17
F5: Development Bank of the Philippines
I9: =NOW() -> 46084.283
C13: =CONCATENATE('INPUT FIELDS'!BZ8," ",'INPUT FIELDS'!BZ9," ",'INPUT FIELDS'!BZ7)
C14: LGU Province of Samar
C15: Catbalogan City, Samar
C18: Dear Mr./Ms. | D18: =CONCATENATE(PROPER('INPUT FIELDS'!BZ7),":") -> :
C21: We are glad to inform that your salary loan application has been approved today
C22: with the following terms and conditions, to wit;
C24: Amount | E24: : | F24: ='COMPUTATION SHEET'!AA56 -> 0
C25: Tenor | E25: : | F25: ='COMPUTATION SHEET'!AC56 -> 0 | G25: Months
C26: Interest Rate | E26: : | F26: ='COMPUTATION SHEET'!AB56 | G26: Per Annum
C27: Availability | E27: : | F27: 30 | G27: Days
C28: Others | E28: : | F28: 1. Payment of processing fee of 1% of loan amount with max. of P1,500.00 deducted from loan proceeds
F29: 2. GRT for all other fees and charges for the account of the borrower
C31: Should you need for more clarification, please feel free to visit our branch or call our Relationship Officer,
C32: Ms. Janice B. Solayao at Telephone No. (055) 251-2046.
C34: Thank you.
I37: Very truly yours,
I41: MGR. HELBERT ANTOINE A. ACHAY
I42: Branch Head

Sheet 18
F5: Development Bank of the Philippines
I9: =NOW() -> 46084.283
C13: =CONCATENATE('INPUT FIELDS'!CB8," ",'INPUT FIELDS'!CB9," ",'INPUT FIELDS'!CB7)
C14: LGU Province of Samar
C15: Catbalogan City, Samar
C18: Dear Mr./Ms. | D18: =CONCATENATE(PROPER('INPUT FIELDS'!CB7),":") -> :
C21: We are glad to inform that your salary loan application has been approved today
C22: with the following terms and conditions, to wit;
C24: Amount | E24: : | F24: ='COMPUTATION SHEET'!AA58 -> 0
C25: Tenor | E25: : | F25: ='COMPUTATION SHEET'!AC58 -> 0 | G25: Months
C26: Interest Rate | E26: : | F26: ='COMPUTATION SHEET'!AB58 | G26: Per Annum
